Workbook

Sheet 前7天钻石抽卡券统计
A1: 前7天钻石与抽卡券投放统计
A2: 口径：统计新手前7天可获得的钻石和抽卡券；抽卡券钻石等价按150钻石/张。
A3: 进度假设：Day7普通主线4-15、高难2-4章、无限挑战30000分、爬塔40层、竞技场1600分、大秘境7层、通行证约7级。
A4: 未纳入：商店兑换/购买消耗、竞技场赛季结算、公会随机宝箱频次、大秘境排行/积分奖励等缺少明确前7天次数的内容。
A6: 玩法 | B6: 钻石 | C6: 角色抽卡券普通 | D6: 专武抽卡券普通 | E6: 角色抽卡券限时 | F6: 专武抽卡券限时 | G6: 抽卡券合计 | H6: 钻石等价合计 | I6: 付费额外等价 | J6: 备注
A7: 7日任务 | B7: =SUMIFS($H$24:$H$999,$A$24:$A$999,$A7,$G$24:$G$999,B$6,$J$24:$J$999,"是") -> 1500 | C7: =SUMIFS($H$24:$H$999,$A$24:$A$999,$A7,$G$24:$G$999,C$6,$J$24:$J$999,"是") -> 20 | D7: =SUMIFS($H$24:$H$999,$A$24:$A$999,$A7,$G$24:$G$999,D$6,$J$24:$J$999,"是") -> 10 | E7: =SUMIFS($H$24:$H$999,$A$24:$A$999,$A7,$G$24:$G$999,E$6,$J$24:$J$999,"是") -> 0 | F7: =SUMIFS($H$24:$H$999,$A$24:$A$999,$A7,$G$24:$G$999,F$6,$J$24:$J$999,"是") -> 0 | G7: =SUM(C7:F7) -> 30 | H7: =SUMIFS($I$24:$I$999,$A$24:$A$999,$A7,$J$24:$J$999,"是") -> 8400 | I7: =SUMIFS($I$24:$I$999,$A$24:$A$999,$A7,$J$24:$J$999,"否") -> 0
A8: 主线副本 | B8: =SUMIFS($H$24:$H$999,$A$24:$A$999,$A8,$G$24:$G$999,B$6,$J$24:$J$999,"是") -> 2800 | C8: =SUMIFS($H$24:$H$999,$A$24:$A$999,$A8,$G$24:$G$999,C$6,$J$24:$J$999,"是") -> 1 | D8: =SUMIFS($H$24:$H$999,$A$24:$A$999,$A8,$G$24:$G$999,D$6,$J$24:$J$999,"是") -> 0 | E8: =SUMIFS($H$24:$H$999,$A$24:$A$999,$A8,$G$24:$G$999,E$6,$J$24:$J$999,"是") -> 15 | F8: =SUMIFS($H$24:$H$999,$A$24:$A$999,$A8,$G$24:$G$999,F$6,$J$24:$J$999,"是") -> 0 | G8: =SUM(C8:F8) -> 16 | H8: =SUMIFS($I$24:$I$999,$A$24:$A$999,$A8,$J$24:$J$999,"是") -> #REF! | I8: =SUMIFS($I$24:$I$999,$A$24:$A$999,$A8,$J$24:$J$999,"否") -> 0
A9: 任务 | B9: =SUMIFS($H$24:$H$999,$A$24:$A$999,$A9,$G$24:$G$999,B$6,$J$24:$J$999,"是") -> 1880 | C9: =SUMIFS($H$24:$H$999,$A$24:$A$999,$A9,$G$24:$G$999,C$6,$J$24:$J$999,"是") -> 0 | D9: =SUMIFS($H$24:$H$999,$A$24:$A$999,$A9,$G$24:$G$999,D$6,$J$24:$J$999,"是") -> 0 | E9: =SUMIFS($H$24:$H$999,$A$24:$A$999,$A9,$G$24:$G$999,E$6,$J$24:$J$999,"是") -> 40 | F9: =SUMIFS($H$24:$H$999,$A$24:$A$999,$A9,$G$24:$G$999,F$6,$J$24:$J$999,"是") -> 10 | G9: =SUM(C9:F9) -> 50 | H9: =SUMIFS($I$24:$I$999,$A$24:$A$999,$A9,$J$24:$J$999,"是") -> 9380 | I9: =SUMIFS($I$24:$I$999,$A$24:$A$999,$A9,$J$24:$J$999,"否") -> 0
A10: 大秘境 | B10: =SUMIFS($H$24:$H$999,$A$24:$A$999,$A10,$G$24:$G$999,B$6,$J$24:$J$999,"是") -> 0 | C10: =SUMIFS($H$24:$H$999,$A$24:$A$999,$A10,$G$24:$G$999,C$6,$J$24:$J$999,"是") -> 0 | D10: =SUMIFS($H$24:$H$999,$A$24:$A$999,$A10,$G$24:$G$999,D$6,$J$24:$J$999,"是") -> 0 | E10: =SUMIFS($H$24:$H$999,$A$24:$A$999,$A10,$G$24:$G$999,E$6,$J$24:$J$999,"是") -> 7 | F10: =SUMIFS($H$24:$H$999,$A$24:$A$999,$A10,$G$24:$G$999,F$6,$J$24:$J$999,"是") -> 1 | G10: =SUM(C10:F10) -> 8 | H10: =SUMIFS($I$24:$I$999,$A$24:$A$999,$A10,$J$24:$J$999,"是") -> 1200 | I10: =SUMIFS($I$24:$I$999,$A$24:$A$999,$A10,$J$24:$J$999,"否") -> 0
A11: 无限挑战 | B11: =SUMIFS($H$24:$H$999,$A$24:$A$999,$A11,$G$24:$G$999,B$6,$J$24:$J$999,"是") -> #REF! | C11: =SUMIFS($H$24:$H$999,$A$24:$A$999,$A11,$G$24:$G$999,C$6,$J$24:$J$999,"是") -> #REF! | D11: =SUMIFS($H$24:$H$999,$A$24:$A$999,$A11,$G$24:$G$999,D$6,$J$24:$J$999,"是") -> 0 | E11: =SUMIFS($H$24:$H$999,$A$24:$A$999,$A11,$G$24:$G$999,E$6,$J$24:$J$999,"是") -> #REF! | F11: =SUMIFS($H$24:$H$999,$A$24:$A$999,$A11,$G$24:$G$999,F$6,$J$24:$J$999,"是") -> 0 | G11: =SUM(C11:F11) -> #REF! | H11: =SUMIFS($I$24:$I$999,$A$24:$A$999,$A11,$J$24:$J$999,"是") -> #REF! | I11: =SUMIFS($I$24:$I$999,$A$24:$A$999,$A11,$J$24:$J$999,"否") -> 0
A12: 爬塔 | B12: =SUMIFS($H$24:$H$999,$A$24:$A$999,$A12,$G$24:$G$999,B$6,$J$24:$J$999,"是") -> 0 | C12: =SUMIFS($H$24:$H$999,$A$24:$A$999,$A12,$G$24:$G$999,C$6,$J$24:$J$999,"是") -> 0 | D12: =SUMIFS($H$24:$H$999,$A$24:$A$999,$A12,$G$24:$G$999,D$6,$J$24:$J$999,"是") -> 0 | E12: =SUMIFS($H$24:$H$999,$A$24:$A$999,$A12,$G$24:$G$999,E$6,$J$24:$J$999,"是") -> 0 | F12: =SUMIFS($H$24:$H$999,$A$24:$A$999,$A12,$G$24:$G$999,F$6,$J$24:$J$999,"是") -> 0 | G12: =SUM(C12:F12) -> 0 | H12: =SUMIFS($I$24:$I$999,$A$24:$A$999,$A12,$J$24:$J$999,"是") -> 9003600 | I12: =SUMIFS($I$24:$I$999,$A$24:$A$999,$A12,$J$24:$J$999,"否") -> 0
A13: 竞技场 | B13: =SUMIFS($H$24:$H$999,$A$24:$A$999,$A13,$G$24:$G$999,B$6,$J$24:$J$999,"是") -> 600 | C13: =SUMIFS($H$24:$H$999,$A$24:$A$999,$A13,$G$24:$G$999,C$6,$J$24:$J$999,"是") -> 0 | D13: =SUMIFS($H$24:$H$999,$A$24:$A$999,$A13,$G$24:$G$999,D$6,$J$24:$J$999,"是") -> 0 | E13: =SUMIFS($H$24:$H$999,$A$24:$A$999,$A13,$G$24:$G$999,E$6,$J$24:$J$999,"是") -> 0 | F13: =SUMIFS($H$24:$H$999,$A$24:$A$999,$A13,$G$24:$G$999,F$6,$J$24:$J$999,"是") -> 0 | G13: =SUM(C13:F13) -> 0 | H13: =SUMIFS($I$24:$I$999,$A$24:$A$999,$A13,$J$24:$J$999,"是") -> #N/A | I13: =SUMIFS($I$24:$I$999,$A$24:$A$999,$A13,$J$24:$J$999,"否") -> 0
A14: 签到 | B14: =SUMIFS($H$24:$H$999,$A$24:$A$999,$A14,$G$24:$G$999,B$6,$J$24:$J$999,"是") -> 150 | C14: =SUMIFS($H$24:$H$999,$A$24:$A$999,$A14,$G$24:$G$999,C$6,$J$24:$J$999,"是") -> 2 | D14: =SUMIFS($H$24:$H$999,$A$24:$A$999,$A14,$G$24:$G$999,D$6,$J$24:$J$999,"是") -> 0 | E14: =SUMIFS($H$24:$H$999,$A$24:$A$999,$A14,$G$24:$G$999,E$6,$J$24:$J$999,"是") -> 0 | F14: =SUMIFS($H$24:$H$999,$A$24:$A$999,$A14,$G$24:$G$999,F$6,$J$24:$J$999,"是") -> 0 | G14: =SUM(C14:F14) -> 2 | H14: =SUMIFS($I$24:$I$999,$A$24:$A$999,$A14,$J$24:$J$999,"是") -> 450 | I14: =SUMIFS($I$24:$I$999,$A$24:$A$999,$A14,$J$24:$J$999,"否") -> 0
A15: 通行证 | B15: =SUMIFS($H$24:$H$999,$A$24:$A$999,$A15,$G$24:$G$999,B$6,$J$24:$J$999,"是") -> 0 | C15: =SUMIFS($H$24:$H$999,$A$24:$A$999,$A15,$G$24:$G$999,C$6,$J$24:$J$999,"是") -> 0 | D15: =SUMIFS($H$24:$H$999,$A$24:$A$999,$A15,$G$24:$G$999,D$6,$J$24:$J$999,"是") -> 0 | E15: =SUMIFS($H$24:$H$999,$A$24:$A$999,$A15,$G$24:$G$999,E$6,$J$24:$J$999,"是") -> 0 | F15: =SUMIFS($H$24:$H$999,$A$24:$A$999,$A15,$G$24:$G$999,F$6,$J$24:$J$999,"是") -> 0 | G15: =SUM(C15:F15) -> 0 | H15: =SUMIFS($I$24:$I$999,$A$24:$A$999,$A15,$J$24:$J$999,"是") -> 0 | I15: =SUMIFS($I$24:$I$999,$A$24:$A$999,$A15,$J$24:$J$999,"否") -> 680
A16: 高难主线 | B16: =SUMIFS($H$24:$H$999,$A$24:$A$999,$A16,$G$24:$G$999,B$6,$J$24:$J$999,"是") -> 750 | C16: =SUMIFS($H$24:$H$999,$A$24:$A$999,$A16,$G$24:$G$999,C$6,$J$24:$J$999,"是") -> 0 | D16: =SUMIFS($H$24:$H$999,$A$24:$A$999,$A16,$G$24:$G$999,D$6,$J$24:$J$999,"是") -> 0 | E16: =SUMIFS($H$24:$H$999,$A$24:$A$999,$A16,$G$24:$G$999,E$6,$J$24:$J$999,"是") -> 15 | F16: =SUMIFS($H$24:$H$999,$A$24:$A$999,$A16,$G$24:$G$999,F$6,$J$24:$J$999,"是") -> 0 | G16: =SUM(C16:F16) -> 15 | H16: =SUMIFS($I$24:$I$999,$A$24:$A$999,$A16,$J$24:$J$999,"是") -> 6600 | I16: =SUMIFS($I$24:$I$999,$A$24:$A$999,$A16,$J$24:$J$999,"否") -> 0
A17: 免费口径合计 | B17: =SUM(B7:B16) -> #REF! | C17: =SUM(C7:C16) -> #REF! | D17: =SUM(D7:D16) -> 10 | E17: =SUM(E7:E16) -> #REF! | F17: =SUM(F7:F16) -> 11 | G17: =SUM(G7:G16) -> #REF! | H17: =SUM(H7:H16) -> #REF! | I17: =SUM(I7:I16) -> 680
A23: 玩法 | B23: 口径/模块 | C23: 来源页签 | D23: 来源位置 | E23: 原始道具 | F23: 倍数/次数 | G23: 统计道具 | H23: 前7天数量 | I23: 钻石等价 | J23: 计入免费口径 | K23: 备注
A24: 7日任务 | B24: 任务奖励 | C24: 7日任务 | D24: H16/I16 | E24: ='7日任务'!I16 -> 体力药 | F24: 1 | G24: =IF(E24="钻石","钻石",IF(ISNUMBER(SEARCH("角色抽卡券限时",E24)),"角色抽卡券限时",IF(ISNUMBER(SEARCH("专武抽卡券限时",E24)),"专武抽卡券限时",IF(ISNUMBER(SEARCH("角色抽卡券",E24)),"角色抽卡券普通",IF(ISNUMBER(SEARCH("专武抽卡券",E24)),"专武抽卡券普通",""))))) | H24: ='7日任务'!J16*F24 -> 2 | I24: =IF(G24="钻石",H24,H24*150) -> 300 | J24: 是 | K24: Day1-Day7全部任务
A25: 7日任务 | B25: 任务奖励 | C25: 7日任务 | D25: H25/I25 | E25: ='7日任务'!I27 -> 体力药 | F25: 1 | G25: =IF(E25="钻石","钻石",IF(ISNUMBER(SEARCH("角色抽卡券限时",E25)),"角色抽卡券限时",IF(ISNUMBER(SEARCH("专武抽卡券限时",E25)),"专武抽卡券限时",IF(ISNUMBER(SEARCH("角色抽卡券",E25)),"角色抽卡券普通",IF(ISNUMBER(SEARCH("专武抽卡券",E25)),"专武抽卡券普通",""))))) | H25: ='7日任务'!J27*F25 -> 2 | I25: =IF(G25="钻石",H25,H25*150) -> 300 | J25: 是 | K25: Day1-Day7全部任务
A26: 7日任务 | B26: 任务奖励 | C26: 7日任务 | D26: H35/I35 | E26: ='7日任务'!I39 -> 体力药 | F26: 1 | G26: =IF(E26="钻石","钻石",IF(ISNUMBER(SEARCH("角色抽卡券限时",E26)),"角色抽卡券限时",IF(ISNUMBER(SEARCH("专武抽卡券限时",E26)),"专武抽卡券限时",IF(ISNUMBER(SEARCH("角色抽卡券",E26)),"角色抽卡券普通",IF(ISNUMBER(SEARCH("专武抽卡券",E26)),"专武抽卡券普通",""))))) | H26: ='7日任务'!J39*F26 -> 2 | I26: =IF(G26="钻石",H26,H26*150) -> 300 | J26: 是 | K26: Day1-Day7全部任务
A27: 7日任务 | B27: 任务奖励 | C27: 7日任务 | D27: H45/I45 | E27: ='7日任务'!I51 -> 体力药 | F27: 1 | G27: =IF(E27="钻石","钻石",IF(ISNUMBER(SEARCH("角色抽卡券限时",E27)),"角色抽卡券限时",IF(ISNUMBER(SEARCH("专武抽卡券限时",E27)),"专武抽卡券限时",IF(ISNUMBER(SEARCH("角色抽卡券",E27)),"角色抽卡券普通",IF(ISNUMBER(SEARCH("专武抽卡券",E27)),"专武抽卡券普通",""))))) | H27: ='7日任务'!J51*F27 -> 2 | I27: =IF(G27="钻石",H27,H27*150) -> 300 | J27: 是 | K27: Day1-Day7全部任务
A28: 7日任务 | B28: 任务奖励 | C28: 7日任务 | D28: H55/I55 | E28: ='7日任务'!I63 -> 体力药 | F28: 1 | G28: =IF(E28="钻石","钻石",IF(ISNUMBER(SEARCH("角色抽卡券限时",E28)),"角色抽卡券限时",IF(ISNUMBER(SEARCH("专武抽卡券限时",E28)),"专武抽卡券限时",IF(ISNUMBER(SEARCH("角色抽卡券",E28)),"角色抽卡券普通",IF(ISNUMBER(SEARCH("专武抽卡券",E28)),"专武抽卡券普通",""))))) | H28: ='7日任务'!J63*F28 -> 2 | I28: =IF(G28="钻石",H28,H28*150) -> 300 | J28: 是 | K28: Day1-Day7全部任务
A29: 7日任务 | B29: 任务奖励 | C29: 7日任务 | D29: H65/I65 | E29: ='7日任务'!I75 -> 体力药 | F29: 1 | G29: =IF(E29="钻石","钻石",IF(ISNUMBER(SEARCH("角色抽卡券限时",E29)),"角色抽卡券限时",IF(ISNUMBER(SEARCH("专武抽卡券限时",E29)),"专武抽卡券限时",IF(ISNUMBER(SEARCH("角色抽卡券",E29)),"角色抽卡券普通",IF(ISNUMBER(SEARCH("专武抽卡券",E29)),"专武抽卡券普通",""))))) | H29: ='7日任务'!J75*F29 -> 2 | I29: =IF(G29="钻石",H29,H29*150) -> 300 | J29: 是 | K29: Day1-Day7全部任务
A30: 7日任务 | B30: 任务奖励 | C30: 7日任务 | D30: H75/I75 | E30: ='7日任务'!I87 -> 体力药 | F30: 1 | G30: =IF(E30="钻石","钻石",IF(ISNUMBER(SEARCH("角色抽卡券限时",E30)),"角色抽卡券限时",IF(ISNUMBER(SEARCH("专武抽卡券限时",E30)),"专武抽卡券限时",IF(ISNUMBER(SEARCH("角色抽卡券",E30)),"角色抽卡券普通",IF(ISNUMBER(SEARCH("专武抽卡券",E30)),"专武抽卡券普通",""))))) | H30: ='7日任务'!J87*F30 -> 2 | I30: =IF(G30="钻石",H30,H30*150) -> 300 | J30: 是 | K30: Day1-Day7全部任务
A31: 7日任务 | B31: 阶段奖励 | C31: 7日任务 | D31: B91/C91 | E31: ='7日任务'!B105 -> 角色抽卡券普通 | F31: 1 | G31: =IF(E31="钻石","钻石",IF(ISNUMBER(SEARCH("角色抽卡券限时",E31)),"角色抽卡券限时",IF(ISNUMBER(SEARCH("专武抽卡券限时",E31)),"专武抽卡券限时",IF(ISNUMBER(SEARCH("角色抽卡券",E31)),"角色抽卡券普通",IF(ISNUMBER(SEARCH("专武抽卡券",E31)),"专武抽卡券普通",""))))) -> 角色抽卡券普通 | H31: ='7日任务'!C105*F31 -> 10 | I31: =IF(G31="钻石",H31,H31*150) -> 1500 | J31: 是 | K31: 按560积分可领取
A32: 7日任务 | B32: 阶段奖励 | C32: 7日任务 | D32: B92/C92 | E32: ='7日任务'!B106 -> 角色抽卡券普通 | F32: 1 | G32: =IF(E32="钻石","钻石",IF(ISNUMBER(SEARCH("角色抽卡券限时",E32)),"角色抽卡券限时",IF(ISNUMBER(SEARCH("专武抽卡券限时",E32)),"专武抽卡券限时",IF(ISNUMBER(SEARCH("角色抽卡券",E32)),"角色抽卡券普通",IF(ISNUMBER(SEARCH("专武抽卡券",E32)),"专武抽卡券普通",""))))) -> 角色抽卡券普通 | H32: ='7日任务'!C106*F32 -> 10 | I32: =IF(G32="钻石",H32,H32*150) -> 1500 | J32: 是 | K32: 按560积分可领取
A33: 7日任务 | B33: 阶段奖励 | C33: 7日任务 | D33: B93/C93 | E33: ='7日任务'!B107 -> 专武抽卡券普通 | F33: 1 | G33: =IF(E33="钻石","钻石",IF(ISNUMBER(SEARCH("角色抽卡券限时",E33)),"角色抽卡券限时",IF(ISNUMBER(SEARCH("专武抽卡券限时",E33)),"专武抽卡券限时",IF(ISNUMBER(SEARCH("角色抽卡券",E33)),"角色抽卡券普通",IF(ISNUMBER(SEARCH("专武抽卡券",E33)),"专武抽卡券普通",""))))) -> 专武抽卡券普通 | H33: ='7日任务'!C107*F33 -> 10 | I33: =IF(G33="钻石",H33,H33*150) -> 1500 | J33: 是 | K33: 按560积分可领取
A34: 7日任务 | B34: 阶段奖励 | C34: 7日任务 | D34: B94/C94 | E34: ='7日任务'!B108 -> SSR角色 | F34: 1 | G34: =IF(E34="钻石","钻石",IF(ISNUMBER(SEARCH("角色抽卡券限时",E34)),"角色抽卡券限时",IF(ISNUMBER(SEARCH("专武抽卡券限时",E34)),"专武抽卡券限时",IF(ISNUMBER(SEARCH("角色抽卡券",E34)),"角色抽卡券普通",IF(ISNUMBER(SEARCH("专武抽卡券",E34)),"专武抽卡券普通",""))))) | H34: ='7日任务'!C108*F34 -> 1 | I34: =IF(G34="钻石",H34,H34*150) -> 150 | J34: 是 | K34: 按560积分可领取
A35: 7日任务 | B35: 阶段奖励 | C35: 7日任务 | D35: B96/C96 | E35: ='7日任务'!B110 -> SSR专武 | F35: 1 | G35: =IF(E35="钻石","钻石",IF(ISNUMBER(SEARCH("角色抽卡券限时",E35)),"角色抽卡券限时",IF(ISNUMBER(SEARCH("专武抽卡券限时",E35)),"专武抽卡券限时",IF(ISNUMBER(SEARCH("角色抽卡券",E35)),"角色抽卡券普通",IF(ISNUMBER(SEARCH("专武抽卡券",E35)),"专武抽卡券普通",""))))) | H35: ='7日任务'!C110*F35 -> 1 | I35: =IF(G35="钻石",H35,H35*150) -> 150 | J35: 是 | K35: 按560积分可领取
A36: 7日任务 | B36: 阶段奖励 | C36: 7日任务 | D36: D91/E91 | E36: ='7日任务'!D105 -> 钻石 | F36: 1 | G36: =IF(E36="钻石","钻石",IF(ISNUMBER(SEARCH("角色抽卡券限时",E36)),"角色抽卡券限时",IF(ISNUMBER(SEARCH("专武抽卡券限时",E36)),"专武抽卡券限时",IF(ISNUMBER(SEARCH("角色抽卡券",E36)),"角色抽卡券普通",IF(ISNUMBER(SEARCH("专武抽卡券",E36)),"专武抽卡券普通",""))))) -> 钻石 | H36: ='7日任务'!E105*F36 -> 500 | I36: =IF(G36="钻石",H36,H36*150) -> 500 | J36: 是 | K36: 按560积分可领取
A37: 7日任务 | B37: 阶段奖励 | C37: 7日任务 | D37: D92/E92 | E37: ='7日任务'!D106 -> 钻石 | F37: 1 | G37: =IF(E37="钻石","钻石",IF(ISNUMBER(SEARCH("角色抽卡券限时",E37)),"角色抽卡券限时",IF(ISNUMBER(SEARCH("专武抽卡券限时",E37)),"专武抽卡券限时",IF(ISNUMBER(SEARCH("角色抽卡券",E37)),"角色抽卡券普通",IF(ISNUMBER(SEARCH("专武抽卡券",E37)),"专武抽卡券普通",""))))) -> 钻石 | H37: ='7日任务'!E106*F37 -> 500 | I37: =IF(G37="钻石",H37,H37*150) -> 500 | J37: 是 | K37: 按560积分可领取
A38: 7日任务 | B38: 阶段奖励 | C38: 7日任务 | D38: D93/E93 | E38: ='7日任务'!D107 -> 钻石 | F38: 1 | G38: =IF(E38="钻石","钻石",IF(ISNUMBER(SEARCH("角色抽卡券限时",E38)),"角色抽卡券限时",IF(ISNUMBER(SEARCH("专武抽卡券限时",E38)),"专武抽卡券限时",IF(ISNUMBER(SEARCH("角色抽卡券",E38)),"角色抽卡券普通",IF(ISNUMBER(SEARCH("专武抽卡券",E38)),"专武抽卡券普通",""))))) -> 钻石 | H38: ='7日任务'!E107*F38 -> 500 | I38: =IF(G38="钻石",H38,H38*150) -> 500 | J38: 是 | K38: 按560积分可领取
A39: 7日任务 | B39: 阶段奖励 | C39: 7日任务 | D39: D94/E94 | E39: ='7日任务'!D108 -> 0 | F39: 1 | G39: =IF(E39="钻石","钻石",IF(ISNUMBER(SEARCH("角色抽卡券限时",E39)),"角色抽卡券限时",IF(ISNUMBER(SEARCH("专武抽卡券限时",E39)),"专武抽卡券限时",IF(ISNUMBER(SEARCH("角色抽卡券",E39)),"角色抽卡券普通",IF(ISNUMBER(SEARCH("专武抽卡券",E39)),"专武抽卡券普通",""))))) | H39: ='7日任务'!E108*F39 -> 0 | I39: =IF(G39="钻石",H39,H39*150) -> 0 | J39: 是 | K39: 按560积分可领取
A40: 7日任务 | B40: 阶段奖励 | C40: 7日任务 | D40: D96/E96 | E40: ='7日任务'!D110 -> 0 | F40: 1 | G40: =IF(E40="钻石","钻石",IF(ISNUMBER(SEARCH("角色抽卡券限时",E40)),"角色抽卡券限时",IF(ISNUMBER(SEARCH("专武抽卡券限时",E40)),"专武抽卡券限时",IF(ISNUMBER(SEARCH("角色抽卡券",E40)),"角色抽卡券普通",IF(ISNUMBER(SEARCH("专武抽卡券",E40)),"专武抽卡券普通",""))))) | H40: ='7日任务'!E110*F40 -> 0 | I40: =IF(G40="钻石",H40,H40*150) -> 0 | J40: 是 | K40: 按560积分可领取
A41: 主线副本 | B41: 首周可达一次性奖励 | C41: 主线副本 | D41: AC10/AD10 | E41: =主线副本!AC10 -> 钻石 | F41: 1 | G41: =IF(E41="钻石","钻石",IF(ISNUMBER(SEARCH("角色抽卡券限时",E41)),"角色抽卡券限时",IF(ISNUMBER(SEARCH("专武抽卡券限时",E41)),"专武抽卡券限时",IF(ISNUMBER(SEARCH("角色抽卡券",E41)),"角色抽卡券普通",IF(ISNUMBER(SEARCH("专武抽卡券",E41)),"专武抽卡券普通",""))))) -> 钻石 | H41: =主线副本!AD10*F41 -> 50 | I41: =IF(G41="钻石",H41,H41*150) -> 50 | J41: 是 | K41: Day7到普通主线4-15
A42: 主线副本 | B42: 首周可达一次性奖励 | C42: 主线副本 | D42: AC11/AD11 | E42: =主线副本!AC11 -> 钻石 | F42: 1 | G42: =IF(E42="钻石","钻石",IF(ISNUMBER(SEARCH("角色抽卡券限时",E42)),"角色抽卡券限时",IF(ISNUMBER(SEARCH("专武抽卡券限时",E42)),"专武抽卡券限时",IF(ISNUMBER(SEARCH("角色抽卡券",E42)),"角色抽卡券普通",IF(ISNUMBER(SEARCH("专武抽卡券",E42)),"专武抽卡券普通",""))))) -> 钻石 | H42: =主线副本!AD11*F42 -> 50 | I42: =IF(G42="钻石",H42,H42*150) -> 50 | J42: 是 | K42: Day7到普通主线4-15
A43: 主线副本 | B43: 首周可达一次性奖励 | C43: 主线副本 | D43: AC12/AD12 | E43: =主线副本!AC12 -> 钻石 | F43: 1 | G43: =IF(E43="钻石","钻石",IF(ISNUMBER(SEARCH("角色抽卡券限时",E43)),"角色抽卡券限时",IF(ISNUMBER(SEARCH("专武抽卡券限时",E43)),"专武抽卡券限时",IF(ISNUMBER(SEARCH("角色抽卡券",E43)),"角色抽卡券普通",IF(ISNUMBER(SEARCH("专武抽卡券",E43)),"专武抽卡券普通",""))))) -> 钻石 | H43: =主线副本!AD12*F43 -> 150 | I43: =IF(G43="钻石",H43,H43*150) -> 150 | J43: 是 | K43: Day7到普通主线4-15
A44: 主线副本 | B44: 首周可达一次性奖励 | C44: 主线副本 | D44: AC13/AD13 | E44: =主线副本!AC13 -> 钻石 | F44: 1 | G44: =IF(E44="钻石","钻石",IF(ISNUMBER(SEARCH("角色抽卡券限时",E44)),"角色抽卡券限时",IF(ISNUMBER(SEARCH("专武抽卡券限时",E44)),"专武抽卡券限时",IF(ISNUMBER(SEARCH("角色抽卡券",E44)),"角色抽卡券普通",IF(ISNUMBER(SEARCH("专武抽卡券",E44)),"专武抽卡券普通",""))))) -> 钻石 | H44: =主线副本!AD13*F44 -> 50 | I44: =IF(G44="钻石",H44,H44*150) -> 50 | J44: 是 | K44: Day7到普通主线4-15
A45: 主线副本 | B45: 首周可达一次性奖励 | C45: 主线副本 | D45: AC14/AD14 | E45: =主线副本!AC14 -> 钻石 | F45: 1 | G45: =IF(E45="钻石","钻石",IF(ISNUMBER(SEARCH("角色抽卡券限时",E45)),"角色抽卡券限时",IF(ISNUMBER(SEARCH("专武抽卡券限时",E45)),"专武抽卡券限时",IF(ISNUMBER(SEARCH("角色抽卡券",E45)),"角色抽卡券普通",IF(ISNUMBER(SEARCH("专武抽卡券",E45)),"专武抽卡券普通",""))))) -> 钻石 | H45: =主线副本!AD14*F45 -> 50 | I45: =IF(G45="钻石",H45,H45*150) -> 50 | J45: 是 | K45: Day7到普通主线4-15
A46: 主线副本 | B46: 首周可达一次性奖励 | C46: 主线副本 | D46: AC15/AD15 | E46: =主线副本!AC15 -> 钻石 | F46: 1 | G46: =IF(E46="钻石","钻石",IF(ISNUMBER(SEARCH("角色抽卡券限时",E46)),"角色抽卡券限时",IF(ISNUMBER(SEARCH("专武抽卡券限时",E46)),"专武抽卡券限时",IF(ISNUMBER(SEARCH("角色抽卡券",E46)),"角色抽卡券普通",IF(ISNUMBER(SEARCH("专武抽卡券",E46)),"专武抽卡券普通",""))))) -> 钻石 | H46: =主线副本!AD15*F46 -> 50 | I46: =IF(G46="钻石",H46,H46*150) -> 50 | J46: 是 | K46: Day7到普通主线4-15
A47: 主线副本 | B47: 首周可达一次性奖励 | C47: 主线副本 | D47: AC16/AD16 | E47: =主线副本!AC16 -> 钻石 | F47: 1 | G47: =IF(E47="钻石","钻石",IF(ISNUMBER(SEARCH("角色抽卡券限时",E47)),"角色抽卡券限时",IF(ISNUMBER(SEARCH("专武抽卡券限时",E47)),"专武抽卡券限时",IF(ISNUMBER(SEARCH("角色抽卡券",E47)),"角色抽卡券普通",IF(ISNUMBER(SEARCH("专武抽卡券",E47)),"专武抽卡券普通",""))))) -> 钻石 | H47: =主线副本!AD16*F47 -> 50 | I47: =IF(G47="钻石",H47,H47*150) -> 50 | J47: 是 | K47: Day7到普通主线4-15
A48: 主线副本 | B48: 首周可达一次性奖励 | C48: 主线副本 | D48: AC17/AD17 | E48: =主线副本!AC17 -> 钻石 | F48: 1 | G48: =IF(E48="钻石","钻石",IF(ISNUMBER(SEARCH("角色抽卡券限时",E48)),"角色抽卡券限时",IF(ISNUMBER(SEARCH("专武抽卡券限时",E48)),"专武抽卡券限时",IF(ISNUMBER(SEARCH("角色抽卡券",E48)),"角色抽卡券普通",IF(ISNUMBER(SEARCH("专武抽卡券",E48)),"专武抽卡券普通",""))))) -> 钻石 | H48: =主线副本!AD17*F48 -> 150 | I48: =IF(G48="钻石",H48,H48*150) -> 150 | J48: 是 | K48: Day7到普通主线4-15
A49: 主线副本 | B49: 首周可达一次性奖励 | C49: 主线副本 | D49: AC18/AD18 | E49: =主线副本!#REF! -> #REF! | F49: 1 | G49: =IF(E49="钻石","钻石",IF(ISNUMBER(SEARCH("角色抽卡券限时",E49)),"角色抽卡券限时",IF(ISNUMBER(SEARCH("专武抽卡券限时",E49)),"专武抽卡券限时",IF(ISNUMBER(SEARCH("角色抽卡券",E49)),"角色抽卡券普通",IF(ISNUMBER(SEARCH("专武抽卡券",E49)),"专武抽卡券普通",""))))) -> #REF! | H49: =主线副本!#REF!*F49 -> #REF! | I49: =IF(G49="钻石",H49,H49*150) -> #REF! | J49: 是 | K49: Day7到普通主线4-15
A50: 主线副本 | B50: 首周可达一次性奖励 | C50: 主线副本 | D50: AC19/AD19 | E50: =主线副本!AC18 -> 钻石 | F50: 1 | G50: =IF(E50="钻石","钻石",IF(ISNUMBER(SEARCH("角色抽卡券限时",E50)),"角色抽卡券限时",IF(ISNUMBER(SEARCH("专武抽卡券限时",E50)),"专武抽卡券限时",IF(ISNUMBER(SEARCH("角色抽卡券",E50)),"角色抽卡券普通",IF(ISNUMBER(SEARCH("专武抽卡券",E50)),"专武抽卡券普通",""))))) -> 钻石 | H50: =主线副本!AD18*F50 -> 50 | I50: =IF(G50="钻石",H50,H50*150) -> 50 | J50: 是 | K50: Day7到普通主线4-15
A51: 主线副本 | B51: 首周可达一次性奖励 | C51: 主线副本 | D51: AC20/AD20 | E51: =主线副本!AC19 -> 钻石 | F51: 1 | G51: =IF(E51="钻石","钻石",IF(ISNUMBER(SEARCH("角色抽卡券限时",E51)),"角色抽卡券限时",IF(ISNUMBER(SEARCH("专武抽卡券限时",E51)),"专武抽卡券限时",IF(ISNUMBER(SEARCH("角色抽卡券",E51)),"角色抽卡券普通",IF(ISNUMBER(SEARCH("专武抽卡券",E51)),"专武抽卡券普通",""))))) -> 钻石 | H51: =主线副本!AD19*F51 -> 50 | I51: =IF(G51="钻石",H51,H51*150) -> 50 | J51: 是 | K51: Day7到普通主线4-15
A52: 主线副本 | B52: 首周可达一次性奖励 | C52: 主线副本 | D52: AC21/AD21 | E52: =主线副本!AC20 -> 钻石 | F52: 1 | G52: =IF(E52="钻石","钻石",IF(ISNUMBER(SEARCH("角色抽卡券限时",E52)),"角色抽卡券限时",IF(ISNUMBER(SEARCH("专武抽卡券限时",E52)),"专武抽卡券限时",IF(ISNUMBER(SEARCH("角色抽卡券",E52)),"角色抽卡券普通",IF(ISNUMBER(SEARCH("专武抽卡券",E52)),"专武抽卡券普通",""))))) -> 钻石 | H52: =主线副本!AD20*F52 -> 50 | I52: =IF(G52="钻石",H52,H52*150) -> 50 | J52: 是 | K52: Day7到普通主线4-15
A53: 主线副本 | B53: 首周可达一次性奖励 | C53: 主线副本 | D53: AC22/AD22 | E53: =主线副本!AC21 -> 钻石 | F53: 1 | G53: =IF(E53="钻石","钻石",IF(ISNUMBER(SEARCH("角色抽卡券限时",E53)),"角色抽卡券限时",IF(ISNUMBER(SEARCH("专武抽卡券限时",E53)),"专武抽卡券限时",IF(ISNUMBER(SEARCH("角色抽卡券",E53)),"角色抽卡券普通",IF(ISNUMBER(SEARCH("专武抽卡券",E53)),"专武抽卡券普通",""))))) -> 钻石 | H53: =主线副本!AD21*F53 -> 50 | I53: =IF(G53="钻石",H53,H53*150) -> 50 | J53: 是 | K53: Day7到普通主线4-15
A54: 主线副本 | B54: 首周可达一次性奖励 | C54: 主线副本 | D54: AC23/AD23 | E54: =主线副本!AC22 -> 钻石 | F54: 1 | G54: =IF(E54="钻石","钻石",IF(ISNUMBER(SEARCH("角色抽卡券限时",E54)),"角色抽卡券限时",IF(ISNUMBER(SEARCH("专武抽卡券限时",E54)),"专武抽卡券限时",IF(ISNUMBER(SEARCH("角色抽卡券",E54)),"角色抽卡券普通",IF(ISNUMBER(SEARCH("专武抽卡券",E54)),"专武抽卡券普通",""))))) -> 钻石 | H54: =主线副本!AD22*F54 -> 150 | I54: =IF(G54="钻石",H54,H54*150) -> 150 | J54: 是 | K54: Day7到普通主线4-15
A55: 主线副本 | B55: 首周可达一次性奖励 | C55: 主线副本 | D55: AC24/AD24 | E55: =主线副本!#REF! -> #REF! | F55: 1 | G55: =IF(E55="钻石","钻石",IF(ISNUMBER(SEARCH("角色抽卡券限时",E55)),"角色抽卡券限时",IF(ISNUMBER(SEARCH("专武抽卡券限时",E55)),"专武抽卡券限时",IF(ISNUMBER(SEARCH("角色抽卡券",E55)),"角色抽卡券普通",IF(ISNUMBER(SEARCH("专武抽卡券",E55)),"专武抽卡券普通",""))))) -> #REF! | H55: =主线副本!#REF!*F55 -> #REF! | I55: =IF(G55="钻石",H55,H55*150) -> #REF! | J55: 是 | K55: Day7到普通主线4-15
A56: 主线副本 | B56: 首周可达一次性奖励 | C56: 主线副本 | D56: AC25/AD25 | E56: =主线副本!AC23 -> 钻石 | F56: 1 | G56: =IF(E56="钻石","钻石",IF(ISNUMBER(SEARCH("角色抽卡券限时",E56)),"角色抽卡券限时",IF(ISNUMBER(SEARCH("专武抽卡券限时",E56)),"专武抽卡券限时",IF(ISNUMBER(SEARCH("角色抽卡券",E56)),"角色抽卡券普通",IF(ISNUMBER(SEARCH("专武抽卡券",E56)),"专武抽卡券普通",""))))) -> 钻石 | H56: =主线副本!AD23*F56 -> 50 | I56: =IF(G56="钻石",H56,H56*150) -> 50 | J56: 是 | K56: Day7到普通主线4-15
A57: 主线副本 | B57: 首周可达一次性奖励 | C57: 主线副本 | D57: AC26/AD26 | E57: =主线副本!AC24 -> 钻石 | F57: 1 | G57: =IF(E57="钻石","钻石",IF(ISNUMBER(SEARCH("角色抽卡券限时",E57)),"角色抽卡券限时",IF(ISNUMBER(SEARCH("专武抽卡券限时",E57)),"专武抽卡券限时",IF(ISNUMBER(SEARCH("角色抽卡券",E57)),"角色抽卡券普通",IF(ISNUMBER(SEARCH("专武抽卡券",E57)),"专武抽卡券普通",""))))) -> 钻石 | H57: =主线副本!AD24*F57 -> 50 | I57: =IF(G57="钻石",H57,H57*150) -> 50 | J57: 是 | K57: Day7到普通主线4-15
A58: 主线副本 | B58: 首周可达一次性奖励 | C58: 主线副本 | D58: AC27/AD27 | E58: =主线副本!AC25 -> 钻石 | F58: 1 | G58: =IF(E58="钻石","钻石",IF(ISNUMBER(SEARCH("角色抽卡券限时",E58)),"角色抽卡券限时",IF(ISNUMBER(SEARCH("专武抽卡券限时",E58)),"专武抽卡券限时",IF(ISNUMBER(SEARCH("角色抽卡券",E58)),"角色抽卡券普通",IF(ISNUMBER(SEARCH("专武抽卡券",E58)),"专武抽卡券普通",""))))) -> 钻石 | H58: =主线副本!AD25*F58 -> 50 | I58: =IF(G58="钻石",H58,H58*150) -> 50 | J58: 是 | K58: Day7到普通主线4-15
A59: 主线副本 | B59: 首周可达一次性奖励 | C59: 主线副本 | D59: AC28/AD28 | E59: =主线副本!AC26 -> 钻石 | F59: 1 | G59: =IF(E59="钻石","钻石",IF(ISNUMBER(SEARCH("角色抽卡券限时",E59)),"角色抽卡券限时",IF(ISNUMBER(SEARCH("专武抽卡券限时",E59)),"专武抽卡券限时",IF(ISNUMBER(SEARCH("角色抽卡券",E59)),"角色抽卡券普通",IF(ISNUMBER(SEARCH("专武抽卡券",E59)),"专武抽卡券普通",""))))) -> 钻石 | H59: =主线副本!AD26*F59 -> 50 | I59: =IF(G59="钻石",H59,H59*150) -> 50 | J59: 是 | K59: Day7到普通主线4-15
A60: 主线副本 | B60: 首周可达一次性奖励 | C60: 主线副本 | D60: AC29/AD29 | E60: =主线副本!AC27 -> 钻石 | F60: 1 | G60: =IF(E60="钻石","钻石",IF(ISNUMBER(SEARCH("角色抽卡券限时",E60)),"角色抽卡券限时",IF(ISNUMBER(SEARCH("专武抽卡券限时",E60)),"专武抽卡券限时",IF(ISNUMBER(SEARCH("角色抽卡券",E60)),"角色抽卡券普通",IF(ISNUMBER(SEARCH("专武抽卡券",E60)),"专武抽卡券普通",""))))) -> 钻石 | H60: =主线副本!AD27*F60 -> 150 | I60: =IF(G60="钻石",H60,H60*150) -> 150 | J60: 是 | K60: Day7到普通主线4-15
A61: 主线副本 | B61: 首周可达一次性奖励 | C61: 主线副本 | D61: AC30/AD30 | E61: =主线副本!AC30 -> 0 | F61: 1 | G61: =IF(E61="钻石","钻石",IF(ISNUMBER(SEARCH("角色抽卡券限时",E61)),"角色抽卡券限时",IF(ISNUMBER(SEARCH("专武抽卡券限时",E61)),"专武抽卡券限时",IF(ISNUMBER(SEARCH("角色抽卡券",E61)),"角色抽卡券普通",IF(ISNUMBER(SEARCH("专武抽卡券",E61)),"专武抽卡券普通",""))))) | H61: =主线副本!AD30*F61 -> 0 | I61: =IF(G61="钻石",H61,H61*150) -> 0 | J61: 是 | K61: Day7到普通主线4-15
A62: 主线副本 | B62: 首周可达一次性奖励 | C62: 主线副本 | D62: AC6/AD6 | E62: =主线副本!AC6 -> 钻石 | F62: 1 | G62: =IF(E62="钻石","钻石",IF(ISNUMBER(SEARCH("角色抽卡券限时",E62)),"角色抽卡券限时",IF(ISNUMBER(SEARCH("专武抽卡券限时",E62)),"专武抽卡券限时",IF(ISNUMBER(SEARCH("角色抽卡券",E62)),"角色抽卡券普通",IF(ISNUMBER(SEARCH("专武抽卡券",E62)),"专武抽卡券普通",""))))) -> 钻石 | H62: =主线副本!AD6*F62 -> 50 | I62: =IF(G62="钻石",H62,H62*150) -> 50 | J62: 是 | K62: Day7到普通主线4-15
A63: 主线副本 | B63: 首周可达一次性奖励 | C63: 主线副本 | D63: AC7/AD7 | E63: =主线副本!AC7 -> 钻石 | F63: 1 | G63: =IF(E63="钻石","钻石",IF(ISNUMBER(SEARCH("角色抽卡券限时",E63)),"角色抽卡券限时",IF(ISNUMBER(SEARCH("专武抽卡券限时",E63)),"专武抽卡券限时",IF(ISNUMBER(SEARCH("角色抽卡券",E63)),"角色抽卡券普通",IF(ISNUMBER(SEARCH("专武抽卡券",E63)),"专武抽卡券普通",""))))) -> 钻石 | H63: =主线副本!AD7*F63 -> 50 | I63: =IF(G63="钻石",H63,H63*150) -> 50 | J63: 是 | K63: Day7到普通主线4-15
A64: 主线副本 | B64: 首周可达一次性奖励 | C64: 主线副本 | D64: AC8/AD8 | E64: =主线副本!AC8 -> 钻石 | F64: 1 | G64: =IF(E64="钻石","钻石",IF(ISNUMBER(SEARCH("角色抽卡券限时",E64)),"角色抽卡券限时",IF(ISNUMBER(SEARCH("专武抽卡券限时",E64)),"专武抽卡券限时",IF(ISNUMBER(SEARCH("角色抽卡券",E64)),"角色抽卡券普通",IF(ISNUMBER(SEARCH("专武抽卡券",E64)),"专武抽卡券普通",""))))) -> 钻石 | H64: =主线副本!AD8*F64 -> 150 | I64: =IF(G64="钻石",H64,H64*150) -> 150 | J64: 是 | K64: Day7到普通主线4-15
A65: 主线副本 | B65: 首周可达一次性奖励 | C65: 主线副本 | D65: AC9/AD9 | E65: =主线副本!AC9 -> 钻石 | F65: 1 | G65: =IF(E65="钻石","钻石",IF(ISNUMBER(SEARCH("角色抽卡券限时",E65)),"角色抽卡券限时",IF(ISNUMBER(SEARCH("专武抽卡券限时",E65)),"专武抽卡券限时",IF(ISNUMBER(SEARCH("角色抽卡券",E65)),"角色抽卡券普通",IF(ISNUMBER(SEARCH("专武抽卡券",E65)),"专武抽卡券普通",""))))) -> 钻石 | H65: =主线副本!AD9*F65 -> 50 | I65: =IF(G65="钻石",H65,H65*150) -> 50 | J65: 是 | K65: Day7到普通主线4-15
A66: 主线副本 | B66: 首周可达一次性奖励 | C66: 主线副本 | D66: AG12/AH12 | E66: =主线副本!AG12 -> 角色抽卡券限时 | F66: 1 | G66: =IF(E66="钻石","钻石",IF(ISNUMBER(SEARCH("角色抽卡券限时",E66)),"角色抽卡券限时",IF(ISNUMBER(SEARCH("专武抽卡券限时",E66)),"专武抽卡券限时",IF(ISNUMBER(SEARCH("角色抽卡券",E66)),"角色抽卡券普通",IF(ISNUMBER(SEARCH("专武抽卡券",E66)),"专武抽卡券普通",""))))) -> 角色抽卡券限时 | H66: =主线副本!AH12*F66 -> 3 | I66: =IF(G66="钻石",H66,H66*150) -> 450 | J66: 是 | K66: Day7到普通主线4-15
A67: 主线副本 | B67: 首周可达一次性奖励 | C67: 主线副本 | D67: AG17/AH17 | E67: =主线副本!AG17 -> 角色抽卡券限时 | F67: 1 | G67: =IF(E67="钻石","钻石",IF(ISNUMBER(SEARCH("角色抽卡券限时",E67)),"角色抽卡券限时",IF(ISNUMBER(SEARCH("专武抽卡券限时",E67)),"专武抽卡券限时",IF(ISNUMBER(SEARCH("角色抽卡券",E67)),"角色抽卡券普通",IF(ISNUMBER(SEARCH("专武抽卡券",E67)),"专武抽卡券普通",""))))) -> 角色抽卡券限时 | H67: =主线副本!AH17*F67 -> 3 | I67: =IF(G67="钻石",H67,H67*150) -> 450 | J67: 是 | K67: Day7到普通主线4-15
A68: 主线副本 | B68: 首周可达一次性奖励 | C68: 主线副本 | D68: AG18/AH18 | E68: =主线副本!#REF! -> #REF! | F68: 1 | G68: =IF(E68="钻石","钻石",IF(ISNUMBER(SEARCH("角色抽卡券限时",E68)),"角色抽卡券限时",IF(ISNUMBER(SEARCH("专武抽卡券限时",E68)),"专武抽卡券限时",IF(ISNUMBER(SEARCH("角色抽卡券",E68)),"角色抽卡券普通",IF(ISNUMBER(SEARCH("专武抽卡券",E68)),"专武抽卡券普通",""))))) -> #REF! | H68: =主线副本!#REF!*F68 -> #REF! | I68: =IF(G68="钻石",H68,H68*150) -> #REF! | J68: 是 | K68: Day7到普通主线4-15
A69: 主线副本 | B69: 首周可达一次性奖励 | C69: 主线副本 | D69: AG23/AH23 | E69: =主线副本!AG22 -> 角色抽卡券限时 | F69: 1 | G69: =IF(E69="钻石","钻石",IF(ISNUMBER(SEARCH("角色抽卡券限时",E69)),"角色抽卡券限时",IF(ISNUMBER(SEARCH("专武抽卡券限时",E69)),"专武抽卡券限时",IF(ISNUMBER(SEARCH("角色抽卡券",E69)),"角色抽卡券普通",IF(ISNUMBER(SEARCH("专武抽卡券",E69)),"专武抽卡券普通",""))))) -> 角色抽卡券限时 | H69: =主线副本!AH22*F69 -> 3 | I69: =IF(G69="钻石",H69,H69*150) -> 450 | J69: 是 | K69: Day7到普通主线4-15
A70: 主线副本 | B70: 首周可达一次性奖励 | C70: 主线副本 | D70: AG24/AH24 | E70: =主线副本!#REF! -> #REF! | F70: 1 | G70: =IF(E70="钻石","钻石",IF(ISNUMBER(SEARCH("角色抽卡券限时",E70)),"角色抽卡券限时",IF(ISNUMBER(SEARCH("专武抽卡券限时",E70)),"专武抽卡券限时",IF(ISNUMBER(SEARCH("角色抽卡券",E70)),"角色抽卡券普通",IF(ISNUMBER(SEARCH("专武抽卡券",E70)),"专武抽卡券普通",""))))) -> #REF! | H70: =主线副本!#REF!*F70 -> #REF! | I70: =IF(G70="钻石",H70,H70*150) -> #REF! | J70: 是 | K70: Day7到普通主线4-15
A71: 主线副本 | B71: 首周可达一次性奖励 | C71: 主线副本 | D71: AG29/AH29 | E71: =主线副本!AG27 -> 角色抽卡券限时 | F71: 1 | G71: =IF(E71="钻石","钻石",IF(ISNUMBER(SEARCH("角色抽卡券限时",E71)),"角色抽卡券限时",IF(ISNUMBER(SEARCH("专武抽卡券限时",E71)),"专武抽卡券限时",IF(ISNUMBER(SEARCH("角色抽卡券",E71)),"角色抽卡券普通",IF(ISNUMBER(SEARCH("专武抽卡券",E71)),"专武抽卡券普通",""))))) -> 角色抽卡券限时 | H71: =主线副本!AH27*F71 -> 3 | I71: =IF(G71="钻石",H71,H71*150) -> 450 | J71: 是 | K71: Day7到普通主线4-15
A72: 主线副本 | B72: 首周可达一次性奖励 | C72: 主线副本 | D72: AG30/AH30 | E72: =主线副本!AG30 -> 0 | F72: 1 | G72: =IF(E72="钻石","钻石",IF(ISNUMBER(SEARCH("角色抽卡券限时",E72)),"角色抽卡券限时",IF(ISNUMBER(SEARCH("专武抽卡券限时",E72)),"专武抽卡券限时",IF(ISNUMBER(SEARCH("角色抽卡券",E72)),"角色抽卡券普通",IF(ISNUMBER(SEARCH("专武抽卡券",E72)),"专武抽卡券普通",""))))) | H72: =主线副本!AH30*F72 -> 0 | I72: =IF(G72="钻石",H72,H72*150) -> 0 | J72: 是 | K72: Day7到普通主线4-15
A73: 主线副本 | B73: 首周可达一次性奖励 | C73: 主线副本 | D73: AG8/AH8 | E73: =主线副本!AG8 -> 角色抽卡券限时 | F73: 1 | G73: =IF(E73="钻石","钻石",IF(ISNUMBER(SEARCH("角色抽卡券限时",E73)),"角色抽卡券限时",IF(ISNUMBER(SEARCH("专武抽卡券限时",E73)),"专武抽卡券限时",IF(ISNUMBER(SEARCH("角色抽卡券",E73)),"角色抽卡券普通",IF(ISNUMBER(SEARCH("专武抽卡券",E73)),"专武抽卡券普通",""))))) -> 角色抽卡券限时 | H73: =主线副本!AH8*F73 -> 3 | I73: =IF(G73="钻石",H73,H73*150) -> 450 | J73: 是 | K73: Day7到普通主线4-15
A74: 主线副本 | B74: 首周可达一次性奖励 | C74: 主线副本 | D74: D10/E10 | E74: =主线副本!D10 -> 钻石 | F74: 1 | G74: =IF(E74="钻石","钻石",IF(ISNUMBER(SEARCH("角色抽卡券限时",E74)),"角色抽卡券限时",IF(ISNUMBER(SEARCH("专武抽卡券限时",E74)),"专武抽卡券限时",IF(ISNUMBER(SEARCH("角色抽卡券",E74)),"角色抽卡券普通",IF(ISNUMBER(SEARCH("专武抽卡券",E74)),"专武抽卡券普通",""))))) -> 钻石 | H74: =主线副本!E10*F74 -> 20 | I74: =IF(G74="钻石",H74,H74*150) -> 20 | J74: 是 | K74: Day7到普通主线4-15
A75: 主线副本 | B75: 首周可达一次性奖励 | C75: 主线副本 | D75: D11/E11 | E75: =主线副本!D11 -> 钻石 | F75: 1 | G75: =IF(E75="钻石","钻石",IF(ISNUMBER(SEARCH("角色抽卡券限时",E75)),"角色抽卡券限时",IF(ISNUMBER(SEARCH("专武抽卡券限时",E75)),"专武抽卡券限时",IF(ISNUMBER(SEARCH("角色抽卡券",E75)),"角色抽卡券普通",IF(ISNUMBER(SEARCH("专武抽卡券",E75)),"专武抽卡券普通",""))))) -> 钻石 | H75: =主线副本!E11*F75 -> 20 | I75: =IF(G75="钻石",H75,H75*150) -> 20 | J75: 是 | K75: Day7到普通主线4-15
A76: 主线副本 | B76: 首周可达一次性奖励 | C76: 主线副本 | D76: D12/E12 | E76: =主线副本!D12 -> 钻石 | F76: 1 | G76: =IF(E76="钻石","钻石",IF(ISNUMBER(SEARCH("角色抽卡券限时",E76)),"角色抽卡券限时",IF(ISNUMBER(SEARCH("专武抽卡券限时",E76)),"专武抽卡券限时",IF(ISNUMBER(SEARCH("角色抽卡券",E76)),"角色抽卡券普通",IF(ISNUMBER(SEARCH("专武抽卡券",E76)),"专武抽卡券普通",""))))) -> 钻石 | H76: =主线副本!E12*F76 -> 20 | I76: =IF(G76="钻石",H76,H76*150) -> 20 | J76: 是 | K76: Day7到普通主线4-15
A77: 主线副本 | B77: 首周可达一次性奖励 | C77: 主线副本 | D77: D13/E13 | E77: =主线副本!D13 -> 钻石 | F77: 1 | G77: =IF(E77="钻石","钻石",IF(ISNUMBER(SEARCH("角色抽卡券限时",E77)),"角色抽卡券限时",IF(ISNUMBER(SEARCH("专武抽卡券限时",E77)),"专武抽卡券限时",IF(ISNUMBER(SEARCH("角色抽卡券",E77)),"角色抽卡券普通",IF(ISNUMBER(SEARCH("专武抽卡券",E77)),"专武抽卡券普通",""))))) -> 钻石 | H77: =主线副本!E13*F77 -> 20 | I77: =IF(G77="钻石",H77,H77*150) -> 20 | J77: 是 | K77: Day7到普通主线4-15
A78: 主线副本 | B78: 首周可达一次性奖励 | C78: 主线副本 | D78: D14/E14 | E78: =主线副本!D14 -> 钻石 | F78: 1 | G78: =IF(E78="钻石","钻石",IF(ISNUMBER(SEARCH("角色抽卡券限时",E78)),"角色抽卡券限时",IF(ISNUMBER(SEARCH("专武抽卡券限时",E78)),"专武抽卡券限时",IF(ISNUMBER(SEARCH("角色抽卡券",E78)),"角色抽卡券普通",IF(ISNUMBER(SEARCH("专武抽卡券",E78)),"专武抽卡券普通",""))))) -> 钻石 | H78: =主线副本!E14*F78 -> 20 | I78: =IF(G78="钻石",H78,H78*150) -> 20 | J78: 是 | K78: Day7到普通主线4-15
A79: 主线副本 | B79: 首周可达一次性奖励 | C79: 主线副本 | D79: D15/E15 | E79: =主线副本!D15 -> 钻石 | F79: 1 | G79: =IF(E79="钻石","钻石",IF(ISNUMBER(SEARCH("角色抽卡券限时",E79)),"角色抽卡券限时",IF(ISNUMBER(SEARCH("专武抽卡券限时",E79)),"专武抽卡券限时",IF(ISNUMBER(SEARCH("角色抽卡券",E79)),"角色抽卡券普通",IF(ISNUMBER(SEARCH("专武抽卡券",E79)),"专武抽卡券普通",""))))) -> 钻石 | H79: =主线副本!E15*F79 -> 20 | I79: =IF(G79="钻石",H79,H79*150) -> 20 | J79: 是 | K79: Day7到普通主线4-15
A80: 主线副本 | B80: 首周可达一次性奖励 | C80: 主线副本 | D80: D16/E16 | E80: =主线副本!D16 -> 钻石 | F80: 1 | G80: =IF(E80="钻石","钻石",IF(ISNUMBER(SEARCH("角色抽卡券限时",E80)),"角色抽卡券限时",IF(ISNUMBER(SEARCH("专武抽卡券限时",E80)),"专武抽卡券限时",IF(ISNUMBER(SEARCH("角色抽卡券",E80)),"角色抽卡券普通",IF(ISNUMBER(SEARCH("专武抽卡券",E80)),"专武抽卡券普通",""))))) -> 钻石 | H80: =主线副本!E16*F80 -> 20 | I80: =IF(G80="钻石",H80,H80*150) -> 20 | J80: 是 | K80: Day7到普通主线4-15
A81: 主线副本 | B81: 首周可达一次性奖励 | C81: 主线副本 | D81: D17/E17 | E81: =主线副本!D17 -> 钻石 | F81: 1 | G81: =IF(E81="钻石","钻石",IF(ISNUMBER(SEARCH("角色抽卡券限时",E81)),"角色抽卡券限时",IF(ISNUMBER(SEARCH("专武抽卡券限时",E81)),"专武抽卡券限时",IF(ISNUMBER(SEARCH("角色抽卡券",E81)),"角色抽卡券普通",IF(ISNUMBER(SEARCH("专武抽卡券",E81)),"专武抽卡券普通",""))))) -> 钻石 | H81: =主线副本!E17*F81 -> 20 | I81: =IF(G81="钻石",H81,H81*150) -> 20 | J81: 是 | K81: Day7到普通主线4-15
A82: 主线副本 | B82: 首周可达一次性奖励 | C82: 主线副本 | D82: D18/E18 | E82: =主线副本!D18 -> 钻石 | F82: 1 | G82: =IF(E82="钻石","钻石",IF(ISNUMBER(SEARCH("角色抽卡券限时",E82)),"角色抽卡券限时",IF(ISNUMBER(SEARCH("专武抽卡券限时",E82)),"专武抽卡券限时",IF(ISNUMBER(SEARCH("角色抽卡券",E82)),"角色抽卡券普通",IF(ISNUMBER(SEARCH("专武抽卡券",E82)),"专武抽卡券普通",""))))) -> 钻石 | H82: =主线副本!E18*F82 -> 20 | I82: =IF(G82="钻石",H82,H82*150) -> 20 | J82: 是 | K82: Day7到普通主线4-15
A83: 主线副本 | B83: 首周可达一次性奖励 | C83: 主线副本 | D83: D19/E19 | E83: =主线副本!D19 -> 钻石 | F83: 1 | G83: =IF(E83="钻石","钻石",IF(ISNUMBER(SEARCH("角色抽卡券限时",E83)),"角色抽卡券限时",IF(ISNUMBER(SEARCH("专武抽卡券限时",E83)),"专武抽卡券限时",IF(ISNUMBER(SEARCH("角色抽卡券",E83)),"角色抽卡券普通",IF(ISNUMBER(SEARCH("专武抽卡券",E83)),"专武抽卡券普通",""))))) -> 钻石 | H83: =主线副本!E19*F83 -> 20 | I83: =IF(G83="钻石",H83,H83*150) -> 20 | J83: 是 | K83: Day7到普通主线4-15
A84: 主线副本 | B84: 首周可达一次性奖励 | C84: 主线副本 | D84: D20/E20 | E84: =主线副本!D20 -> 钻石 | F84: 1 | G84: =IF(E84="钻石","钻石",IF(ISNUMBER(SEARCH("角色抽卡券限时",E84)),"角色抽卡券限时",IF(ISNUMBER(SEARCH("专武抽卡券限时",E84)),"专武抽卡券限时",IF(ISNUMBER(SEARCH("角色抽卡券",E84)),"角色抽卡券普通",IF(ISNUMBER(SEARCH("专武抽卡券",E84)),"专武抽卡券普通",""))))) -> 钻石 | H84: =主线副本!E20*F84 -> 20 | I84: =IF(G84="钻石",H84,H84*150) -> 20 | J84: 是 | K84: Day7到普通主线4-15
A85: 主线副本 | B85: 首周可达一次性奖励 | C85: 主线副本 | D85: D21/E21 | E85: =主线副本!D21 -> 钻石 | F85: 1 | G85: =IF(E85="钻石","钻石",IF(ISNUMBER(SEARCH("角色抽卡券限时",E85)),"角色抽卡券限时",IF(ISNUMBER(SEARCH("专武抽卡券限时",E85)),"专武抽卡券限时",IF(ISNUMBER(SEARCH("角色抽卡券",E85)),"角色抽卡券普通",IF(ISNUMBER(SEARCH("专武抽卡券",E85)),"专武抽卡券普通",""))))) -> 钻石 | H85: =主线副本!E21*F85 -> 20 | I85: =IF(G85="钻石",H85,H85*150) -> 20 | J85: 是 | K85: Day7到普通主线4-15
... A123: 主线副本 | B123: 首周可达一次性奖励 | C123: 主线副本 | D123: D59/E59 | E123: =主线副本!D59 -> 钻石 | F123: 1 | G123: =IF(E123="钻石","钻石",IF(ISNUMBER(SEARCH("角色抽卡券限时",E123)),"角色抽卡券限时",IF(ISNUMBER(SEARCH("专武抽卡券限时",E123)),"专武抽卡券限时",IF(ISNUMBER(SEARCH("角色抽卡券",E123)),"角色抽卡券普通",IF(ISNUMBER(SEARCH("专武抽卡券",E123)),"专武抽卡券普通",""))))) -> 钻石 | H123: =主线副本!E59*F123 -> 20 | I123: =IF(G123="钻石",H123,H123*150) -> 20 | J123: 是 | K123: Day7到普通主线4-15
A124: 主线副本 | B124: 首周可达一次性奖励 | C124: 主线副本 | D124: D6/E6 | E124: =主线副本!D6 -> 钻石 | F124: 1 | G124: =IF(E124="钻石","钻石",IF(ISNUMBER(SEARCH("角色抽卡券限时",E124)),"角色抽卡券限时",IF(ISNUMBER(SEARCH("专武抽卡券限时",E124)),"专武抽卡券限时",IF(ISNUMBER(SEARCH("角色抽卡券",E124)),"角色抽卡券普通",IF(ISNUMBER(SEARCH("专武抽卡券",E124)),"专武抽卡券普通",""))))) -> 钻石 | H124: =主线副本!E6*F124 -> 20 | I124: =IF(G124="钻石",H124,H124*150) -> 20 | J124: 是 | K124: Day7到普通主线4-15
A125: 主线副本 | B125: 首周可达一次性奖励 | C125: 主线副本 | D125: D60/E60 | E125: =主线副本!D60 -> 钻石 | F125: 1 | G125: =IF(E125="钻石","钻石",IF(ISNUMBER(SEARCH("角色抽卡券限时",E125)),"角色抽卡券限时",IF(ISNUMBER(SEARCH("专武抽卡券限时",E125)),"专武抽卡券限时",IF(ISNUMBER(SEARCH("角色抽卡券",E125)),"角色抽卡券普通",IF(ISNUMBER(SEARCH("专武抽卡券",E125)),"专武抽卡券普通",""))))) -> 钻石 | H125: =主线副本!E60*F125 -> 20 | I125: =IF(G125="钻石",H125,H125*150) -> 20 | J125: 是 | K125: Day7到普通主线4-15
A126: 主线副本 | B126: 首周可达一次性奖励 | C126: 主线副本 | D126: D61/E61 | E126: =主线副本!D61 -> 钻石 | F126: 1 | G126: =IF(E126="钻石","钻石",IF(ISNUMBER(SEARCH("角色抽卡券限时",E126)),"角色抽卡券限时",IF(ISNUMBER(SEARCH("专武抽卡券限时",E126)),"专武抽卡券限时",IF(ISNUMBER(SEARCH("角色抽卡券",E126)),"角色抽卡券普通",IF(ISNUMBER(SEARCH("专武抽卡券",E126)),"专武抽卡券普通",""))))) -> 钻石 | H126: =主线副本!E61*F126 -> 20 | I126: =IF(G126="钻石",H126,H126*150) -> 20 | J126: 是 | K126: Day7到普通主线4-15
A127: 主线副本 | B127: 首周可达一次性奖励 | C127: 主线副本 | D127: D62/E62 | E127: =主线副本!D62 -> 钻石 | F127: 1 | G127: =IF(E127="钻石","钻石",IF(ISNUMBER(SEARCH("角色抽卡券限时",E127)),"角色抽卡券限时",IF(ISNUMBER(SEARCH("专武抽卡券限时",E127)),"专武抽卡券限时",IF(ISNUMBER(SEARCH("角色抽卡券",E127)),"角色抽卡券普通",IF(ISNUMBER(SEARCH("专武抽卡券",E127)),"专武抽卡券普通",""))))) -> 钻石 | H127: =主线副本!E62*F127 -> 20 | I127: =IF(G127="钻石",H127,H127*150) -> 20 | J127: 是 | K127: Day7到普通主线4-15
A128: 主线副本 | B128: 首周可达一次性奖励 | C128: 主线副本 | D128: D63/E63 | E128: =主线副本!D63 -> 钻石 | F128: 1 | G128: =IF(E128="钻石","钻石",IF(ISNUMBER(SEARCH("角色抽卡券限时",E128)),"角色抽卡券限时",IF(ISNUMBER(SEARCH("专武抽卡券限时",E128)),"专武抽卡券限时",IF(ISNUMBER(SEARCH("角色抽卡券",E128)),"角色抽卡券普通",IF(ISNUMBER(SEARCH("专武抽卡券",E128)),"专武抽卡券普通",""))))) -> 钻石 | H128: =主线副本!E63*F128 -> 20 | I128: =IF(G128="钻石",H128,H128*150) -> 20 | J128: 是 | K128: Day7到普通主线4-15
A129: 主线副本 | B129: 首周可达一次性奖励 | C129: 主线副本 | D129: D64/E64 | E129: =主线副本!D64 -> 钻石 | F129: 1 | G129: =IF(E129="钻石","钻石",IF(ISNUMBER(SEARCH("角色抽卡券限时",E129)),"角色抽卡券限时",IF(ISNUMBER(SEARCH("专武抽卡券限时",E129)),"专武抽卡券限时",IF(ISNUMBER(SEARCH("角色抽卡券",E129)),"角色抽卡券普通",IF(ISNUMBER(SEARCH("专武抽卡券",E129)),"专武抽卡券普通",""))))) -> 钻石 | H129: =主线副本!E64*F129 -> 20 | I129: =IF(G129="钻石",H129,H129*150) -> 20 | J129: 是 | K129: Day7到普通主线4-15
A130: 主线副本 | B130: 首周可达一次性奖励 | C130: 主线副本 | D130: D65/E65 | E130: =主线副本!D65 -> 钻石 | F130: 1 | G130: =IF(E130="钻石","钻石",IF(ISNUMBER(SEARCH("角色抽卡券限时",E130)),"角色抽卡券限时",IF(ISNUMBER(SEARCH("专武抽卡券限时",E130)),"专武抽卡券限时",IF(ISNUMBER(SEARCH("角色抽卡券",E130)),"角色抽卡券普通",IF(ISNUMBER(SEARCH("专武抽卡券",E130)),"专武抽卡券普通",""))))) -> 钻石 | H130: =主线副本!E65*F130 -> 20 | I130: =IF(G130="钻石",H130,H130*150) -> 20 | J130: 是 | K130: Day7到普通主线4-15
A131: 主线副本 | B131: 首周可达一次性奖励 | C131: 主线副本 | D131: D7/E7 | E131: =主线副本!D7 -> 钻石 | F131: 1 | G131: =IF(E131="钻石","钻石",IF(ISNUMBER(SEARCH("角色抽卡券限时",E131)),"角色抽卡券限时",IF(ISNUMBER(SEARCH("专武抽卡券限时",E131)),"专武抽卡券限时",IF(ISNUMBER(SEARCH("角色抽卡券",E131)),"角色抽卡券普通",IF(ISNUMBER(SEARCH("专武抽卡券",E131)),"专武抽卡券普通",""))))) -> 钻石 | H131: =主线副本!E7*F131 -> 20 | I131: =IF(G131="钻石",H131,H131*150) -> 20 | J131: 是 | K131: Day7到普通主线4-15
A132: 主线副本 | B132: 首周可达一次性奖励 | C132: 主线副本 | D132: D8/E8 | E132: =主线副本!D8 -> 钻石 | F132: 1 | G132: =IF(E132="钻石","钻石",IF(ISNUMBER(SEARCH("角色抽卡券限时",E132)),"角色抽卡券限时",IF(ISNUMBER(SEARCH("专武抽卡券限时",E132)),"专武抽卡券限时",IF(ISNUMBER(SEARCH("角色抽卡券",E132)),"角色抽卡券普通",IF(ISNUMBER(SEARCH("专武抽卡券",E132)),"专武抽卡券普通",""))))) -> 钻石 | H132: =主线副本!E8*F132 -> 20 | I132: =IF(G132="钻石",H132,H132*150) -> 20 | J132: 是 | K132: Day7到普通主线4-15
A133: 主线副本 | B133: 首周可达一次性奖励 | C133: 主线副本 | D133: D9/E9 | E133: =主线副本!D9 -> 钻石 | F133: 1 | G133: =IF(E133="钻石","钻石",IF(ISNUMBER(SEARCH("角色抽卡券限时",E133)),"角色抽卡券限时",IF(ISNUMBER(SEARCH("专武抽卡券限时",E133)),"专武抽卡券限时",IF(ISNUMBER(SEARCH("角色抽卡券",E133)),"角色抽卡券普通",IF(ISNUMBER(SEARCH("专武抽卡券",E133)),"专武抽卡券普通",""))))) -> 钻石 | H133: =主线副本!E9*F133 -> 20 | I133: =IF(G133="钻石",H133,H133*150) -> 20 | J133: 是 | K133: Day7到普通主线4-15
A134: 主线副本 | B134: 首周可达一次性奖励 | C134: 主线副本 | D134: N11/O11 | E134: =主线副本!N11 -> 角色抽卡券 | F134: 1 | G134: =IF(E134="钻石","钻石",IF(ISNUMBER(SEARCH("角色抽卡券限时",E134)),"角色抽卡券限时",IF(ISNUMBER(SEARCH("专武抽卡券限时",E134)),"专武抽卡券限时",IF(ISNUMBER(SEARCH("角色抽卡券",E134)),"角色抽卡券普通",IF(ISNUMBER(SEARCH("专武抽卡券",E134)),"专武抽卡券普通",""))))) -> 角色抽卡券普通 | H134: =主线副本!O11*F134 -> 1 | I134: =IF(G134="钻石",H134,H134*150) -> 150 | J134: 是 | K134: Day7到普通主线4-15
A135: 任务 | B135: 每周任务箱子 | C135: 任务 | D135: D17/E17 | E135: =任务!D17 -> 钻石 | F135: 1 | G135: =IF(E135="钻石","钻石",IF(ISNUMBER(SEARCH("角色抽卡券限时",E135)),"角色抽卡券限时",IF(ISNUMBER(SEARCH("专武抽卡券限时",E135)),"专武抽卡券限时",IF(ISNUMBER(SEARCH("角色抽卡券",E135)),"角色抽卡券普通",IF(ISNUMBER(SEARCH("专武抽卡券",E135)),"专武抽卡券普通",""))))) -> 钻石 | H135: =任务!E17*F135 -> 50 | I135: =IF(G135="钻石",H135,H135*150) -> 50 | J135: 是 | K135: 首周完成一轮
A136: 任务 | B136: 每周任务箱子 | C136: 任务 | D136: D18/E18 | E136: =任务!D18 -> 钻石 | F136: 1 | G136: =IF(E136="钻石","钻石",IF(ISNUMBER(SEARCH("角色抽卡券限时",E136)),"角色抽卡券限时",IF(ISNUMBER(SEARCH("专武抽卡券限时",E136)),"专武抽卡券限时",IF(ISNUMBER(SEARCH("角色抽卡券",E136)),"角色抽卡券普通",IF(ISNUMBER(SEARCH("专武抽卡券",E136)),"专武抽卡券普通",""))))) -> 钻石 | H136: =任务!E18*F136 -> 50 | I136: =IF(G136="钻石",H136,H136*150) -> 50 | J136: 是 | K136: 首周完成一轮
A137: 任务 | B137: 每周任务箱子 | C137: 任务 | D137: D19/E19 | E137: =任务!D19 -> 钻石 | F137: 1 | G137: =IF(E137="钻石","钻石",IF(ISNUMBER(SEARCH("角色抽卡券限时",E137)),"角色抽卡券限时",IF(ISNUMBER(SEARCH("专武抽卡券限时",E137)),"专武抽卡券限时",IF(ISNUMBER(SEARCH("角色抽卡券",E137)),"角色抽卡券普通",IF(ISNUMBER(SEARCH("专武抽卡券",E137)),"专武抽卡券普通",""))))) -> 钻石 | H137: =任务!E19*F137 -> 100 | I137: =IF(G137="钻石",H137,H137*150) -> 100 | J137: 是 | K137: 首周完成一轮
A138: 任务 | B138: 每周任务箱子 | C138: 任务 | D138: D20/E20 | E138: =任务!D20 -> 钻石 | F138: 1 | G138: =IF(E138="钻石","钻石",IF(ISNUMBER(SEARCH("角色抽卡券限时",E138)),"角色抽卡券限时",IF(ISNUMBER(SEARCH("专武抽卡券限时",E138)),"专武抽卡券限时",IF(ISNUMBER(SEARCH("角色抽卡券",E138)),"角色抽卡券普通",IF(ISNUMBER(SEARCH("专武抽卡券",E138)),"专武抽卡券普通",""))))) -> 钻石 | H138: =任务!E20*F138 -> 100 | I138: =IF(G138="钻石",H138,H138*150) -> 100 | J138: 是 | K138: 首周完成一轮
A139: 任务 | B139: 每周任务箱子 | C139: 任务 | D139: D21/E21 | E139: =任务!D21 -> 钻石 | F139: 1 | G139: =IF(E139="钻石","钻石",IF(ISNUMBER(SEARCH("角色抽卡券限时",E139)),"角色抽卡券限时",IF(ISNUMBER(SEARCH("专武抽卡券限时",E139)),"专武抽卡券限时",IF(ISNUMBER(SEARCH("角色抽卡券",E139)),"角色抽卡券普通",IF(ISNUMBER(SEARCH("专武抽卡券",E139)),"专武抽卡券普通",""))))) -> 钻石 | H139: =任务!E21*F139 -> 150 | I139: =IF(G139="钻石",H139,H139*150) -> 150 | J139: 是 | K139: 首周完成一轮
A140: 任务 | B140: 每周任务箱子 | C140: 任务 | D140: D22/E22 | E140: =任务!D22 -> 钻石 | F140: 1 | G140: =IF(E140="钻石","钻石",IF(ISNUMBER(SEARCH("角色抽卡券限时",E140)),"角色抽卡券限时",IF(ISNUMBER(SEARCH("专武抽卡券限时",E140)),"专武抽卡券限时",IF(ISNUMBER(SEARCH("角色抽卡券",E140)),"角色抽卡券普通",IF(ISNUMBER(SEARCH("专武抽卡券",E140)),"专武抽卡券普通",""))))) -> 钻石 | H140: =任务!E22*F140 -> 150 | I140: =IF(G140="钻石",H140,H140*150) -> 150 | J140: 是 | K140: 首周完成一轮
A141: 任务 | B141: 每日任务 | C141: 任务 | D141: H7/I7 | E141: =任务!H7 -> 钻石 | F141: 7 | G141: =IF(E141="钻石","钻石",IF(ISNUMBER(SEARCH("角色抽卡券限时",E141)),"角色抽卡券限时",IF(ISNUMBER(SEARCH("专武抽卡券限时",E141)),"专武抽卡券限时",IF(ISNUMBER(SEARCH("角色抽卡券",E141)),"角色抽卡券普通",IF(ISNUMBER(SEARCH("专武抽卡券",E141)),"专武抽卡券普通",""))))) -> 钻石 | H141: =任务!I7*F141 -> 350 | I141: =IF(G141="钻石",H141,H141*150) -> 350 | J141: 是 | K141: 每日任务奖励*7
A142: 任务 | B142: 每日任务 | C142: 任务 | D142: H9/I9 | E142: =任务!H9 -> 钻石 | F142: 7 | G142: =IF(E142="钻石","钻石",IF(ISNUMBER(SEARCH("角色抽卡券限时",E142)),"角色抽卡券限时",IF(ISNUMBER(SEARCH("专武抽卡券限时",E142)),"专武抽卡券限时",IF(ISNUMBER(SEARCH("角色抽卡券",E142)),"角色抽卡券普通",IF(ISNUMBER(SEARCH("专武抽卡券",E142)),"专武抽卡券普通",""))))) -> 钻石 | H142: =任务!I9*F142 -> 350 | I142: =IF(G142="钻石",H142,H142*150) -> 350 | J142: 是 | K142: 每日任务奖励*7
A143: 任务 | B143: 阶段任务 | C143: 任务 | D143: C42/D42 | E143: =任务!C42 -> 角色抽卡券限时 | F143: 1 | G143: =IF(E143="钻石","钻石",IF(ISNUMBER(SEARCH("角色抽卡券限时",E143)),"角色抽卡券限时",IF(ISNUMBER(SEARCH("专武抽卡券限时",E143)),"专武抽卡券限时",IF(ISNUMBER(SEARCH("角色抽卡券",E143)),"角色抽卡券普通",IF(ISNUMBER(SEARCH("专武抽卡券",E143)),"专武抽卡券普通",""))))) -> 角色抽卡券限时 | H143: =任务!D42*F143 -> 10 | I143: =IF(G143="钻石",H143,H143*150) -> 1500 | J143: 是 | K143: 按Day7推进到4-15
...

Sheet 玩法钻石抽卡券统计
A1: 各玩法钻石与抽卡券投放统计
A2: 口径：统计奖励投放；排除道具定价、养成消耗、商店购买/兑换消耗。通行证付费奖励单独保留在口径列。抽卡券钻石等价按道具定价150钻石/张。
A4: 玩法 | B4: 钻石 | C4: 角色抽卡券普通 | D4: 专武抽卡券普通 | E4: 角色抽卡券限时 | F4: 专武抽卡券限时 | G4: 抽卡券合计 | H4: 钻石等价合计 | I4: 备注
A5: 7日任务 | B5: =SUMIFS($G$20:$G$999,$A$20:$A$999,$A5,$F$20:$F$999,B$4) -> 1500 | C5: =SUMIFS($G$20:$G$999,$A$20:$A$999,$A5,$F$20:$F$999,C$4) -> 20 | D5: =SUMIFS($G$20:$G$999,$A$20:$A$999,$A5,$F$20:$F$999,D$4) -> 10 | E5: =SUMIFS($G$20:$G$999,$A$20:$A$999,$A5,$F$20:$F$999,E$4) -> 0 | F5: =SUMIFS($G$20:$G$999,$A$20:$A$999,$A5,$F$20:$F$999,F$4) -> 0 | G5: =SUM(C5:F5) -> 30 | H5: =SUMIFS($H$20:$H$999,$A$20:$A$999,$A5) -> 6000
A6: 主线副本 | B6: =SUMIFS($G$20:$G$999,$A$20:$A$999,$A6,$F$20:$F$999,B$4) -> 1600 | C6: =SUMIFS($G$20:$G$999,$A$20:$A$999,$A6,$F$20:$F$999,C$4) -> 0 | D6: =SUMIFS($G$20:$G$999,$A$20:$A$999,$A6,$F$20:$F$999,D$4) -> 0 | E6: =SUMIFS($G$20:$G$999,$A$20:$A$999,$A6,$F$20:$F$999,E$4) -> 9 | F6: =SUMIFS($G$20:$G$999,$A$20:$A$999,$A6,$F$20:$F$999,F$4) -> 0 | G6: =SUM(C6:F6) -> 9 | H6: =SUMIFS($H$20:$H$999,$A$20:$A$999,$A6) -> 2950
A7: 任务 | B7: =SUMIFS($G$20:$G$999,$A$20:$A$999,$A7,$F$20:$F$999,B$4) -> 1280 | C7: =SUMIFS($G$20:$G$999,$A$20:$A$999,$A7,$F$20:$F$999,C$4) -> 0 | D7: =SUMIFS($G$20:$G$999,$A$20:$A$999,$A7,$F$20:$F$999,D$4) -> 0 | E7: =SUMIFS($G$20:$G$999,$A$20:$A$999,$A7,$F$20:$F$999,E$4) -> 40 | F7: =SUMIFS($G$20:$G$999,$A$20:$A$999,$A7,$F$20:$F$999,F$4) -> 10 | G7: =SUM(C7:F7) -> 50 | H7: =SUMIFS($H$20:$H$999,$A$20:$A$999,$A7) -> 8780
A8: 公会 | B8: =SUMIFS($G$20:$G$999,$A$20:$A$999,$A8,$F$20:$F$999,B$4) -> 150 | C8: =SUMIFS($G$20:$G$999,$A$20:$A$999,$A8,$F$20:$F$999,C$4) -> 1 | D8: =SUMIFS($G$20:$G$999,$A$20:$A$999,$A8,$F$20:$F$999,D$4) -> 1 | E8: =SUMIFS($G$20:$G$999,$A$20:$A$999,$A8,$F$20:$F$999,E$4) -> 0 | F8: =SUMIFS($G$20:$G$999,$A$20:$A$999,$A8,$F$20:$F$999,F$4) -> 0 | G8: =SUM(C8:F8) -> 2 | H8: =SUMIFS($H$20:$H$999,$A$20:$A$999,$A8) -> 450
A9: 大秘境 | B9: =SUMIFS($G$20:$G$999,$A$20:$A$999,$A9,$F$20:$F$999,B$4) -> 1254 | C9: =SUMIFS($G$20:$G$999,$A$20:$A$999,$A9,$F$20:$F$999,C$4) -> 4 | D9: =SUMIFS($G$20:$G$999,$A$20:$A$999,$A9,$F$20:$F$999,D$4) -> 4 | E9: =SUMIFS($G$20:$G$999,$A$20:$A$999,$A9,$F$20:$F$999,E$4) -> 38 | F9: =SUMIFS($G$20:$G$999,$A$20:$A$999,$A9,$F$20:$F$999,F$4) -> 26 | G9: =SUM(C9:F9) -> 72 | H9: =SUMIFS($H$20:$H$999,$A$20:$A$999,$A9) -> 12054
A10: 无限挑战 | B10: =SUMIFS($G$20:$G$999,$A$20:$A$999,$A10,$F$20:$F$999,B$4) -> #REF! | C10: =SUMIFS($G$20:$G$999,$A$20:$A$999,$A10,$F$20:$F$999,C$4) -> #REF! | D10: =SUMIFS($G$20:$G$999,$A$20:$A$999,$A10,$F$20:$F$999,D$4) -> 0 | E10: =SUMIFS($G$20:$G$999,$A$20:$A$999,$A10,$F$20:$F$999,E$4) -> #REF! | F10: =SUMIFS($G$20:$G$999,$A$20:$A$999,$A10,$F$20:$F$999,F$4) -> #REF! | G10: =SUM(C10:F10) -> #REF! | H10: =SUMIFS($H$20:$H$999,$A$20:$A$999,$A10) -> #REF!
A11: 爬塔 | B11: =SUMIFS($G$20:$G$999,$A$20:$A$999,$A11,$F$20:$F$999,B$4) -> 0 | C11: =SUMIFS($G$20:$G$999,$A$20:$A$999,$A11,$F$20:$F$999,C$4) -> 0 | D11: =SUMIFS($G$20:$G$999,$A$20:$A$999,$A11,$F$20:$F$999,D$4) -> 0 | E11: =SUMIFS($G$20:$G$999,$A$20:$A$999,$A11,$F$20:$F$999,E$4) -> 0 | F11: =SUMIFS($G$20:$G$999,$A$20:$A$999,$A11,$F$20:$F$999,F$4) -> 0 | G11: =SUM(C11:F11) -> 0 | H11: =SUMIFS($H$20:$H$999,$A$20:$A$999,$A11) -> 0
A12: 竞技场 | B12: =SUMIFS($G$20:$G$999,$A$20:$A$999,$A12,$F$20:$F$999,B$4) -> 6100 | C12: =SUMIFS($G$20:$G$999,$A$20:$A$999,$A12,$F$20:$F$999,C$4) -> 0 | D12: =SUMIFS($G$20:$G$999,$A$20:$A$999,$A12,$F$20:$F$999,D$4) -> 0 | E12: =SUMIFS($G$20:$G$999,$A$20:$A$999,$A12,$F$20:$F$999,E$4) -> 0 | F12: =SUMIFS($G$20:$G$999,$A$20:$A$999,$A12,$F$20:$F$999,F$4) -> 0 | G12: =SUM(C12:F12) -> 0 | H12: =SUMIFS($H$20:$H$999,$A$20:$A$999,$A12) -> #N/A
A13: 签到 | B13: =SUMIFS($G$20:$G$999,$A$20:$A$999,$A13,$F$20:$F$999,B$4) -> 250 | C13: =SUMIFS($G$20:$G$999,$A$20:$A$999,$A13,$F$20:$F$999,C$4) -> 8 | D13: =SUMIFS($G$20:$G$999,$A$20:$A$999,$A13,$F$20:$F$999,D$4) -> 0 | E13: =SUMIFS($G$20:$G$999,$A$20:$A$999,$A13,$F$20:$F$999,E$4) -> 0 | F13: =SUMIFS($G$20:$G$999,$A$20:$A$999,$A13,$F$20:$F$999,F$4) -> 0 | G13: =SUM(C13:F13) -> 8 | H13: =SUMIFS($H$20:$H$999,$A$20:$A$999,$A13) -> 1450
A14: 通行证 | B14: =SUMIFS($G$20:$G$999,$A$20:$A$999,$A14,$F$20:$F$999,B$4) -> 2130 | C14: =SUMIFS($G$20:$G$999,$A$20:$A$999,$A14,$F$20:$F$999,C$4) -> 10 | D14: =SUMIFS($G$20:$G$999,$A$20:$A$999,$A14,$F$20:$F$999,D$4) -> 10 | E14: =SUMIFS($G$20:$G$999,$A$20:$A$999,$A14,$F$20:$F$999,E$4) -> 0 | F14: =SUMIFS($G$20:$G$999,$A$20:$A$999,$A14,$F$20:$F$999,F$4) -> 0 | G14: =SUM(C14:F14) -> 20 | H14: =SUMIFS($H$20:$H$999,$A$20:$A$999,$A14) -> 5130
A15: 高难主线 | B15: =SUMIFS($G$20:$G$999,$A$20:$A$999,$A15,$F$20:$F$999,B$4) -> 750 | C15: =SUMIFS($G$20:$G$999,$A$20:$A$999,$A15,$F$20:$F$999,C$4) -> 0 | D15: =SUMIFS($G$20:$G$999,$A$20:$A$999,$A15,$F$20:$F$999,D$4) -> 0 | E15: =SUMIFS($G$20:$G$999,$A$20:$A$999,$A15,$F$20:$F$999,E$4) -> 15 | F15: =SUMIFS($G$20:$G$999,$A$20:$A$999,$A15,$F$20:$F$999,F$4) -> 0 | G15: =SUM(C15:F15) -> 15 | H15: =SUMIFS($H$20:$H$999,$A$20:$A$999,$A15) -> 3000
A16: Boss挑战 | B16: =SUMIFS($G$20:$G$999,$A$20:$A$999,$A16,$F$20:$F$999,B$4) -> 4750 | C16: =SUMIFS($G$20:$G$999,$A$20:$A$999,$A16,$F$20:$F$999,C$4) -> 0 | D16: =SUMIFS($G$20:$G$999,$A$20:$A$999,$A16,$F$20:$F$999,D$4) -> 15 | E16: =SUMIFS($G$20:$G$999,$A$20:$A$999,$A16,$F$20:$F$999,E$4) -> 0 | F16: =SUMIFS($G$20:$G$999,$A$20:$A$999,$A16,$F$20:$F$999,F$4) -> 0 | G16: =SUM(C16:F16) -> 15 | H16: =SUMIFS($H$20:$H$999,$A$20:$A$999,$A16) -> 7000 | I16: 一次性Boss首通奖励
A17: 合计 | B17: =SUM(B5:B16) -> #REF! | C17: =SUM(C5:C16) -> #REF! | D17: =SUM(D5:D16) -> 40 | E17: =SUM(E5:E16) -> #REF! | F17: =SUM(F5:F16) -> #REF! | G17: =SUM(G5:G16) -> #REF! | H17: =SUM(H5:H16) -> #REF!
A19: 玩法 | B19: 口径/模块 | C19: 来源页签 | D19: 来源位置 | E19: 原始道具 | F19: 统计道具 | G19: 数量 | H19: 钻石等价 | I19: 备注
A20: 7日任务 | B20: 任务奖励 | C20: 7日任务 | D20: H16/I16 | E20: ='7日任务'!I16 -> 体力药 | F20: =IF(E20="钻石","钻石",IF(ISNUMBER(SEARCH("角色抽卡券限时",E20)),"角色抽卡券限时",IF(ISNUMBER(SEARCH("专武抽卡券限时",E20)),"专武抽卡券限时",IF(ISNUMBER(SEARCH("角色抽卡券",E20)),"角色抽卡券普通",IF(ISNUMBER(SEARCH("专武抽卡券",E20)),"专武抽卡券普通",""))))) | G20: ='7日任务'!J16 -> 2 | H20: =IF(F20="",0,IF(F20="钻石",G20,G20*150)) -> 0
A21: 7日任务 | B21: 任务奖励 | C21: 7日任务 | D21: H25/I25 | E21: ='7日任务'!I27 -> 体力药 | F21: =IF(E21="钻石","钻石",IF(ISNUMBER(SEARCH("角色抽卡券限时",E21)),"角色抽卡券限时",IF(ISNUMBER(SEARCH("专武抽卡券限时",E21)),"专武抽卡券限时",IF(ISNUMBER(SEARCH("角色抽卡券",E21)),"角色抽卡券普通",IF(ISNUMBER(SEARCH("专武抽卡券",E21)),"专武抽卡券普通",""))))) | G21: ='7日任务'!J27 -> 2 | H21: =IF(F21="",0,IF(F21="钻石",G21,G21*150)) -> 0
A22: 7日任务 | B22: 任务奖励 | C22: 7日任务 | D22: H35/I35 | E22: ='7日任务'!I39 -> 体力药 | F22: =IF(E22="钻石","钻石",IF(ISNUMBER(SEARCH("角色抽卡券限时",E22)),"角色抽卡券限时",IF(ISNUMBER(SEARCH("专武抽卡券限时",E22)),"专武抽卡券限时",IF(ISNUMBER(SEARCH("角色抽卡券",E22)),"角色抽卡券普通",IF(ISNUMBER(SEARCH("专武抽卡券",E22)),"专武抽卡券普通",""))))) | G22: ='7日任务'!J39 -> 2 | H22: =IF(F22="",0,IF(F22="钻石",G22,G22*150)) -> 0
A23: 7日任务 | B23: 任务奖励 | C23: 7日任务 | D23: H45/I45 | E23: ='7日任务'!I51 -> 体力药 | F23: =IF(E23="钻石","钻石",IF(ISNUMBER(SEARCH("角色抽卡券限时",E23)),"角色抽卡券限时",IF(ISNUMBER(SEARCH("专武抽卡券限时",E23)),"专武抽卡券限时",IF(ISNUMBER(SEARCH("角色抽卡券",E23)),"角色抽卡券普通",IF(ISNUMBER(SEARCH("专武抽卡券",E23)),"专武抽卡券普通",""))))) | G23: ='7日任务'!J51 -> 2 | H23: =IF(F23="",0,IF(F23="钻石",G23,G23*150)) -> 0
A24: 7日任务 | B24: 任务奖励 | C24: 7日任务 | D24: H55/I55 | E24: ='7日任务'!I63 -> 体力药 | F24: =IF(E24="钻石","钻石",IF(ISNUMBER(SEARCH("角色抽卡券限时",E24)),"角色抽卡券限时",IF(ISNUMBER(SEARCH("专武抽卡券限时",E24)),"专武抽卡券限时",IF(ISNUMBER(SEARCH("角色抽卡券",E24)),"角色抽卡券普通",IF(ISNUMBER(SEARCH("专武抽卡券",E24)),"专武抽卡券普通",""))))) | G24: ='7日任务'!J63 -> 2 | H24: =IF(F24="",0,IF(F24="钻石",G24,G24*150)) -> 0
A25: 7日任务 | B25: 任务奖励 | C25: 7日任务 | D25: H65/I65 | E25: ='7日任务'!I75 -> 体力药 | F25: =IF(E25="钻石","钻石",IF(ISNUMBER(SEARCH("角色抽卡券限时",E25)),"角色抽卡券限时",IF(ISNUMBER(SEARCH("专武抽卡券限时",E25)),"专武抽卡券限时",IF(ISNUMBER(SEARCH("角色抽卡券",E25)),"角色抽卡券普通",IF(ISNUMBER(SEARCH("专武抽卡券",E25)),"专武抽卡券普通",""))))) | G25: ='7日任务'!J75 -> 2 | H25: =IF(F25="",0,IF(F25="钻石",G25,G25*150)) -> 0
A26: 7日任务 | B26: 任务奖励 | C26: 7日任务 | D26: H75/I75 | E26: ='7日任务'!I87 -> 体力药 | F26: =IF(E26="钻石","钻石",IF(ISNUMBER(SEARCH("角色抽卡券限时",E26)),"角色抽卡券限时",IF(ISNUMBER(SEARCH("专武抽卡券限时",E26)),"专武抽卡券限时",IF(ISNUMBER(SEARCH("角色抽卡券",E26)),"角色抽卡券普通",IF(ISNUMBER(SEARCH("专武抽卡券",E26)),"专武抽卡券普通",""))))) | G26: ='7日任务'!J87 -> 2 | H26: =IF(F26="",0,IF(F26="钻石",G26,G26*150)) -> 0
A27: 7日任务 | B27: 阶段奖励 | C27: 7日任务 | D27: B91/C91 | E27: ='7日任务'!B105 -> 角色抽卡券普通 | F27: =IF(E27="钻石","钻石",IF(ISNUMBER(SEARCH("角色抽卡券限时",E27)),"角色抽卡券限时",IF(ISNUMBER(SEARCH("专武抽卡券限时",E27)),"专武抽卡券限时",IF(ISNUMBER(SEARCH("角色抽卡券",E27)),"角色抽卡券普通",IF(ISNUMBER(SEARCH("专武抽卡券",E27)),"专武抽卡券普通",""))))) -> 角色抽卡券普通 | G27: ='7日任务'!C105 -> 10 | H27: =IF(F27="",0,IF(F27="钻石",G27,G27*150)) -> 1500
A28: 7日任务 | B28: 阶段奖励 | C28: 7日任务 | D28: B92/C92 | E28: ='7日任务'!B106 -> 角色抽卡券普通 | F28: =IF(E28="钻石","钻石",IF(ISNUMBER(SEARCH("角色抽卡券限时",E28)),"角色抽卡券限时",IF(ISNUMBER(SEARCH("专武抽卡券限时",E28)),"专武抽卡券限时",IF(ISNUMBER(SEARCH("角色抽卡券",E28)),"角色抽卡券普通",IF(ISNUMBER(SEARCH("专武抽卡券",E28)),"专武抽卡券普通",""))))) -> 角色抽卡券普通 | G28: ='7日任务'!C106 -> 10 | H28: =IF(F28="",0,IF(F28="钻石",G28,G28*150)) -> 1500
A29: 7日任务 | B29: 阶段奖励 | C29: 7日任务 | D29: B93/C93 | E29: ='7日任务'!B107 -> 专武抽卡券普通 | F29: =IF(E29="钻石","钻石",IF(ISNUMBER(SEARCH("角色抽卡券限时",E29)),"角色抽卡券限时",IF(ISNUMBER(SEARCH("专武抽卡券限时",E29)),"专武抽卡券限时",IF(ISNUMBER(SEARCH("角色抽卡券",E29)),"角色抽卡券普通",IF(ISNUMBER(SEARCH("专武抽卡券",E29)),"专武抽卡券普通",""))))) -> 专武抽卡券普通 | G29: ='7日任务'!C107 -> 10 | H29: =IF(F29="",0,IF(F29="钻石",G29,G29*150)) -> 1500
A30: 7日任务 | B30: 阶段奖励 | C30: 7日任务 | D30: B94/C94 | E30: ='7日任务'!B108 -> SSR角色 | F30: =IF(E30="钻石","钻石",IF(ISNUMBER(SEARCH("角色抽卡券限时",E30)),"角色抽卡券限时",IF(ISNUMBER(SEARCH("专武抽卡券限时",E30)),"专武抽卡券限时",IF(ISNUMBER(SEARCH("角色抽卡券",E30)),"角色抽卡券普通",IF(ISNUMBER(SEARCH("专武抽卡券",E30)),"专武抽卡券普通",""))))) | G30: ='7日任务'!C108 -> 1 | H30: =IF(F30="",0,IF(F30="钻石",G30,G30*150)) -> 0
A31: 7日任务 | B31: 阶段奖励 | C31: 7日任务 | D31: B96/C96 | E31: ='7日任务'!B110 -> SSR专武 | F31: =IF(E31="钻石","钻石",IF(ISNUMBER(SEARCH("角色抽卡券限时",E31)),"角色抽卡券限时",IF(ISNUMBER(SEARCH("专武抽卡券限时",E31)),"专武抽卡券限时",IF(ISNUMBER(SEARCH("角色抽卡券",E31)),"角色抽卡券普通",IF(ISNUMBER(SEARCH("专武抽卡券",E31)),"专武抽卡券普通",""))))) | G31: ='7日任务'!C110 -> 1 | H31: =IF(F31="",0,IF(F31="钻石",G31,G31*150)) -> 0
A32: 7日任务 | B32: 阶段奖励 | C32: 7日任务 | D32: D91/E91 | E32: ='7日任务'!D105 -> 钻石 | F32: =IF(E32="钻石","钻石",IF(ISNUMBER(SEARCH("角色抽卡券限时",E32)),"角色抽卡券限时",IF(ISNUMBER(SEARCH("专武抽卡券限时",E32)),"专武抽卡券限时",IF(ISNUMBER(SEARCH("角色抽卡券",E32)),"角色抽卡券普通",IF(ISNUMBER(SEARCH("专武抽卡券",E32)),"专武抽卡券普通",""))))) -> 钻石 | G32: ='7日任务'!E105 -> 500 | H32: =IF(F32="",0,IF(F32="钻石",G32,G32*150)) -> 500
A33: 7日任务 | B33: 阶段奖励 | C33: 7日任务 | D33: D92/E92 | E33: ='7日任务'!D106 -> 钻石 | F33: =IF(E33="钻石","钻石",IF(ISNUMBER(SEARCH("角色抽卡券限时",E33)),"角色抽卡券限时",IF(ISNUMBER(SEARCH("专武抽卡券限时",E33)),"专武抽卡券限时",IF(ISNUMBER(SEARCH("角色抽卡券",E33)),"角色抽卡券普通",IF(ISNUMBER(SEARCH("专武抽卡券",E33)),"专武抽卡券普通",""))))) -> 钻石 | G33: ='7日任务'!E106 -> 500 | H33: =IF(F33="",0,IF(F33="钻石",G33,G33*150)) -> 500
A34: 7日任务 | B34: 阶段奖励 | C34: 7日任务 | D34: D93/E93 | E34: ='7日任务'!D107 -> 钻石 | F34: =IF(E34="钻石","钻石",IF(ISNUMBER(SEARCH("角色抽卡券限时",E34)),"角色抽卡券限时",IF(ISNUMBER(SEARCH("专武抽卡券限时",E34)),"专武抽卡券限时",IF(ISNUMBER(SEARCH("角色抽卡券",E34)),"角色抽卡券普通",IF(ISNUMBER(SEARCH("专武抽卡券",E34)),"专武抽卡券普通",""))))) -> 钻石 | G34: ='7日任务'!E107 -> 500 | H34: =IF(F34="",0,IF(F34="钻石",G34,G34*150)) -> 500
A35: 7日任务 | B35: 阶段奖励 | C35: 7日任务 | D35: D94/E94 | E35: ='7日任务'!D108 -> 0 | F35: =IF(E35="钻石","钻石",IF(ISNUMBER(SEARCH("角色抽卡券限时",E35)),"角色抽卡券限时",IF(ISNUMBER(SEARCH("专武抽卡券限时",E35)),"专武抽卡券限时",IF(ISNUMBER(SEARCH("角色抽卡券",E35)),"角色抽卡券普通",IF(ISNUMBER(SEARCH("专武抽卡券",E35)),"专武抽卡券普通",""))))) | G35: ='7日任务'!E108 -> 0 | H35: =IF(F35="",0,IF(F35="钻石",G35,G35*150)) -> 0
A36: 7日任务 | B36: 阶段奖励 | C36: 7日任务 | D36: D96/E96 | E36: ='7日任务'!D110 -> 0 | F36: =IF(E36="钻石","钻石",IF(ISNUMBER(SEARCH("角色抽卡券限时",E36)),"角色抽卡券限时",IF(ISNUMBER(SEARCH("专武抽卡券限时",E36)),"专武抽卡券限时",IF(ISNUMBER(SEARCH("角色抽卡券",E36)),"角色抽卡券普通",IF(ISNUMBER(SEARCH("专武抽卡券",E36)),"专武抽卡券普通",""))))) | G36: ='7日任务'!E110 -> 0 | H36: =IF(F36="",0,IF(F36="钻石",G36,G36*150)) -> 0
A37: 主线副本 | B37: 普通通关奖励 | C37: 配置页-主线副本 | D37: S10/U10 | E37: ='配置页-主线副本'!T10 -> 金币 | F37: =IF(E37="钻石","钻石",IF(ISNUMBER(SEARCH("角色抽卡券限时",E37)),"角色抽卡券限时",IF(ISNUMBER(SEARCH("专武抽卡券限时",E37)),"专武抽卡券限时",IF(ISNUMBER(SEARCH("角色抽卡券",E37)),"角色抽卡券普通",IF(ISNUMBER(SEARCH("专武抽卡券",E37)),"专武抽卡券普通",""))))) | G37: ='配置页-主线副本'!#REF! -> #REF! | H37: =IF(F37="",0,IF(F37="钻石",G37,G37*150)) -> 0
A38: 主线副本 | B38: 普通通关奖励 | C38: 配置页-主线副本 | D38: S101/U101 | E38: ='配置页-主线副本'!T101 -> 角色经验中 | F38: =IF(E38="钻石","钻石",IF(ISNUMBER(SEARCH("角色抽卡券限时",E38)),"角色抽卡券限时",IF(ISNUMBER(SEARCH("专武抽卡券限时",E38)),"专武抽卡券限时",IF(ISNUMBER(SEARCH("角色抽卡券",E38)),"角色抽卡券普通",IF(ISNUMBER(SEARCH("专武抽卡券",E38)),"专武抽卡券普通",""))))) | G38: ='配置页-主线副本'!#REF! -> #REF! | H38: =IF(F38="",0,IF(F38="钻石",G38,G38*150)) -> 0
A39: 主线副本 | B39: 普通通关奖励 | C39: 配置页-主线副本 | D39: S105/U105 | E39: ='配置页-主线副本'!T105 -> 星盘中级道具辅2 | F39: =IF(E39="钻石","钻石",IF(ISNUMBER(SEARCH("角色抽卡券限时",E39)),"角色抽卡券限时",IF(ISNUMBER(SEARCH("专武抽卡券限时",E39)),"专武抽卡券限时",IF(ISNUMBER(SEARCH("角色抽卡券",E39)),"角色抽卡券普通",IF(ISNUMBER(SEARCH("专武抽卡券",E39)),"专武抽卡券普通",""))))) | G39: ='配置页-主线副本'!#REF! -> #REF! | H39: =IF(F39="",0,IF(F39="钻石",G39,G39*150)) -> 0
A40: 主线副本 | B40: 普通通关奖励 | C40: 配置页-主线副本 | D40: S109/U109 | E40: ='配置页-主线副本'!T109 -> 金币 | F40: =IF(E40="钻石","钻石",IF(ISNUMBER(SEARCH("角色抽卡券限时",E40)),"角色抽卡券限时",IF(ISNUMBER(SEARCH("专武抽卡券限时",E40)),"专武抽卡券限时",IF(ISNUMBER(SEARCH("角色抽卡券",E40)),"角色抽卡券普通",IF(ISNUMBER(SEARCH("专武抽卡券",E40)),"专武抽卡券普通",""))))) | G40: ='配置页-主线副本'!#REF! -> #REF! | H40: =IF(F40="",0,IF(F40="钻石",G40,G40*150)) -> 0
A41: 主线副本 | B41: 普通通关奖励 | C41: 配置页-主线副本 | D41: S113/U113 | E41: ='配置页-主线副本'!T113 -> 角色经验中 | F41: =IF(E41="钻石","钻石",IF(ISNUMBER(SEARCH("角色抽卡券限时",E41)),"角色抽卡券限时",IF(ISNUMBER(SEARCH("专武抽卡券限时",E41)),"专武抽卡券限时",IF(ISNUMBER(SEARCH("角色抽卡券",E41)),"角色抽卡券普通",IF(ISNUMBER(SEARCH("专武抽卡券",E41)),"专武抽卡券普通",""))))) | G41: ='配置页-主线副本'!#REF! -> #REF! | H41: =IF(F41="",0,IF(F41="钻石",G41,G41*150)) -> 0
A42: 主线副本 | B42: 普通通关奖励 | C42: 配置页-主线副本 | D42: S117/U117 | E42: ='配置页-主线副本'!T117 -> 角色升阶材料中攻 | F42: =IF(E42="钻石","钻石",IF(ISNUMBER(SEARCH("角色抽卡券限时",E42)),"角色抽卡券限时",IF(ISNUMBER(SEARCH("专武抽卡券限时",E42)),"专武抽卡券限时",IF(ISNUMBER(SEARCH("角色抽卡券",E42)),"角色抽卡券普通",IF(ISNUMBER(SEARCH("专武抽卡券",E42)),"专武抽卡券普通",""))))) | G42: ='配置页-主线副本'!#REF! -> #REF! | H42: =IF(F42="",0,IF(F42="钻石",G42,G42*150)) -> 0
A43: 主线副本 | B43: 普通通关奖励 | C43: 配置页-主线副本 | D43: S121/U121 | E43: ='配置页-主线副本'!T121 -> 金币 | F43: =IF(E43="钻石","钻石",IF(ISNUMBER(SEARCH("角色抽卡券限时",E43)),"角色抽卡券限时",IF(ISNUMBER(SEARCH("专武抽卡券限时",E43)),"专武抽卡券限时",IF(ISNUMBER(SEARCH("角色抽卡券",E43)),"角色抽卡券普通",IF(ISNUMBER(SEARCH("专武抽卡券",E43)),"专武抽卡券普通",""))))) | G43: ='配置页-主线副本'!#REF! -> #REF! | H43: =IF(F43="",0,IF(F43="钻石",G43,G43*150)) -> 0
A44: 主线副本 | B44: 普通通关奖励 | C44: 配置页-主线副本 | D44: S125/U125 | E44: ='配置页-主线副本'!T125 -> 角色经验中 | F44: =IF(E44="钻石","钻石",IF(ISNUMBER(SEARCH("角色抽卡券限时",E44)),"角色抽卡券限时",IF(ISNUMBER(SEARCH("专武抽卡券限时",E44)),"专武抽卡券限时",IF(ISNUMBER(SEARCH("角色抽卡券",E44)),"角色抽卡券普通",IF(ISNUMBER(SEARCH("专武抽卡券",E44)),"专武抽卡券普通",""))))) | G44: ='配置页-主线副本'!#REF! -> #REF! | H44: =IF(F44="",0,IF(F44="钻石",G44,G44*150)) -> 0
A45: 主线副本 | B45: 普通通关奖励 | C45: 配置页-主线副本 | D45: S129/U129 | E45: ='配置页-主线副本'!T129 -> 星盘高级道具攻2 | F45: =IF(E45="钻石","钻石",IF(ISNUMBER(SEARCH("角色抽卡券限时",E45)),"角色抽卡券限时",IF(ISNUMBER(SEARCH("专武抽卡券限时",E45)),"专武抽卡券限时",IF(ISNUMBER(SEARCH("角色抽卡券",E45)),"角色抽卡券普通",IF(ISNUMBER(SEARCH("专武抽卡券",E45)),"专武抽卡券普通",""))))) | G45: ='配置页-主线副本'!#REF! -> #REF! | H45: =IF(F45="",0,IF(F45="钻石",G45,G45*150)) -> 0
A46: 主线副本 | B46: 普通通关奖励 | C46: 配置页-主线副本 | D46: S13/U13 | E46: ='配置页-主线副本'!T13 -> 金币 | F46: =IF(E46="钻石","钻石",IF(ISNUMBER(SEARCH("角色抽卡券限时",E46)),"角色抽卡券限时",IF(ISNUMBER(SEARCH("专武抽卡券限时",E46)),"专武抽卡券限时",IF(ISNUMBER(SEARCH("角色抽卡券",E46)),"角色抽卡券普通",IF(ISNUMBER(SEARCH("专武抽卡券",E46)),"专武抽卡券普通",""))))) | G46: ='配置页-主线副本'!#REF! -> #REF! | H46: =IF(F46="",0,IF(F46="钻石",G46,G46*150)) -> 0
A47: 主线副本 | B47: 普通通关奖励 | C47: 配置页-主线副本 | D47: S133/U133 | E47: ='配置页-主线副本'!T133 -> 金币 | F47: =IF(E47="钻石","钻石",IF(ISNUMBER(SEARCH("角色抽卡券限时",E47)),"角色抽卡券限时",IF(ISNUMBER(SEARCH("专武抽卡券限时",E47)),"专武抽卡券限时",IF(ISNUMBER(SEARCH("角色抽卡券",E47)),"角色抽卡券普通",IF(ISNUMBER(SEARCH("专武抽卡券",E47)),"专武抽卡券普通",""))))) | G47: ='配置页-主线副本'!#REF! -> #REF! | H47: =IF(F47="",0,IF(F47="钻石",G47,G47*150)) -> 0
A48: 主线副本 | B48: 普通通关奖励 | C48: 配置页-主线副本 | D48: S137/U137 | E48: ='配置页-主线副本'!T137 -> 角色经验中 | F48: =IF(E48="钻石","钻石",IF(ISNUMBER(SEARCH("角色抽卡券限时",E48)),"角色抽卡券限时",IF(ISNUMBER(SEARCH("专武抽卡券限时",E48)),"专武抽卡券限时",IF(ISNUMBER(SEARCH("角色抽卡券",E48)),"角色抽卡券普通",IF(ISNUMBER(SEARCH("专武抽卡券",E48)),"专武抽卡券普通",""))))) | G48: ='配置页-主线副本'!#REF! -> #REF! | H48: =IF(F48="",0,IF(F48="钻石",G48,G48*150)) -> 0
A49: 主线副本 | B49: 普通通关奖励 | C49: 配置页-主线副本 | D49: S141/U141 | E49: ='配置页-主线副本'!T141 -> 星盘高级道具辅2 | F49: =IF(E49="钻石","钻石",IF(ISNUMBER(SEARCH("角色抽卡券限时",E49)),"角色抽卡券限时",IF(ISNUMBER(SEARCH("专武抽卡券限时",E49)),"专武抽卡券限时",IF(ISNUMBER(SEARCH("角色抽卡券",E49)),"角色抽卡券普通",IF(ISNUMBER(SEARCH("专武抽卡券",E49)),"专武抽卡券普通",""))))) | G49: ='配置页-主线副本'!#REF! -> #REF! | H49: =IF(F49="",0,IF(F49="钻石",G49,G49*150)) -> 0
A50: 主线副本 | B50: 普通通关奖励 | C50: 配置页-主线副本 | D50: S145/U145 | E50: ='配置页-主线副本'!T145 -> 金币 | F50: =IF(E50="钻石","钻石",IF(ISNUMBER(SEARCH("角色抽卡券限时",E50)),"角色抽卡券限时",IF(ISNUMBER(SEARCH("专武抽卡券限时",E50)),"专武抽卡券限时",IF(ISNUMBER(SEARCH("角色抽卡券",E50)),"角色抽卡券普通",IF(ISNUMBER(SEARCH("专武抽卡券",E50)),"专武抽卡券普通",""))))) | G50: ='配置页-主线副本'!#REF! -> #REF! | H50: =IF(F50="",0,IF(F50="钻石",G50,G50*150)) -> 0
A51: 主线副本 | B51: 普通通关奖励 | C51: 配置页-主线副本 | D51: S149/U149 | E51: ='配置页-主线副本'!T149 -> 角色经验中 | F51: =IF(E51="钻石","钻石",IF(ISNUMBER(SEARCH("角色抽卡券限时",E51)),"角色抽卡券限时",IF(ISNUMBER(SEARCH("专武抽卡券限时",E51)),"专武抽卡券限时",IF(ISNUMBER(SEARCH("角色抽卡券",E51)),"角色抽卡券普通",IF(ISNUMBER(SEARCH("专武抽卡券",E51)),"专武抽卡券普通",""))))) | G51: ='配置页-主线副本'!#REF! -> #REF! | H51: =IF(F51="",0,IF(F51="钻石",G51,G51*150)) -> 0
A52: 主线副本 | B52: 普通通关奖励 | C52: 配置页-主线副本 | D52: S153/U153 | E52: ='配置页-主线副本'!T153 -> 星盘顶级道具攻1 | F52: =IF(E52="钻石","钻石",IF(ISNUMBER(SEARCH("角色抽卡券限时",E52)),"角色抽卡券限时",IF(ISNUMBER(SEARCH("专武抽卡券限时",E52)),"专武抽卡券限时",IF(ISNUMBER(SEARCH("角色抽卡券",E52)),"角色抽卡券普通",IF(ISNUMBER(SEARCH("专武抽卡券",E52)),"专武抽卡券普通",""))))) | G52: ='配置页-主线副本'!#REF! -> #REF! | H52: =IF(F52="",0,IF(F52="钻石",G52,G52*150)) -> 0
A53: 主线副本 | B53: 普通通关奖励 | C53: 配置页-主线副本 | D53: S157/U157 | E53: ='配置页-主线副本'!T157 -> 金币 | F53: =IF(E53="钻石","钻石",IF(ISNUMBER(SEARCH("角色抽卡券限时",E53)),"角色抽卡券限时",IF(ISNUMBER(SEARCH("专武抽卡券限时",E53)),"专武抽卡券限时",IF(ISNUMBER(SEARCH("角色抽卡券",E53)),"角色抽卡券普通",IF(ISNUMBER(SEARCH("专武抽卡券",E53)),"专武抽卡券普通",""))))) | G53: ='配置页-主线副本'!#REF! -> #REF! | H53: =IF(F53="",0,IF(F53="钻石",G53,G53*150)) -> 0
A54: 主线副本 | B54: 普通通关奖励 | C54: 配置页-主线副本 | D54: S161/U161 | E54: ='配置页-主线副本'!T161 -> 角色经验中 | F54: =IF(E54="钻石","钻石",IF(ISNUMBER(SEARCH("角色抽卡券限时",E54)),"角色抽卡券限时",IF(ISNUMBER(SEARCH("专武抽卡券限时",E54)),"专武抽卡券限时",IF(ISNUMBER(SEARCH("角色抽卡券",E54)),"角色抽卡券普通",IF(ISNUMBER(SEARCH("专武抽卡券",E54)),"专武抽卡券普通",""))))) | G54: ='配置页-主线副本'!#REF! -> #REF! | H54: =IF(F54="",0,IF(F54="钻石",G54,G54*150)) -> 0
A55: 主线副本 | B55: 普通通关奖励 | C55: 配置页-主线副本 | D55: S165/U165 | E55: ='配置页-主线副本'!T165 -> 星盘顶级道具辅1 | F55: =IF(E55="钻石","钻石",IF(ISNUMBER(SEARCH("角色抽卡券限时",E55)),"角色抽卡券限时",IF(ISNUMBER(SEARCH("专武抽卡券限时",E55)),"专武抽卡券限时",IF(ISNUMBER(SEARCH("角色抽卡券",E55)),"角色抽卡券普通",IF(ISNUMBER(SEARCH("专武抽卡券",E55)),"专武抽卡券普通",""))))) | G55: ='配置页-主线副本'!#REF! -> #REF! | H55: =IF(F55="",0,IF(F55="钻石",G55,G55*150)) -> 0
A56: 主线副本 | B56: 普通通关奖励 | C56: 配置页-主线副本 | D56: S169/U169 | E56: ='配置页-主线副本'!S169 -> 0 | F56: =IF(E56="钻石","钻石",IF(ISNUMBER(SEARCH("角色抽卡券限时",E56)),"角色抽卡券限时",IF(ISNUMBER(SEARCH("专武抽卡券限时",E56)),"专武抽卡券限时",IF(ISNUMBER(SEARCH("角色抽卡券",E56)),"角色抽卡券普通",IF(ISNUMBER(SEARCH("专武抽卡券",E56)),"专武抽卡券普通",""))))) | G56: ='配置页-主线副本'!U169 -> 0 | H56: =IF(F56="",0,IF(F56="钻石",G56,G56*150)) -> 0
A57: 主线副本 | B57: 普通通关奖励 | C57: 配置页-主线副本 | D57: S17/U17 | E57: ='配置页-主线副本'!T17 -> 角色经验中 | F57: =IF(E57="钻石","钻石",IF(ISNUMBER(SEARCH("角色抽卡券限时",E57)),"角色抽卡券限时",IF(ISNUMBER(SEARCH("专武抽卡券限时",E57)),"专武抽卡券限时",IF(ISNUMBER(SEARCH("角色抽卡券",E57)),"角色抽卡券普通",IF(ISNUMBER(SEARCH("专武抽卡券",E57)),"专武抽卡券普通",""))))) | G57: ='配置页-主线副本'!#REF! -> #REF! | H57: =IF(F57="",0,IF(F57="钻石",G57,G57*150)) -> 0
A58: 主线副本 | B58: 普通通关奖励 | C58: 配置页-主线副本 | D58: S173/U173 | E58: ='配置页-主线副本'!S173 -> 0 | F58: =IF(E58="钻石","钻石",IF(ISNUMBER(SEARCH("角色抽卡券限时",E58)),"角色抽卡券限时",IF(ISNUMBER(SEARCH("专武抽卡券限时",E58)),"专武抽卡券限时",IF(ISNUMBER(SEARCH("角色抽卡券",E58)),"角色抽卡券普通",IF(ISNUMBER(SEARCH("专武抽卡券",E58)),"专武抽卡券普通",""))))) | G58: ='配置页-主线副本'!U173 -> 0 | H58: =IF(F58="",0,IF(F58="钻石",G58,G58*150)) -> 0
A59: 主线副本 | B59: 普通通关奖励 | C59: 配置页-主线副本 | D59: S177/U177 | E59: ='配置页-主线副本'!S177 -> 0 | F59: =IF(E59="钻石","钻石",IF(ISNUMBER(SEARCH("角色抽卡券限时",E59)),"角色抽卡券限时",IF(ISNUMBER(SEARCH("专武抽卡券限时",E59)),"专武抽卡券限时",IF(ISNUMBER(SEARCH("角色抽卡券",E59)),"角色抽卡券普通",IF(ISNUMBER(SEARCH("专武抽卡券",E59)),"专武抽卡券普通",""))))) | G59: ='配置页-主线副本'!U177 -> 0 | H59: =IF(F59="",0,IF(F59="钻石",G59,G59*150)) -> 0
A60: 主线副本 | B60: 普通通关奖励 | C60: 配置页-主线副本 | D60: S181/U181 | E60: ='配置页-主线副本'!S181 -> 0 | F60: =IF(E60="钻石","钻石",IF(ISNUMBER(SEARCH("角色抽卡券限时",E60)),"角色抽卡券限时",IF(ISNUMBER(SEARCH("专武抽卡券限时",E60)),"专武抽卡券限时",IF(ISNUMBER(SEARCH("角色抽卡券",E60)),"角色抽卡券普通",IF(ISNUMBER(SEARCH("专武抽卡券",E60)),"专武抽卡券普通",""))))) | G60: ='配置页-主线副本'!U181 -> 0 | H60: =IF(F60="",0,IF(F60="钻石",G60,G60*150)) -> 0
A61: 主线副本 | B61: 普通通关奖励 | C61: 配置页-主线副本 | D61: S185/U185 | E61: ='配置页-主线副本'!S185 -> 0 | F61: =IF(E61="钻石","钻石",IF(ISNUMBER(SEARCH("角色抽卡券限时",E61)),"角色抽卡券限时",IF(ISNUMBER(SEARCH("专武抽卡券限时",E61)),"专武抽卡券限时",IF(ISNUMBER(SEARCH("角色抽卡券",E61)),"角色抽卡券普通",IF(ISNUMBER(SEARCH("专武抽卡券",E61)),"专武抽卡券普通",""))))) | G61: ='配置页-主线副本'!U185 -> 0 | H61: =IF(F61="",0,IF(F61="钻石",G61,G61*150)) -> 0
A62: 主线副本 | B62: 普通通关奖励 | C62: 配置页-主线副本 | D62: S189/U189 | E62: ='配置页-主线副本'!S189 -> 0 | F62: =IF(E62="钻石","钻石",IF(ISNUMBER(SEARCH("角色抽卡券限时",E62)),"角色抽卡券限时",IF(ISNUMBER(SEARCH("专武抽卡券限时",E62)),"专武抽卡券限时",IF(ISNUMBER(SEARCH("角色抽卡券",E62)),"角色抽卡券普通",IF(ISNUMBER(SEARCH("专武抽卡券",E62)),"专武抽卡券普通",""))))) | G62: ='配置页-主线副本'!U189 -> 0 | H62: =IF(F62="",0,IF(F62="钻石",G62,G62*150)) -> 0
A63: 主线副本 | B63: 普通通关奖励 | C63: 配置页-主线副本 | D63: S193/U193 | E63: ='配置页-主线副本'!S193 -> 0 | F63: =IF(E63="钻石","钻石",IF(ISNUMBER(SEARCH("角色抽卡券限时",E63)),"角色抽卡券限时",IF(ISNUMBER(SEARCH("专武抽卡券限时",E63)),"专武抽卡券限时",IF(ISNUMBER(SEARCH("角色抽卡券",E63)),"角色抽卡券普通",IF(ISNUMBER(SEARCH("专武抽卡券",E63)),"专武抽卡券普通",""))))) | G63: ='配置页-主线副本'!U193 -> 0 | H63: =IF(F63="",0,IF(F63="钻石",G63,G63*150)) -> 0
A64: 主线副本 | B64: 普通通关奖励 | C64: 配置页-主线副本 | D64: S197/U197 | E64: ='配置页-主线副本'!S197 -> 0 | F64: =IF(E64="钻石","钻石",IF(ISNUMBER(SEARCH("角色抽卡券限时",E64)),"角色抽卡券限时",IF(ISNUMBER(SEARCH("专武抽卡券限时",E64)),"专武抽卡券限时",IF(ISNUMBER(SEARCH("角色抽卡券",E64)),"角色抽卡券普通",IF(ISNUMBER(SEARCH("专武抽卡券",E64)),"专武抽卡券普通",""))))) | G64: ='配置页-主线副本'!U197 -> 0 | H64: =IF(F64="",0,IF(F64="钻石",G64,G64*150)) -> 0
A65: 主线副本 | B65: 普通通关奖励 | C65: 配置页-主线副本 | D65: S201/U201 | E65: ='配置页-主线副本'!S201 -> 0 | F65: =IF(E65="钻石","钻石",IF(ISNUMBER(SEARCH("角色抽卡券限时",E65)),"角色抽卡券限时",IF(ISNUMBER(SEARCH("专武抽卡券限时",E65)),"专武抽卡券限时",IF(ISNUMBER(SEARCH("角色抽卡券",E65)),"角色抽卡券普通",IF(ISNUMBER(SEARCH("专武抽卡券",E65)),"专武抽卡券普通",""))))) | G65: ='配置页-主线副本'!U201 -> 0 | H65: =IF(F65="",0,IF(F65="钻石",G65,G65*150)) -> 0
A66: 主线副本 | B66: 普通通关奖励 | C66: 配置页-主线副本 | D66: S205/U205 | E66: ='配置页-主线副本'!S205 -> 0 | F66: =IF(E66="钻石","钻石",IF(ISNUMBER(SEARCH("角色抽卡券限时",E66)),"角色抽卡券限时",IF(ISNUMBER(SEARCH("专武抽卡券限时",E66)),"专武抽卡券限时",IF(ISNUMBER(SEARCH("角色抽卡券",E66)),"角色抽卡券普通",IF(ISNUMBER(SEARCH("专武抽卡券",E66)),"专武抽卡券普通",""))))) | G66: ='配置页-主线副本'!U205 -> 0 | H66: =IF(F66="",0,IF(F66="钻石",G66,G66*150)) -> 0
A67: 主线副本 | B67: 普通通关奖励 | C67: 配置页-主线副本 | D67: S209/U209 | E67: ='配置页-主线副本'!S209 -> 0 | F67: =IF(E67="钻石","钻石",IF(ISNUMBER(SEARCH("角色抽卡券限时",E67)),"角色抽卡券限时",IF(ISNUMBER(SEARCH("专武抽卡券限时",E67)),"专武抽卡券限时",IF(ISNUMBER(SEARCH("角色抽卡券",E67)),"角色抽卡券普通",IF(ISNUMBER(SEARCH("专武抽卡券",E67)),"专武抽卡券普通",""))))) | G67: ='配置页-主线副本'!U209 -> 0 | H67: =IF(F67="",0,IF(F67="钻石",G67,G67*150)) -> 0
A68: 主线副本 | B68: 普通通关奖励 | C68: 配置页-主线副本 | D68: S21/U21 | E68: ='配置页-主线副本'!T21 -> 星盘低级道具防2 | F68: =IF(E68="钻石","钻石",IF(ISNUMBER(SEARCH("角色抽卡券限时",E68)),"角色抽卡券限时",IF(ISNUMBER(SEARCH("专武抽卡券限时",E68)),"专武抽卡券限时",IF(ISNUMBER(SEARCH("角色抽卡券",E68)),"角色抽卡券普通",IF(ISNUMBER(SEARCH("专武抽卡券",E68)),"专武抽卡券普通",""))))) | G68: ='配置页-主线副本'!#REF! -> #REF! | H68: =IF(F68="",0,IF(F68="钻石",G68,G68*150)) -> 0
A69: 主线副本 | B69: 普通通关奖励 | C69: 配置页-主线副本 | D69: S213/U213 | E69: ='配置页-主线副本'!S213 -> 0 | F69: =IF(E69="钻石","钻石",IF(ISNUMBER(SEARCH("角色抽卡券限时",E69)),"角色抽卡券限时",IF(ISNUMBER(SEARCH("专武抽卡券限时",E69)),"专武抽卡券限时",IF(ISNUMBER(SEARCH("角色抽卡券",E69)),"角色抽卡券普通",IF(ISNUMBER(SEARCH("专武抽卡券",E69)),"专武抽卡券普通",""))))) | G69: ='配置页-主线副本'!U213 -> 0 | H69: =IF(F69="",0,IF(F69="钻石",G69,G69*150)) -> 0
A70: 主线副本 | B70: 普通通关奖励 | C70: 配置页-主线副本 | D70: S217/U217 | E70: ='配置页-主线副本'!S217 -> 0 | F70: =IF(E70="钻石","钻石",IF(ISNUMBER(SEARCH("角色抽卡券限时",E70)),"角色抽卡券限时",IF(ISNUMBER(SEARCH("专武抽卡券限时",E70)),"专武抽卡券限时",IF(ISNUMBER(SEARCH("角色抽卡券",E70)),"角色抽卡券普通",IF(ISNUMBER(SEARCH("专武抽卡券",E70)),"专武抽卡券普通",""))))) | G70: ='配置页-主线副本'!U217 -> 0 | H70: =IF(F70="",0,IF(F70="钻石",G70,G70*150)) -> 0
A71: 主线副本 | B71: 普通通关奖励 | C71: 配置页-主线副本 | D71: S221/U221 | E71: ='配置页-主线副本'!S221 -> 0 | F71: =IF(E71="钻石","钻石",IF(ISNUMBER(SEARCH("角色抽卡券限时",E71)),"角色抽卡券限时",IF(ISNUMBER(SEARCH("专武抽卡券限时",E71)),"专武抽卡券限时",IF(ISNUMBER(SEARCH("角色抽卡券",E71)),"角色抽卡券普通",IF(ISNUMBER(SEARCH("专武抽卡券",E71)),"专武抽卡券普通",""))))) | G71: ='配置页-主线副本'!U221 -> 0 | H71: =IF(F71="",0,IF(F71="钻石",G71,G71*150)) -> 0
A72: 主线副本 | B72: 普通通关奖励 | C72: 配置页-主线副本 | D72: S225/U225 | E72: ='配置页-主线副本'!S225 -> 0 | F72: =IF(E72="钻石","钻石",IF(ISNUMBER(SEARCH("角色抽卡券限时",E72)),"角色抽卡券限时",IF(ISNUMBER(SEARCH("专武抽卡券限时",E72)),"专武抽卡券限时",IF(ISNUMBER(SEARCH("角色抽卡券",E72)),"角色抽卡券普通",IF(ISNUMBER(SEARCH("专武抽卡券",E72)),"专武抽卡券普通",""))))) | G72: ='配置页-主线副本'!U225 -> 0 | H72: =IF(F72="",0,IF(F72="钻石",G72,G72*150)) -> 0
A73: 主线副本 | B73: 普通通关奖励 | C73: 配置页-主线副本 | D73: S25/U25 | E73: ='配置页-主线副本'!T25 -> 金币 | F73: =IF(E73="钻石","钻石",IF(ISNUMBER(SEARCH("角色抽卡券限时",E73)),"角色抽卡券限时",IF(ISNUMBER(SEARCH("专武抽卡券限时",E73)),"专武抽卡券限时",IF(ISNUMBER(SEARCH("角色抽卡券",E73)),"角色抽卡券普通",IF(ISNUMBER(SEARCH("专武抽卡券",E73)),"专武抽卡券普通",""))))) | G73: ='配置页-主线副本'!#REF! -> #REF! | H73: =IF(F73="",0,IF(F73="钻石",G73,G73*150)) -> 0
A74: 主线副本 | B74: 普通通关奖励 | C74: 配置页-主线副本 | D74: S29/U29 | E74: ='配置页-主线副本'!T29 -> 角色经验中 | F74: =IF(E74="钻石","钻石",IF(ISNUMBER(SEARCH("角色抽卡券限时",E74)),"角色抽卡券限时",IF(ISNUMBER(SEARCH("专武抽卡券限时",E74)),"专武抽卡券限时",IF(ISNUMBER(SEARCH("角色抽卡券",E74)),"角色抽卡券普通",IF(ISNUMBER(SEARCH("专武抽卡券",E74)),"专武抽卡券普通",""))))) | G74: ='配置页-主线副本'!#REF! -> #REF! | H74: =IF(F74="",0,IF(F74="钻石",G74,G74*150)) -> 0
A75: 主线副本 | B75: 普通通关奖励 | C75: 配置页-主线副本 | D75: S33/U33 | E75: ='配置页-主线副本'!T33 -> 角色经验中 | F75: =IF(E75="钻石","钻石",IF(ISNUMBER(SEARCH("角色抽卡券限时",E75)),"角色抽卡券限时",IF(ISNUMBER(SEARCH("专武抽卡券限时",E75)),"专武抽卡券限时",IF(ISNUMBER(SEARCH("角色抽卡券",E75)),"角色抽卡券普通",IF(ISNUMBER(SEARCH("专武抽卡券",E75)),"专武抽卡券普通",""))))) | G75: ='配置页-主线副本'!#REF! -> #REF! | H75: =IF(F75="",0,IF(F75="钻石",G75,G75*150)) -> 0
A76: 主线副本 | B76: 普通通关奖励 | C76: 配置页-主线副本 | D76: S37/U37 | E76: ='配置页-主线副本'!T37 -> 角色经验中 | F76: =IF(E76="钻石","钻石",IF(ISNUMBER(SEARCH("角色抽卡券限时",E76)),"角色抽卡券限时",IF(ISNUMBER(SEARCH("专武抽卡券限时",E76)),"专武抽卡券限时",IF(ISNUMBER(SEARCH("角色抽卡券",E76)),"角色抽卡券普通",IF(ISNUMBER(SEARCH("专武抽卡券",E76)),"专武抽卡券普通",""))))) | G76: ='配置页-主线副本'!#REF! -> #REF! | H76: =IF(F76="",0,IF(F76="钻石",G76,G76*150)) -> 0
A77: 主线副本 | B77: 普通通关奖励 | C77: 配置页-主线副本 | D77: S4/U4 | E77: ='配置页-主线副本'!T4 -> 金币 | F77: =IF(E77="钻石","钻石",IF(ISNUMBER(SEARCH("角色抽卡券限时",E77)),"角色抽卡券限时",IF(ISNUMBER(SEARCH("专武抽卡券限时",E77)),"专武抽卡券限时",IF(ISNUMBER(SEARCH("角色抽卡券",E77)),"角色抽卡券普通",IF(ISNUMBER(SEARCH("专武抽卡券",E77)),"专武抽卡券普通",""))))) | G77: ='配置页-主线副本'!#REF! -> #REF! | H77: =IF(F77="",0,IF(F77="钻石",G77,G77*150)) -> 0
A78: 主线副本 | B78: 普通通关奖励 | C78: 配置页-主线副本 | D78: S40/U40 | E78: ='配置页-主线副本'!T40 -> 金币 | F78: =IF(E78="钻石","钻石",IF(ISNUMBER(SEARCH("角色抽卡券限时",E78)),"角色抽卡券限时",IF(ISNUMBER(SEARCH("专武抽卡券限时",E78)),"专武抽卡券限时",IF(ISNUMBER(SEARCH("角色抽卡券",E78)),"角色抽卡券普通",IF(ISNUMBER(SEARCH("专武抽卡券",E78)),"专武抽卡券普通",""))))) | G78: ='配置页-主线副本'!#REF! -> #REF! | H78: =IF(F78="",0,IF(F78="钻石",G78,G78*150)) -> 0
A79: 主线副本 | B79: 普通通关奖励 | C79: 配置页-主线副本 | D79: S43/U43 | E79: ='配置页-主线副本'!T43 -> 金币 | F79: =IF(E79="钻石","钻石",IF(ISNUMBER(SEARCH("角色抽卡券限时",E79)),"角色抽卡券限时",IF(ISNUMBER(SEARCH("专武抽卡券限时",E79)),"专武抽卡券限时",IF(ISNUMBER(SEARCH("角色抽卡券",E79)),"角色抽卡券普通",IF(ISNUMBER(SEARCH("专武抽卡券",E79)),"专武抽卡券普通",""))))) | G79: ='配置页-主线副本'!#REF! -> #REF! | H79: =IF(F79="",0,IF(F79="钻石",G79,G79*150)) -> 0
A80: 主线副本 | B80: 普通通关奖励 | C80: 配置页-主线副本 | D80: S46/U46 | E80: ='配置页-主线副本'!T46 -> 金币 | F80: =IF(E80="钻石","钻石",IF(ISNUMBER(SEARCH("角色抽卡券限时",E80)),"角色抽卡券限时",IF(ISNUMBER(SEARCH("专武抽卡券限时",E80)),"专武抽卡券限时",IF(ISNUMBER(SEARCH("角色抽卡券",E80)),"角色抽卡券普通",IF(ISNUMBER(SEARCH("专武抽卡券",E80)),"专武抽卡券普通",""))))) | G80: ='配置页-主线副本'!#REF! -> #REF! | H80: =IF(F80="",0,IF(F80="钻石",G80,G80*150)) -> 0
A81: 主线副本 | B81: 普通通关奖励 | C81: 配置页-主线副本 | D81: S49/U49 | E81: ='配置页-主线副本'!T49 -> 金币 | F81: =IF(E81="钻石","钻石",IF(ISNUMBER(SEARCH("角色抽卡券限时",E81)),"角色抽卡券限时",IF(ISNUMBER(SEARCH("专武抽卡券限时",E81)),"专武抽卡券限时",IF(ISNUMBER(SEARCH("角色抽卡券",E81)),"角色抽卡券普通",IF(ISNUMBER(SEARCH("专武抽卡券",E81)),"专武抽卡券普通",""))))) | G81: ='配置页-主线副本'!#REF! -> #REF! | H81: =IF(F81="",0,IF(F81="钻石",G81,G81*150)) -> 0
A82: 主线副本 | B82: 普通通关奖励 | C82: 配置页-主线副本 | D82: S52/U52 | E82: ='配置页-主线副本'!T52 -> 金币 | F82: =IF(E82="钻石","钻石",IF(ISNUMBER(SEARCH("角色抽卡券限时",E82)),"角色抽卡券限时",IF(ISNUMBER(SEARCH("专武抽卡券限时",E82)),"专武抽卡券限时",IF(ISNUMBER(SEARCH("角色抽卡券",E82)),"角色抽卡券普通",IF(ISNUMBER(SEARCH("专武抽卡券",E82)),"专武抽卡券普通",""))))) | G82: ='配置页-主线副本'!#REF! -> #REF! | H82: =IF(F82="",0,IF(F82="钻石",G82,G82*150)) -> 0
A83: 主线副本 | B83: 普通通关奖励 | C83: 配置页-主线副本 | D83: S55/U55 | E83: ='配置页-主线副本'!T55 -> 金币 | F83: =IF(E83="钻石","钻石",IF(ISNUMBER(SEARCH("角色抽卡券限时",E83)),"角色抽卡券限时",IF(ISNUMBER(SEARCH("专武抽卡券限时",E83)),"专武抽卡券限时",IF(ISNUMBER(SEARCH("角色抽卡券",E83)),"角色抽卡券普通",IF(ISNUMBER(SEARCH("专武抽卡券",E83)),"专武抽卡券普通",""))))) | G83: ='配置页-主线副本'!#REF! -> #REF! | H83: =IF(F83="",0,IF(F83="钻石",G83,G83*150)) -> 0
A84: 主线副本 | B84: 普通通关奖励 | C84: 配置页-主线副本 | D84: S59/U59 | E84: ='配置页-主线副本'!T59 -> 角色经验中 | F84: =IF(E84="钻石","钻石",IF(ISNUMBER(SEARCH("角色抽卡券限时",E84)),"角色抽卡券限时",IF(ISNUMBER(SEARCH("专武抽卡券限时",E84)),"专武抽卡券限时",IF(ISNUMBER(SEARCH("角色抽卡券",E84)),"角色抽卡券普通",IF(ISNUMBER(SEARCH("专武抽卡券",E84)),"专武抽卡券普通",""))))) | G84: ='配置页-主线副本'!#REF! -> #REF! | H84: =IF(F84="",0,IF(F84="钻石",G84,G84*150)) -> 0
A85: 主线副本 | B85: 普通通关奖励 | C85: 配置页-主线副本 | D85: S63/U63 | E85: ='配置页-主线副本'!T63 -> 角色经验中 | F85: =IF(E85="钻石","钻石",IF(ISNUMBER(SEARCH("角色抽卡券限时",E85)),"角色抽卡券限时",IF(ISNUMBER(SEARCH("专武抽卡券限时",E85)),"专武抽卡券限时",IF(ISNUMBER(SEARCH("角色抽卡券",E85)),"角色抽卡券普通",IF(ISNUMBER(SEARCH("专武抽卡券",E85)),"专武抽卡券普通",""))))) | G85: ='配置页-主线副本'!#REF! -> #REF! | H85: =IF(F85="",0,IF(F85="钻石",G85,G85*150)) -> 0
A86: 主线副本 | B86: 普通通关奖励 | C86: 配置页-主线副本 | D86: S67/U67 | E86: ='配置页-主线副本'!T67 -> 角色经验中 | F86: =IF(E86="钻石","钻石",IF(ISNUMBER(SEARCH("角色抽卡券限时",E86)),"角色抽卡券限时",IF(ISNUMBER(SEARCH("专武抽卡券限时",E86)),"专武抽卡券限时",IF(ISNUMBER(SEARCH("角色抽卡券",E86)),"角色抽卡券普通",IF(ISNUMBER(SEARCH("专武抽卡券",E86)),"专武抽卡券普通",""))))) | G86: ='配置页-主线副本'!#REF! -> #REF! | H86: =IF(F86="",0,IF(F86="钻石",G86,G86*150)) -> 0
A87: 主线副本 | B87: 普通通关奖励 | C87: 配置页-主线副本 | D87: S7/U7 | E87: ='配置页-主线副本'!T7 -> 角色经验低 | F87: =IF(E87="钻石","钻石",IF(ISNUMBER(SEARCH("角色抽卡券限时",E87)),"角色抽卡券限时",IF(ISNUMBER(SEARCH("专武抽卡券限时",E87)),"专武抽卡券限时",IF(ISNUMBER(SEARCH("角色抽卡券",E87)),"角色抽卡券普通",IF(ISNUMBER(SEARCH("专武抽卡券",E87)),"专武抽卡券普通",""))))) | G87: ='配置页-主线副本'!#REF! -> #REF! | H87: =IF(F87="",0,IF(F87="钻石",G87,G87*150)) -> 0
A88: 主线副本 | B88: 普通通关奖励 | C88: 配置页-主线副本 | D88: S71/U71 | E88: ='配置页-主线副本'!T71 -> 角色经验中 | F88: =IF(E88="钻石","钻石",IF(ISNUMBER(SEARCH("角色抽卡券限时",E88)),"角色抽卡券限时",IF(ISNUMBER(SEARCH("专武抽卡券限时",E88)),"专武抽卡券限时",IF(ISNUMBER(SEARCH("角色抽卡券",E88)),"角色抽卡券普通",IF(ISNUMBER(SEARCH("专武抽卡券",E88)),"专武抽卡券普通",""))))) | G88: ='配置页-主线副本'!#REF! -> #REF! | H88: =IF(F88="",0,IF(F88="钻石",G88,G88*150)) -> 0
A89: 主线副本 | B89: 普通通关奖励 | C89: 配置页-主线副本 | D89: S75/U75 | E89: ='配置页-主线副本'!T75 -> 星盘中级道具攻2 | F89: =IF(E89="钻石","钻石",IF(ISNUMBER(SEARCH("角色抽卡券限时",E89)),"角色抽卡券限时",IF(ISNUMBER(SEARCH("专武抽卡券限时",E89)),"专武抽卡券限时",IF(ISNUMBER(SEARCH("角色抽卡券",E89)),"角色抽卡券普通",IF(ISNUMBER(SEARCH("专武抽卡券",E89)),"专武抽卡券普通",""))))) | G89: ='配置页-主线副本'!#REF! -> #REF! | H89: =IF(F89="",0,IF(F89="钻石",G89,G89*150)) -> 0
A90: 主线副本 | B90: 普通通关奖励 | C90: 配置页-主线副本 | D90: S79/U79 | E90: ='配置页-主线副本'!T79 -> 金币 | F90: =IF(E90="钻石","钻石",IF(ISNUMBER(SEARCH("角色抽卡券限时",E90)),"角色抽卡券限时",IF(ISNUMBER(SEARCH("专武抽卡券限时",E90)),"专武抽卡券限时",IF(ISNUMBER(SEARCH("角色抽卡券",E90)),"角色抽卡券普通",IF(ISNUMBER(SEARCH("专武抽卡券",E90)),"专武抽卡券普通",""))))) | G90: ='配置页-主线副本'!#REF! -> #REF! | H90: =IF(F90="",0,IF(F90="钻石",G90,G90*150)) -> 0
A91: 主线副本 | B91: 普通通关奖励 | C91: 配置页-主线副本 | D91: S82/U82 | E91: ='配置页-主线副本'!T82 -> 金币 | F91: =IF(E91="钻石","钻石",IF(ISNUMBER(SEARCH("角色抽卡券限时",E91)),"角色抽卡券限时",IF(ISNUMBER(SEARCH("专武抽卡券限时",E91)),"专武抽卡券限时",IF(ISNUMBER(SEARCH("角色抽卡券",E91)),"角色抽卡券普通",IF(ISNUMBER(SEARCH("专武抽卡券",E91)),"专武抽卡券普通",""))))) | G91: ='配置页-主线副本'!#REF! -> #REF! | H91: =IF(F91="",0,IF(F91="钻石",G91,G91*150)) -> 0
A92: 主线副本 | B92: 普通通关奖励 | C92: 配置页-主线副本 | D92: S85/U85 | E92: ='配置页-主线副本'!T85 -> 金币 | F92: =IF(E92="钻石","钻石",IF(ISNUMBER(SEARCH("角色抽卡券限时",E92)),"角色抽卡券限时",IF(ISNUMBER(SEARCH("专武抽卡券限时",E92)),"专武抽卡券限时",IF(ISNUMBER(SEARCH("角色抽卡券",E92)),"角色抽卡券普通",IF(ISNUMBER(SEARCH("专武抽卡券",E92)),"专武抽卡券普通",""))))) | G92: ='配置页-主线副本'!#REF! -> #REF! | H92: =IF(F92="",0,IF(F92="钻石",G92,G92*150)) -> 0
A93: 主线副本 | B93: 普通通关奖励 | C93: 配置页-主线副本 | D93: S88/U88 | E93: ='配置页-主线副本'!T88 -> 金币 | F93: =IF(E93="钻石","钻石",IF(ISNUMBER(SEARCH("角色抽卡券限时",E93)),"角色抽卡券限时",IF(ISNUMBER(SEARCH("专武抽卡券限时",E93)),"专武抽卡券限时",IF(ISNUMBER(SEARCH("角色抽卡券",E93)),"角色抽卡券普通",IF(ISNUMBER(SEARCH("专武抽卡券",E93)),"专武抽卡券普通",""))))) | G93: ='配置页-主线副本'!#REF! -> #REF! | H93: =IF(F93="",0,IF(F93="钻石",G93,G93*150)) -> 0
A94: 主线副本 | B94: 普通通关奖励 | C94: 配置页-主线副本 | D94: S91/U91 | E94: ='配置页-主线副本'!T91 -> 金币 | F94: =IF(E94="钻石","钻石",IF(ISNUMBER(SEARCH("角色抽卡券限时",E94)),"角色抽卡券限时",IF(ISNUMBER(SEARCH("专武抽卡券限时",E94)),"专武抽卡券限时",IF(ISNUMBER(SEARCH("角色抽卡券",E94)),"角色抽卡券普通",IF(ISNUMBER(SEARCH("专武抽卡券",E94)),"专武抽卡券普通",""))))) | G94: ='配置页-主线副本'!#REF! -> #REF! | H94: =IF(F94="",0,IF(F94="钻石",G94,G94*150)) -> 0
A95: 主线副本 | B95: 普通通关奖励 | C95: 配置页-主线副本 | D95: S94/U94 | E95: ='配置页-主线副本'!T94 -> 金币 | F95: =IF(E95="钻石","钻石",IF(ISNUMBER(SEARCH("角色抽卡券限时",E95)),"角色抽卡券限时",IF(ISNUMBER(SEARCH("专武抽卡券限时",E95)),"专武抽卡券限时",IF(ISNUMBER(SEARCH("角色抽卡券",E95)),"角色抽卡券普通",IF(ISNUMBER(SEARCH("专武抽卡券",E95)),"专武抽卡券普通",""))))) | G95: ='配置页-主线副本'!#REF! -> #REF! | H95: =IF(F95="",0,IF(F95="钻石",G95,G95*150)) -> 0
A96: 主线副本 | B96: 普通通关奖励 | C96: 配置页-主线副本 | D96: S97/U97 | E96: ='配置页-主线副本'!T97 -> 金币 | F96: =IF(E96="钻石","钻石",IF(ISNUMBER(SEARCH("角色抽卡券限时",E96)),"角色抽卡券限时",IF(ISNUMBER(SEARCH("专武抽卡券限时",E96)),"专武抽卡券限时",IF(ISNUMBER(SEARCH("角色抽卡券",E96)),"角色抽卡券普通",IF(ISNUMBER(SEARCH("专武抽卡券",E96)),"专武抽卡券普通",""))))) | G96: ='配置页-主线副本'!#REF! -> #REF! | H96: =IF(F96="",0,IF(F96="钻石",G96,G96*150)) -> 0
A97: 主线副本 | B97: 章节/节点奖励 | C97: 配置页-主线副本 | D97: O16/Q16 | E97: ='配置页-主线副本'!O16 -> 钻石 | F97: =IF(E97="钻石","钻石",IF(ISNUMBER(SEARCH("角色抽卡券限时",E97)),"角色抽卡券限时",IF(ISNUMBER(SEARCH("专武抽卡券限时",E97)),"专武抽卡券限时",IF(ISNUMBER(SEARCH("角色抽卡券",E97)),"角色抽卡券普通",IF(ISNUMBER(SEARCH("专武抽卡券",E97)),"专武抽卡券普通",""))))) -> 钻石 | G97: ='配置页-主线副本'!Q16 -> 50 | H97: =IF(F97="",0,IF(F97="钻石",G97,G97*150)) -> 50
A98: 主线副本 | B98: 章节/节点奖励 | C98: 配置页-主线副本 | D98: O19/Q19 | E98: ='配置页-主线副本'!O19 -> 钻石 | F98: =IF(E98="钻石","钻石",IF(ISNUMBER(SEARCH("角色抽卡券限时",E98)),"角色抽卡券限时",IF(ISNUMBER(SEARCH("专武抽卡券限时",E98)),"专武抽卡券限时",IF(ISNUMBER(SEARCH("角色抽卡券",E98)),"角色抽卡券普通",IF(ISNUMBER(SEARCH("专武抽卡券",E98)),"专武抽卡券普通",""))))) -> 钻石 | G98: ='配置页-主线副本'!Q19 -> 50 | H98: =IF(F98="",0,IF(F98="钻石",G98,G98*150)) -> 50
A99: 主线副本 | B99: 章节/节点奖励 | C99: 配置页-主线副本 | D99: O22/Q22 | E99: ='配置页-主线副本'!O22 -> 钻石 | F99: =IF(E99="钻石","钻石",IF(ISNUMBER(SEARCH("角色抽卡券限时",E99)),"角色抽卡券限时",IF(ISNUMBER(SEARCH("专武抽卡券限时",E99)),"专武抽卡券限时",IF(ISNUMBER(SEARCH("角色抽卡券",E99)),"角色抽卡券普通",IF(ISNUMBER(SEARCH("专武抽卡券",E99)),"专武抽卡券普通",""))))) -> 钻石 | G99: ='配置页-主线副本'!Q22 -> 150 | H99: =IF(F99="",0,IF(F99="钻石",G99,G99*150)) -> 150
A100: 主线副本 | B100: 章节/节点奖励 | C100: 配置页-主线副本 | D100: O24/Q24 | E100: ='配置页-主线副本'!O24 -> 角色抽卡券限时 | F100: =IF(E100="钻石","钻石",IF(ISNUMBER(SEARCH("角色抽卡券限时",E100)),"角色抽卡券限时",IF(ISNUMBER(SEARCH("专武抽卡券限时",E100)),"专武抽卡券限时",IF(ISNUMBER(SEARCH("角色抽卡券",E100)),"角色抽卡券普通",IF(ISNUMBER(SEARCH("专武抽卡券",E100)),"专武抽卡券普通",""))))) -> 角色抽卡券限时 | G100: ='配置页-主线副本'!Q24 -> 3 | H100: =IF(F100="",0,IF(F100="钻石",G100,G100*150)) -> 450
A101: 主线副本 | B101: 章节/节点奖励 | C101: 配置页-主线副本 | D101: O25/Q25 | E101: ='配置页-主线副本'!O25 -> 钻石 | F101: =IF(E101="钻石","钻石",IF(ISNUMBER(SEARCH("角色抽卡券限时",E101)),"角色抽卡券限时",IF(ISNUMBER(SEARCH("专武抽卡券限时",E101)),"专武抽卡券限时",IF(ISNUMBER(SEARCH("角色抽卡券",E101)),"角色抽卡券普通",IF(ISNUMBER(SEARCH("专武抽卡券",E101)),"专武抽卡券普通",""))))) -> 钻石 | G101: ='配置页-主线副本'!Q25 -> 50 | H101: =IF(F101="",0,IF(F101="钻石",G101,G101*150)) -> 50
A102: 主线副本 | B102: 章节/节点奖励 | C102: 配置页-主线副本 | D102: O28/Q28 | E102: ='配置页-主线副本'!O28 -> 钻石 | F102: =IF(E102="钻石","钻石",IF(ISNUMBER(SEARCH("角色抽卡券限时",E102)),"角色抽卡券限时",IF(ISNUMBER(SEARCH("专武抽卡券限时",E102)),"专武抽卡券限时",IF(ISNUMBER(SEARCH("角色抽卡券",E102)),"角色抽卡券普通",IF(ISNUMBER(SEARCH("专武抽卡券",E102)),"专武抽卡券普通",""))))) -> 钻石 | G102: ='配置页-主线副本'!Q28 -> 50 | H102: =IF(F102="",0,IF(F102="钻石",G102,G102*150)) -> 50
...

Sheet 道具定价
B2: 道具备注 | C2: 道具 | D2: 道具id | E2: 道具定价(rmb) | F2: 道具定价(钻石)
A3: 外观道具 | C3: 无 | D3: 0 | E3: 0 | F3: 0
C4: 头像框 | D4: 0 | E4: 0 | F4: 0
C5: 头像 | D5: 0 | E5: 0 | F5: 0
C6: 时装 | D6: 0 | E6: 68 | F6: =E6*10 -> 680
A9: 通用资源 | C9: 体力 | D9: 3 | E9: 0.4 | F9: =E9*10 -> 4 | H9: 体力回复6分钟/1点，一天240点
C10: 钻石 | D10: 2 | E10: 0.1 | F10: =E10*10 -> 1
C11: 金币 | D11: 1 | E11: 0.0001 | F11: =E11*10 -> 0.001
C12: 玩家经验 | D12: 4 | E12: 0.04 | F12: =E12*10 -> 0.4
C13: 角色抽卡券普通 | D13: 106 | E13: 15 | F13: =E13*10 -> 150
C14: 专武抽卡券普通 | D14: 107 | E14: 15 | F14: =E14*10 -> 150
C15: 抽卡大代币 | D15: 21 | E15: 1.5 | F15: =E15*10 -> 15
C16: 抽卡小代币 | D16: 22 | E16: 0.15 | F16: =E16*10 -> 1.5
C17: 爬塔代币 | D17: 27 | E17: 0.1 | F17: =E17*10 -> 1
C18: 体力药 | D18: 105 | E18: =E9*60 -> 24 | F18: =F9*60 -> 240
C19: 竞技场代币 | D19: 19 | E19: 1 | F19: =E19*10 -> 10
C20: 角色抽卡券限时 | D20: 111 | E20: 15 | F20: =E20*10 -> 150
C21: 专武抽卡券限时 | D21: 112 | E21: 15 | F21: =E21*10 -> 150
A22: 公会 | C22: 公会个人代币 | D22: 15 | E22: 0.1 | F22: =E22*10 -> 1
C23: 公会集体代币 | D23: 14 | E23: 0.1 | F23: =E23*10 -> 1
A25: 角色升级升阶 | C25: 角色经验 | E25: 0.0001 | F25: =E25*10 -> 0.001
C26: 角色经验低500 | D26: 100 | E26: =E25*500 -> 0.05 | F26: =E26*10 -> 0.5
C27: 角色经验中2000 | D27: 101 | E27: =E25*2000 -> 0.2 | F27: =E27*10 -> 2
C28: 角色经验高10000 | D28: 102 | E28: =E25*10000 -> 1 | F28: =E28*10 -> 10
C30: 角色万能升阶材料 | E30: =E31 -> 0.4 | F30: =E30*10 -> 4
B31: 可能根据职业 分成多个类型 | C31: 角色升阶材料低 | E31: 0.4 | F31: =E31*10 -> 4
C32: 角色升阶材料中 | E32: =E31*3 -> 1.2 | F32: =E32*10 -> 12
C33: 角色升阶材料高 | E33: =E32*3 -> 3.6 | F33: =E33*10 -> 36
C34: 角色升阶材料低攻击 | D34: 1001 | E34: =E31 -> 0.4 | F34: =E34*10 -> 4
C35: 角色升阶材料中攻击 | D35: 1004 | E35: =E32 -> 1.2 | F35: =E35*10 -> 12
C36: 角色升阶材料高攻击 | D36: 1007 | E36: =E33 -> 3.6 | F36: =E36*10 -> 36
C37: 角色升阶材料低防御 | D37: 1002 | E37: =E34 -> 0.4 | F37: =E37*10 -> 4
C38: 角色升阶材料中防御 | D38: 1005 | E38: =E35 -> 1.2 | F38: =E38*10 -> 12
C39: 角色升阶材料高防御 | D39: 1008 | E39: =E36 -> 3.6 | F39: =E39*10 -> 36
C40: 角色升阶材料低辅助 | D40: 1003 | E40: =E37 -> 0.4 | F40: =E40*10 -> 4
C41: 角色升阶材料中辅助 | D41: 1006 | E41: =E38 -> 1.2 | F41: =E41*10 -> 12
C42: 角色升阶材料高辅助 | D42: 1009 | E42: =E39 -> 3.6 | F42: =E42*10 -> 36
C43: SSR角色 | E43: 750 | F43: =E43*10 -> 7500
C44: SR角色 | E44: 50 | F44: =E44*10 -> 500
C45: R角色 | E45: 9 | F45: =E45*10 -> 90
A46: 星盘 | C46: 星盘低级道具自选 | E46: =E50 -> 1 | F46: =E46*10 -> 10
C47: 星盘中级道具自选 | E47: =E51 -> 1.5 | F47: =E47*10 -> 15
C48: 星盘高级道具自选 | E48: =E52 -> 2 | F48: =E48*10 -> 20
C49: 星盘顶级道具自选 | E49: =E53 -> 2.5 | F49: =E49*10 -> 25
C50: 星盘低级道具 | E50: 1 | F50: =E50*10 -> 10
C51: 星盘中级道具 | E51: 1.5 | F51: =E51*10 -> 15
C52: 星盘高级道具 | E52: 2 | F52: =E52*10 -> 20
C53: 星盘顶级道具 | E53: 2.5 | F53: =E53*10 -> 25
C54: 星盘低级道具攻击1 | D54: 1019 | E54: =E50 -> 1 | F54: =E54*10 -> 10
C55: 星盘中级道具攻击1 | D55: 1025 | E55: =E51 -> 1.5 | F55: =E55*10 -> 15
C56: 星盘高级道具攻击1 | D56: 1031 | E56: =E52 -> 2 | F56: =E56*10 -> 20
C57: 星盘顶级道具攻击1 | D57: 1037 | E57: =E53 -> 2.5 | F57: =E57*10 -> 25
C58: 星盘低级道具攻击2 | D58: 1022 | E58: =E54 -> 1 | F58: =E58*10 -> 10
C59: 星盘中级道具攻击2 | D59: 1028 | E59: =E55 -> 1.5 | F59: =E59*10 -> 15
C60: 星盘高级道具攻击2 | D60: 1034 | E60: =E56 -> 2 | F60: =E60*10 -> 20
C61: 星盘顶级道具攻击2 | D61: 1040 | E61: =E57 -> 2.5 | F61: =E61*10 -> 25
C62: 星盘低级道具防御1 | D62: 1020 | E62: =E58 -> 1 | F62: =E62*10 -> 10
C63: 星盘中级道具防御1 | D63: 1026 | E63: =E59 -> 1.5 | F63: =E63*10 -> 15
C64: 星盘高级道具防御1 | D64: 1032 | E64: =E60 -> 2 | F64: =E64*10 -> 20
C65: 星盘顶级道具防御1 | D65: 1038 | E65: =E61 -> 2.5 | F65: =E65*10 -> 25
... C77: 星盘顶级道具辅助2 | D77: 1042 | E77: =E73 -> 2.5 | F77: =E77*10 -> 25
C78: 额外星盘点 | D78: 103 | E78: 50 | F78: =E78*10 -> 500
A79: 专武 | C79: 专武经验 | E79: 5e-05 | F79: =E79*10 -> 0.0005
C80: 专武经验低1000 | D80: 108 | E80: =E79*1000 -> 0.05 | F80: =E80*10 -> 0.5
C81: 专武经验中4000 | D81: 109 | E81: =E79*4000 -> 0.2 | F81: =E81*10 -> 2
C82: 专武经验高20000 | D82: 110 | E82: =E79*20000 -> 1 | F82: =E82*10 -> 10
C84: 专武万能突破材料 | E84: =E85 -> 0.4 | F84: =E84*10 -> 4
B85: 可能根据职业 分成多个类型 | C85: 专武突破材料低 | E85: 0.4 | F85: =E85*10 -> 4
C86: 专武突破材料中 | E86: =E85*3 -> 1.2 | F86: =E86*10 -> 12
C87: 专武突破材料高 | E87: =E86*3 -> 3.6 | F87: =E87*10 -> 36
C88: 专武突破材料低攻击 | D88: 1010 | E88: 0.4 | F88: =E88*10 -> 4
C89: 专武突破材料中攻击 | D89: 1013 | E89: =E88*3 -> 1.2 | F89: =E89*10 -> 12
C90: 专武突破材料高攻击 | D90: 1016 | E90: =E89*3 -> 3.6 | F90: =E90*10 -> 36
C91: 专武突破材料低防御 | D91: 1011 | E91: 0.4 | F91: =E91*10 -> 4
C92: 专武突破材料中防御 | D92: 1014 | E92: =E91*3 -> 1.2 | F92: =E92*10 -> 12
C93: 专武突破材料高防御 | D93: 1017 | E93: =E92*3 -> 3.6 | F93: =E93*10 -> 36
C94: 专武突破材料低辅助 | D94: 1012 | E94: 0.4 | F94: =E94*10 -> 4
C95: 专武突破材料中辅助 | D95: 1015 | E95: =E94*3 -> 1.2 | F95: =E95*10 -> 12
C96: 专武突破材料高辅助 | D96: 1018 | E96: =E95*3 -> 3.6 | F96: =E96*10 -> 36
C97: SSR专武 | E97: 500 | F97: =E97*10 -> 5000
C98: SR专武 | E98: 50 | F98: =E98*10 -> 500
C99: R专武 | E99: 13 | F99: =E99*10 -> 130
A100: 共鸣（已经废弃） | C100: 装备经验 | E100: 0.001 | F100: =E100*10 -> 0.01
C101: SSR装备 | E101: 150 | F101: =E101*10 -> 1500
C102: SSR装备随机 | E102: 150 | F102: =E102*10 -> 1500
C103: SSR装备自选 | E103: 200 | F103: =E103*10 -> 2000
C104: SR装备 | E104: 30 | F104: =E104*10 -> 300
C105: R装备 | E105: 5 | F105: =E105*10 -> 50
C106: SSR装备突破材料 | E106: =E101*1.5 -> 225 | F106: =E106*10 -> 2250
C107: SR装备突破材料 | E107: =E104*1.5 -> 45 | F107: =E107*10 -> 450
C108: R装备突破材料 | E108: =E105*1.5 -> 7.5 | F108: =E108*10 -> 75
C109: 收容物高级材料 | E109: 4 | F109: =E109*10 -> 40
C110: 收容物低级材料 | E110: 1 | F110: =E110*10 -> 10
A111: 旅券 | C111: 旅券经验 | D111: 6 | E111: 0.001 | F111: =E111*10 -> 0.01
C112: 红旅券 | E112: 5 | F112: =E112*10 -> 50
C113: 金旅券 | E113: 1 | F113: =E113*10 -> 10
C114: 紫旅券 | E114: 0.5 | F114: =E114*10 -> 5
C115: 蓝旅券 | E115: 0.2 | F115: =E115*10 -> 2
A122: 主角装备 | C122: 主角装备蓝色 | E122: =$E$144*映射装备!M32 -> 0.2 | F122: =E122*10 -> 2
C123: 主角装备紫色 | E123: =$E$144*映射装备!M33 -> 0.8 | F123: =E123*10 -> 8
...

Sheet 角色、专武、旅券掉落池
B2: 角色掉落池 | F2: 专武掉落池 | J2: 映射装备掉落池 | N2: 旅券掉落池
B3: 武将名称 | C3: 稀有度 | D3: 武将id | F3: 武将id | G3: 武将名称 | H3: 稀有度 | J3: 映射装备id | K3: 映射装备名称 | L3: 映射装备品质 | N3: 旅券id | O3: 旅券套装id | P3: 旅券名称 | Q3: 旅券部位 | R3: 旅券品质
B4: 塔拉夏 | C4: S | D4: 1003 | F4: 52001 | G4: 秩序崩解杖 | H4: S | J4: 80001 | K4: 初级魂息喷射器 | L4: 蓝 | N4: 60001 | O4: 1 | P4: 追逐天性 | Q4: 1 | R4: 蓝
B5: 陈单单 | C5: S | D5: 1005 | F5: 52002 | G5: 热寂宣告者 | H5: S | J5: 80002 | K5: 中级魂息喷射器 | L5: 紫 | N5: 60002 | O5: 1 | P5: 追逐天性 | Q5: 2 | R5: 蓝
B6: 莉莉娅 | C6: S | D6: 1006 | F6: 52003 | G6: 永恒观测甲 | H6: S | J6: 80003 | K6: 高级魂息喷射器 | L6: 金 | N6: 60003 | O6: 1 | P6: 追逐天性 | Q6: 3 | R6: 蓝
B7: 萨萨莉安 | C7: S | D7: 1007 | F7: 52004 | G7: 纯净界域盾 | H7: S | J7: 80004 | K7: 初级纳米逆变器 | L7: 蓝 | N7: 60004 | O7: 1 | P7: 追逐天性 | Q7: 4 | R7: 蓝
B8: 伊戈尔 | C8: S | D8: 1017 | F8: 52005 | G8: 命运纺锤 | H8: S | J8: 80005 | K8: 中级纳米逆变器 | L8: 紫 | N8: 60005 | O8: 1 | P8: 追逐天性 | Q8: 5 | R8: 蓝
B9: 约瑟夫 | C9: S | D9: 1009 | F9: 52006 | G9: 时光重逢契 | H9: S | J9: 80006 | K9: 高级纳米逆变器 | L9: 金 | N9: 60006 | O9: 1 | P9: 追逐天性 | Q9: 6 | R9: 蓝
B10: 夏提拉 | C10: S | D10: 1013 | F10: 52007 | G10: 虚空裂界刃 | H10: A | J10: 80007 | K10: 初级风暴射线切割器 | L10: 蓝 | N10: 60007 | O10: 1 | P10: 追逐天性 | Q10: 1 | R10: 紫
B11: 雷诺 | C11: S | D11: 1016 | F11: 52008 | G11: 永寂追猎弓 | H11: A | J11: 80008 | K11: 中级风暴射线切割器 | L11: 紫 | N11: 60008 | O11: 1 | P11: 追逐天性 | Q11: 2 | R11: 紫
B12: 瞳 | C12: S | D12: 1032 | F12: 52009 | G12: 偏折棱光盾 | H12: A | J12: 80009 | K12: 高级风暴射线切割器 | L12: 金 | N12: 60009 | O12: 1 | P12: 追逐天性 | Q12: 3 | R12: 紫
B13: 美第奇 | C13: S | D13: 1033 | F13: 52010 | G13: 归航引路铠 | H13: A | J13: 80010 | K13: 初级旋转机枪 | L13: 蓝 | N13: 60010 | O13: 1 | P13: 追逐天性 | Q13: 4 | R13: 紫
B14: 零号 | C14: S | D14: 1034 | F14: 52011 | G14: 群星导引图 | H14: A | J14: 80011 | K14: 中级旋转机枪 | L14: 紫 | N14: 60011 | O14: 1 | P14: 追逐天性 | Q14: 5 | R14: 紫
B15: 薇莱特 | C15: S | D15: 1028 | F15: 52012 | G15: 灵脉同调仪 | H15: A | J15: 80012 | K15: 高级旋转机枪 | L15: 金 | N15: 60012 | O15: 1 | P15: 追逐天性 | Q15: 6 | R15: 紫
... B21: 陈双双 | C21: A | D21: 1011 | F21: 52018 | G21: 潮汐调和铃 | H21: B | J21: 80018 | K21: 高级赤红脉冲手炮 | L21: 金 | N21: 60018 | O21: 1 | P21: 追逐天性 | Q21: 6 | R21: 金
B22: 克莉丝汀 | C22: A | D22: 1014 | J22: 80019 | K22: 初级圣光调和杖 | L22: 蓝 | N22: 60019 | O22: 1 | P22: 追逐天性 | Q22: 1 | R22: 红
B23: 阿莱克西娅 | C23: A | D23: 1015 | J23: 80020 | K23: 中级圣光调和杖 | L23: 紫 | N23: 60020 | O23: 1 | P23: 追逐天性 | Q23: 2 | R23: 红
B24: 艾德琳 | C24: A | D24: 1012 | J24: 80021 | K24: 高级圣光调和杖 | L24: 金 | N24: 60021 | O24: 1 | P24: 追逐天性 | Q24: 3 | R24: 红
B25: 薇 | C25: A | D25: 1008 | J25: 80022 | K25: 初级灾厄刻印权杖 | L25: 蓝 | N25: 60022 | O25: 1 | P25: 追逐天性 | Q25: 4 | R25: 红
B26: 埃莉诺 | C26: A | D26: 1018 | J26: 80023 | K26: 中级灾厄刻印权杖 | L26: 紫 | N26: 60023 | O26: 1 | P26: 追逐天性 | Q26: 5 | R26: 红
B27: 乔一 | C27: A | D27: 1026 | J27: 80024 | K27: 高级灾厄刻印权杖 | L27: 金 | N27: 60024 | O27: 1 | P27: 追逐天性 | Q27: 6 | R27: 红
B28: 塞拉菲娜 | C28: A | D28: 1028 | J28: 80025 | K28: 初级虚空回响法杖 | L28: 蓝 | N28: 60025 | O28: 2 | P28: 翡冷翠郊野牧场 | Q28: 1 | R28: 蓝
B29: 桑塔 | C29: A | D29: 1031 | J29: 80026 | K29: 中级虚空回响法杖 | L29: 紫 | N29: 60026 | O29: 2 | P29: 翡冷翠郊野牧场 | Q29: 2 | R29: 蓝
B30: 卡斯帕 | C30: B | D30: 1020 | J30: 80027 | K30: 高级虚空回响法杖 | L30: 金 | N30: 60027 | O30: 2 | P30: 翡冷翠郊野牧场 | Q30: 3 | R30: 蓝
B31: 梅梅 | C31: B | D31: 1021 | J31: 80028 | K31: 初级隔热战术头盔 | L31: 蓝 | N31: 60028 | O31: 2 | P31: 翡冷翠郊野牧场 | Q31: 4 | R31: 蓝
B32: 马克 | C32: B | D32: 1023 | J32: 80029 | K32: 中级隔热战术头盔 | L32: 紫 | N32: 60029 | O32: 2 | P32: 翡冷翠郊野牧场 | Q32: 5 | R32: 蓝
B33: 卡薇 | C33: B | D33: 1024 | J33: 80030 | K33: 高级隔热战术头盔 | L33: 金 | N33: 60030 | O33: 2 | P33: 翡冷翠郊野牧场 | Q33: 6 | R33: 蓝
... B37: 梅林 | C37: B | D37: 1022 | J37: 80034 | K37: 初级共生头铠 | L37: 蓝 | N37: 60034 | O37: 2 | P37: 翡冷翠郊野牧场 | Q37: 4 | R37: 紫
J38: 80035 | K38: 中级共生头铠 | L38: 紫 | N38: 60035 | O38: 2 | P38: 翡冷翠郊野牧场 | Q38: 5 | R38: 紫
J39: 80036 | K39: 高级共生头铠 | L39: 金 | N39: 60036 | O39: 2 | P39: 翡冷翠郊野牧场 | Q39: 6 | R39: 紫
J40: 80037 | K40: 初级神经链接盔 | L40: 蓝 | N40: 60037 | O40: 2 | P40: 翡冷翠郊野牧场 | Q40: 1 | R40: 金
J41: 80038 | K41: 中级神经链接盔 | L41: 紫 | N41: 60038 | O41: 2 | P41: 翡冷翠郊野牧场 | Q41: 2 | R41: 金
J42: 80039 | K42: 高级神经链接盔 | L42: 金 | N42: 60039 | O42: 2 | P42: 翡冷翠郊野牧场 | Q42: 3 | R42: 金
J43: 80040 | K43: 初级修士法帽 | L43: 蓝 | N43: 60040 | O43: 2 | P43: 翡冷翠郊野牧场 | Q43: 4 | R43: 金
J44: 80041 | K44: 中级修士法帽 | L44: 紫 | N44: 60041 | O44: 2 | P44: 翡冷翠郊野牧场 | Q44: 5 | R44: 金
J45: 80042 | K45: 高级修士法帽 | L45: 金 | N45: 60042 | O45: 2 | P45: 翡冷翠郊野牧场 | Q45: 6 | R45: 金
J46: 80043 | K46: 初级祷言法帽 | L46: 蓝 | N46: 60043 | O46: 2 | P46: 翡冷翠郊野牧场 | Q46: 1 | R46: 红
J47: 80044 | K47: 中级祷言法帽 | L47: 紫 | N47: 60044 | O47: 2 | P47: 翡冷翠郊野牧场 | Q47: 2 | R47: 红
J48: 80045 | K48: 高级祷言法帽 | L48: 金 | N48: 60045 | O48: 2 | P48: 翡冷翠郊野牧场 | Q48: 3 | R48: 红
J49: 80046 | K49: 初级动力装甲 | L49: 蓝 | N49: 60046 | O49: 2 | P49: 翡冷翠郊野牧场 | Q49: 4 | R49: 红
... J193: 80190 | K193: 不灭辉光坠 | L193: 红 | N193: 60190 | O193: 8 | P193: 星之辉 | Q193: 4 | R193: 红
N194: 60191 | O194: 8 | P194: 星之辉 | Q194: 5 | R194: 红
N195: 60192 | O195: 8 | P195: 星之辉 | Q195: 6 | R195: 红
N196: 60193 | O196: 9 | P196: 边域回声 | Q196: 1 | R196: 蓝
N197: 60194 | O197: 9 | P197: 边域回声 | Q197: 2 | R197: 蓝
N198: 60195 | O198: 9 | P198: 边域回声 | Q198: 3 | R198: 蓝
N199: 60196 | O199: 9 | P199: 边域回声 | Q199: 4 | R199: 蓝
N200: 60197 | O200: 9 | P200: 边域回声 | Q200: 5 | R200: 蓝
N201: 60198 | O201: 9 | P201: 边域回声 | Q201: 6 | R201: 蓝
N202: 60199 | O202: 9 | P202: 边域回声 | Q202: 1 | R202: 紫
N203: 60200 | O203: 9 | P203: 边域回声 | Q203: 2 | R203: 紫
N204: 60201 | O204: 9 | P204: 边域回声 | Q204: 3 | R204: 紫
N205: 60202 | O205: 9 | P205: 边域回声 | Q205: 4 | R205: 紫
... N579: 60576 | O579: 24 | P579: 易碎琉璃 | Q579: 6 | R579: 红

Sheet 角色养成汇总
B2: 模块 | C2: 所需金币 | D2: 其他材料价值
B3: 角色升级 | C3: =角色升级!L5 -> 961250 | D3: =角色升级!M4 -> 1922.5 | F3: 1 | G3: 点体力 | H3: = | I3: 4000 | J3: 金币 | K3: = | L3: 4 | M3: 钻石
B4: 角色突破 | C4: =角色升阶!H8 -> 440000 | D4: =角色升阶!F8 -> 672
B5: 角色升星 | C5: 0
B6: 专武 | C6: =专武!N3 -> 263450 | D6: =专武!O2+专武!P11 -> 1989.25
B7: 角色星盘 | C7: =角色星盘!M28 -> 1655000 | D7: =角色星盘!O28 -> 5270
B8: 旅券 | C8: =旅券!P5 -> 2400000 | D8: =旅券!Q4 -> 2400
C9: =SUM(C3:C8) -> 5719700
B10: 单角色汇总 | C10: =C9*道具定价!F11 -> 5719.7 | D10: =SUM(D3:D8) -> 12253.75 | E10: =D10+C10 -> 17973.45 | F10: =E10/4 -> 4493.3625 | G10: =F10/240 -> 18.722344
G11: =D10/240/4 -> 12.764323
B13: 主角装备 | C13: =映射装备!M24 -> 4212808 | D13: =映射装备!M23*道具定价!F144 -> 42128.08
B14: 主角装备铭文

Sheet 角色升级
B2: 等级上限 | C2: 60
J4: 单角色总经验 | L4: =MAX(E7:E76) -> 1922500 | M4: =L4*道具定价!F25 -> 1922.5 | O4: 500
J5: 单角色总金币 | L5: =MAX(G7:G76) -> 961250 | O5: 1000
B6: 等级 | C6: 相对上级提升 | D6: 每级所需经验 | E6: 总经验 | F6: 每级所需金币 | G6: 总金币 | H6: 进度 | J6: 总坑深（钻石） | L6: =L4*道具定价!F25+L5*道具定价!F11 -> 2883.75 | O6: 2000
B7: {=_xlfn.SEQUENCE(C2,1,1,1)} -> 1 | D7: 100 | E7: =SUM($D$7:D7) -> 100 | F7: =ROUND(D7*0.5,0) -> 50 | G7: =SUM($F$7:F7) -> 50 | J7: 100 | O7: 5000
B8: 2 | C8: 50 | D8: =D7+C8 -> 150 | E8: =SUM($D$7:D8) -> 250 | F8: =ROUND(D8*0.5,0) -> 75 | G8: =SUM($F$7:F8) -> 125
B9: 3 | C9: 50 | D9: =D8+C9 -> 200 | E9: =SUM($D$7:D9) -> 450 | F9: =ROUND(D9*0.5,0) -> 100 | G9: =SUM($F$7:F9) -> 225
B10: 4 | C10: 50 | D10: =D9+C10 -> 250 | E10: =SUM($D$7:D10) -> 700 | F10: =ROUND(D10*0.5,0) -> 125 | G10: =SUM($F$7:F10) -> 350
B11: 5 | C11: 50 | D11: =D10+C11 -> 300 | E11: =SUM($D$7:D11) -> 1000 | F11: =ROUND(D11*0.5,0) -> 150 | G11: =SUM($F$7:F11) -> 500
B12: 6 | C12: 100 | D12: =D11+C12 -> 400 | E12: =SUM($D$7:D12) -> 1400 | F12: =ROUND(D12*0.5,0) -> 200 | G12: =SUM($F$7:F12) -> 700
B13: 7 | C13: 100 | D13: =D12+C13 -> 500 | E13: =SUM($D$7:D13) -> 1900 | F13: =ROUND(D13*0.5,0) -> 250 | G13: =SUM($F$7:F13) -> 950
B14: 8 | C14: 100 | D14: =D13+C14 -> 600 | E14: =SUM($D$7:D14) -> 2500 | F14: =ROUND(D14*0.5,0) -> 300 | G14: =SUM($F$7:F14) -> 1250
B15: 9 | C15: 100 | D15: =D14+C15 -> 700 | E15: =SUM($D$7:D15) -> 3200 | F15: =ROUND(D15*0.5,0) -> 350 | G15: =SUM($F$7:F15) -> 1600
B16: 10 | C16: 100 | D16: =D15+C16 -> 800 | E16: =SUM($D$7:D16) -> 4000 | F16: =ROUND(D16*0.5,0) -> 400 | G16: =SUM($F$7:F16) -> 2000
B17: 11 | C17: 200 | D17: =D16+C17 -> 1000 | E17: =SUM($D$7:D17) -> 5000 | F17: =ROUND(D17*0.5,0) -> 500 | G17: =SUM($F$7:F17) -> 2500
B18: 12 | C18: 200 | D18: =D17+C18 -> 1200 | E18: =SUM($D$7:D18) -> 6200 | F18: =ROUND(D18*0.5,0) -> 600 | G18: =SUM($F$7:F18) -> 3100
B19: 13 | C19: 200 | D19: =D18+C19 -> 1400 | E19: =SUM($D$7:D19) -> 7600 | F19: =ROUND(D19*0.5,0) -> 700 | G19: =SUM($F$7:F19) -> 3800
... B66: 60 | C66: 9000 | D66: =D65+C66 -> 156800 | E66: =SUM($D$7:D66) -> 1922500 | F66: =ROUND(D66*0.5,0) -> 78400 | G66: =SUM($F$7:F66) -> 961250

Sheet 角色升阶
B3: 突破等级 | C3: 突破次数 | D3: 消耗类型1 | E3: 消耗数量1 | F3: 消耗价值1 | G3: 消耗类型2 | H3: 消耗数量2 | I3: 消耗价值2 | J3: 消耗价值总 | K3: 消耗价值总 | N3: 消耗价值总 | O3: =SUM(J4:J7) -> 1112
B4: 20 | C4: 1 | D4: 角色升阶材料低 | E4: 6 | F4: =VLOOKUP(D4,道具定价!$C:$F,4,0)*E4 -> 24 | G4: 金币 | H4: 20000 | I4: =VLOOKUP(G4,道具定价!$C:$F,4,0)*H4 -> 20 | J4: =I4+F4 -> 44
B5: 30 | C5: 2 | D5: 角色升阶材料中 | E5: 6 | F5: =VLOOKUP(D5,道具定价!$C:$F,4,0)*E5 -> 72 | G5: 金币 | H5: 60000 | I5: =VLOOKUP(G5,道具定价!$C:$F,4,0)*H5 -> 60 | J5: =I5+F5 -> 132
B6: 40 | C6: 3 | D6: 角色升阶材料中 | E6: 12 | F6: =VLOOKUP(D6,道具定价!$C:$F,4,0)*E6 -> 144 | G6: 金币 | H6: 120000 | I6: =VLOOKUP(G6,道具定价!$C:$F,4,0)*H6 -> 120 | J6: =I6+F6 -> 264
B7: 50 | C7: 4 | D7: 角色升阶材料高 | E7: 12 | F7: =VLOOKUP(D7,道具定价!$C:$F,4,0)*E7 -> 432 | G7: 金币 | H7: 240000 | I7: =VLOOKUP(G7,道具定价!$C:$F,4,0)*H7 -> 240 | J7: =I7+F7 -> 672
F8: =SUM(F4:F7) -> 672 | H8: =SUM(H4:H7) -> 440000

Sheet 角色升星、角色抽卡
H2: 基础概率 | I2: 实际概率 | K2: 首次抽到 | L2: 非首次抽到 | N2: 价值 | O2: 未抽满单抽数量 | P2: 单抽数量
B3: 角色星级 | C3: 升到下一星级需要角色 | F3: 抽卡概率设定 | G3: SSR | H3: 0.01 | I3: =1/G10 -> 0.019795656 | J3: 抽卡大代币 | K3: 2 | L3: 10 | N3: =I3*道具定价!$F$15*L3 -> 2.9693484 | O3: =L3*I3 -> 0.19795656 | P3: =L3*I3 -> 0.19795656
B4: 0 | C4: 1 | G4: SR | H4: 0.1 | I4: =K28*H4/(H3+H4) -> 0.14531023 | J4: 抽卡大代币 | K4: 1 | L4: 3 | N4: =I4*道具定价!$F$16*L4 -> 0.65389603 | O4: =I4*L4 -> 0.43593069 | P4: =L4*I4 -> 0.43593069
B5: 1 | C5: 1 | G5: R | H5: =1-H4-H3 -> 0.89 | I5: =1-I4-I3 -> 0.83489412 | J5: 抽卡小代币 | K5: 3 | L5: 6 | N5: =I5*道具定价!$F$17*L5 -> 5.0093647 | O5: =I5*L5 -> 5.0093647 | P5: =L5*I5 -> 5.0093647
B6: 2 | C6: 1 | N6: =SUM(N3:N5) -> 8.6326091
B7: 3 | C7: 1 | F7: 十连保底1个SR
B8: 4 | C8: 1 | F8: 单抽定价 | G8: 150 | H8: 钻石 | N8: 单抽代币数量 | O8: 前期 | P8: 后期 | Q8: 大后期
B9: 5 | C9: 1 | F9: 保底次数 | G9: 70 | N9: 抽卡大代币 | O9: =O4 -> 0.43593069 | P9: =P4+O3 -> 0.63388724 | Q9: =P4+P3 -> 0.63388724
B10: 6 | C10: 0 | F10: 期望次数 | G10: {=SUMPRODUCT(_xlfn.ANCHORARRAY(F16),G16:G85)} -> 50.516134 | N10: 抽卡小代币 | O10: =P5 -> 5.0093647 | P10: =P5 -> 5.0093647 | Q10: =P5 -> 5.0093647
F11: SSR角色价值 | G11: =G8*G10 -> 7577.4201 | H11: 钻石
F12: SR角色价值 | G12: =G11/H4*H3 -> 757.74201 | H12: 钻石
F13: R角色价值 | G13: =G11/H5*H3 -> 85.139552 | H13: 钻石 | J13: SR/SSR10连概率
F15: 抽卡次数 | G15: 概率 | H15: 不出概率 | J15: 抽卡次数 | K15: 概率 | L15: 不出概率
F16: {=_xlfn.SEQUENCE(G9,1,1,1)} -> 1 | G16: =$H$3 -> 0.01 | H16: =1-G16 -> 0.99 | J16: 1 | K16: =H3+H4 -> 0.11 | L16: =1-K16 -> 0.89
F17: 2 | G17: =$H$3*H16 -> 0.0099 | H17: =POWER(1-$H$3,F17) -> 0.9801 | J17: 2 | K17: =$K$16*L16 -> 0.0979 | L17: =POWER(1-K$16,J17) -> 0.7921
F18: 3 | G18: =$H$3*H17 -> 0.009801 | H18: =POWER(1-$H$3,F18) -> 0.970299 | J18: 3 | K18: =$K$16*L17 -> 0.087131 | L18: =POWER(1-K$16,J18) -> 0.704969
F19: 4 | G19: =$H$3*H18 -> 0.00970299 | H19: =POWER(1-$H$3,F19) -> 0.96059601 | J19: 4 | K19: =$K$16*L18 -> 0.07754659 | L19: =POWER(1-K$16,J19) -> 0.62742241
F20: 5 | G20: =$H$3*H19 -> 0.0096059601 | H20: =POWER(1-$H$3,F20) -> 0.95099005 | J20: 5 | K20: =$K$16*L19 -> 0.069016465 | L20: =POWER(1-K$16,J20) -> 0.55840594
F21: 6 | G21: =$H$3*H20 -> 0.0095099005 | H21: =POWER(1-$H$3,F21) -> 0.94148015 | J21: 6 | K21: =$K$16*L20 -> 0.061424654 | L21: =POWER(1-K$16,J21) -> 0.49698129
F22: 7 | G22: =$H$3*H21 -> 0.0094148015 | H22: =POWER(1-$H$3,F22) -> 0.93206535 | J22: 7 | K22: =$K$16*L21 -> 0.054667942 | L22: =POWER(1-K$16,J22) -> 0.44231335 | N22: 抽卡额外货币规则
F23: 8 | G23: =$H$3*H22 -> 0.0093206535 | H23: =POWER(1-$H$3,F23) -> 0.92274469 | J23: 8 | K23: =$K$16*L22 -> 0.048654468 | L23: =POWER(1-K$16,J23) -> 0.39365888 | N23: 抽到角色时，根据已经抽到的角色数量和角色品质给予一定的额外货币（可配置）
F24: 9 | G24: =$H$3*H23 -> 0.0092274469 | H24: =POWER(1-$H$3,F24) -> 0.91351725 | J24: 9 | K24: =$K$16*L23 -> 0.043302477 | L24: =POWER(1-K$16,J24) -> 0.3503564
F25: 10 | G25: =$H$3*H24 -> 0.0091351725 | H25: =POWER(1-$H$3,F25) -> 0.90438208 | J25: 10 | K25: =1-SUM(K16:K24) -> 0.3503564 | N25: 该额外货币可以在抽卡商店兑换道具，主要兑换的内容是部分养成材料和抽卡道具（限量）
F26: 11 | G26: =$H$3*H25 -> 0.0090438208 | H26: =POWER(1-$H$3,F26) -> 0.89533825
F27: 12 | G27: =$H$3*H26 -> 0.0089533825 | H27: =POWER(1-$H$3,F27) -> 0.88638487 | K27: {=SUMPRODUCT(J16:J25,K16:K25)} -> 6.2562073
F28: 13 | G28: =$H$3*H27 -> 0.0088638487 | H28: =POWER(1-$H$3,F28) -> 0.87752102 | K28: =1/K27 -> 0.15984125
F29: 14 | G29: =$H$3*H28 -> 0.0087752102 | H29: =POWER(1-$H$3,F29) -> 0.86874581
F30: 15 | G30: =$H$3*H29 -> 0.0086874581 | H30: =POWER(1-$H$3,F30) -> 0.86005835
F31: 16 | G31: =$H$3*H30 -> 0.0086005835 | H31: =POWER(1-$H$3,F31) -> 0.85145777
F32: 17 | G32: =$H$3*H31 -> 0.0085145777 | H32: =POWER(1-$H$3,F32) -> 0.84294319
F33: 18 | G33: =$H$3*H32 -> 0.0084294319 | H33: =POWER(1-$H$3,F33) -> 0.83451376
F34: 19 | G34: =$H$3*H33 -> 0.0083451376 | H34: =POWER(1-$H$3,F34) -> 0.82616862
F35: 20 | G35: =$H$3*H34 -> 0.0082616862 | H35: =POWER(1-$H$3,F35) -> 0.81790694
F36: 21 | G36: =$H$3*H35 -> 0.0081790694 | H36: =POWER(1-$H$3,F36) -> 0.80972787
F37: 22 | G37: =$H$3*H36 -> 0.0080972787 | H37: =POWER(1-$H$3,F37) -> 0.80163059
F38: 23 | G38: =$H$3*H37 -> 0.0080163059 | H38: =POWER(1-$H$3,F38) -> 0.79361428
F39: 24 | G39: =$H$3*H38 -> 0.0079361428 | H39: =POWER(1-$H$3,F39) -> 0.78567814
F40: 25 | G40: =$H$3*H39 -> 0.0078567814 | H40: =POWER(1-$H$3,F40) -> 0.77782136
... F84: 69 | G84: =$H$3*H83 -> 0.0050488589 | H84: =POWER(1-$H$3,F84) -> 0.49983703
F85: 70 | G85: =1-SUM(G16:G84) -> 0.49983703 | H85: =POWER(1-$H$3,F85) -> 0.49483866

Sheet 专武升星、抽卡
D2: 基础概率 | E2: 实际概率 | G2: 首次抽到 | H2: 非首次抽到 | J2: 价值 | K2: 未抽满单抽数量 | L2: 单抽数量
B3: 抽卡概率设定 | C3: SSR | D3: 0.02 | E3: =1/C13 -> 0.028471905 | F3: 抽卡大代币 | G3: 2 | H3: 6 | J3: =E3*道具定价!$F$15*H3 -> 2.5624714 | K3: =H3*E3 -> 0.17083143 | L3: =H3*E3 -> 0.17083143
C4: SR | D4: 0.13 | E4: =G38*D4/(D3+D4) -> 0.16186758 | F4: 抽卡大代币 | G4: 1 | H4: 2 | J4: =E4*道具定价!$F$16*H4 -> 0.48560275 | K4: =E4*H4 -> 0.32373517 | L4: =H4*E4 -> 0.32373517
C5: R | D5: =1-D4-D3 -> 0.85 | E5: =1-E3-E4 -> 0.80966051 | F5: 抽卡小代币 | G5: 1 | H5: 4 | J5: =E5*道具定价!$F$17*H5 -> 3.238642 | K5: =E5*H5 -> 3.238642 | L5: =H5*E5 -> 3.238642
J6: =SUM(J3:J5) -> 6.2867162
J8: 单抽代币数量 | K8: 前期 | L8: 后期 | M8: 大后期
J9: 抽卡大代币 | K9: =K4 -> 0.32373517 | L9: =L4+K3 -> 0.4945666 | M9: =L4+L3 -> 0.4945666
J10: 抽卡小代币 | K10: =L5 -> 3.238642 | L10: =L5 -> 3.238642 | M10: =L5 -> 3.238642
B11: 单抽定价 | C11: 150 | D11: 钻石
B12: 保底次数 | C12: 60 | M12: 0.5 | N12: 0.2
B13: 期望次数 | C13: {=SUMPRODUCT(_xlfn.ANCHORARRAY(B17),C17:C76)} -> 35.122343 | L13: SSR | M13: SR | N13: R
B14: SSR专武价值 | C14: =C11*C13 -> 5268.3514 | D14: 钻石 | F14: SR专武价值 | G14: =C14/D4*D3 -> 810.5156 | H14: 钻石 | J14: 专武星级 | K14: 升到下一星级需要专武 | L14: 升到下一星级需要金币 | M14: 升到下一星级需要金币 | N14: 升到下一星级需要金币
F15: R专武价值 | G15: =C14/D5*D3 -> 123.96121 | H15: 钻石 | J15: 1 | K15: 1 | L15: 10000 | M15: =L15*$M$12 -> 5000 | N15: =$N$12*L15 -> 2000
B16: 抽卡次数 | C16: 概率 | D16: 不出概率 | J16: 2 | K16: 1 | L16: 20000 | M16: =L16*$M$12 -> 10000 | N16: =$N$12*L16 -> 4000
B17: {=_xlfn.SEQUENCE(C12,1,1,1)} -> 1 | C17: =$D$3 -> 0.02 | D17: =1-C17 -> 0.98 | J17: 3 | K17: 1 | L17: 50000 | M17: =L17*$M$12 -> 25000 | N17: =$N$12*L17 -> 10000
B18: 2 | C18: =$D$3*D17 -> 0.0196 | D18: =POWER(1-$D$3,B18) -> 0.9604 | J18: 4 | K18: 1 | L18: 80000 | M18: =L18*$M$12 -> 40000 | N18: =$N$12*L18 -> 16000
B19: 3 | C19: =$D$3*D18 -> 0.019208 | D19: =POWER(1-$D$3,B19) -> 0.941192 | J19: 5 | K19: 0
B20: 4 | C20: =$D$3*D19 -> 0.01882384 | D20: =POWER(1-$D$3,B20) -> 0.92236816
B21: 5 | C21: =$D$3*D20 -> 0.018447363 | D21: =POWER(1-$D$3,B21) -> 0.9039208
B22: 6 | C22: =$D$3*D21 -> 0.018078416 | D22: =POWER(1-$D$3,B22) -> 0.88584238
B23: 7 | C23: =$D$3*D22 -> 0.017716848 | D23: =POWER(1-$D$3,B23) -> 0.86812553 | F23: SR/SSR10连概率 | L23: 1,
B24: 8 | C24: =$D$3*D23 -> 0.017362511 | D24: =POWER(1-$D$3,B24) -> 0.85076302 | L24: =_xlfn.CONCAT($L$23,L15) -> 1,10000 | M24: =_xlfn.CONCAT($L$23,M15) -> 1,5000 | N24: =_xlfn.CONCAT($L$23,N15) -> 1,2000
B25: 9 | C25: =$D$3*D24 -> 0.01701526 | D25: =POWER(1-$D$3,B25) -> 0.83374776 | F25: 抽卡次数 | G25: 概率 | H25: 不出概率 | L25: =_xlfn.CONCAT($L$23,L16) -> 1,20000 | M25: =_xlfn.CONCAT($L$23,M16) -> 1,10000 | N25: =_xlfn.CONCAT($L$23,N16) -> 1,4000
B26: 10 | C26: =$D$3*D25 -> 0.016674955 | D26: =POWER(1-$D$3,B26) -> 0.81707281 | F26: 1 | G26: =D3+D4 -> 0.15 | H26: =1-G26 -> 0.85 | L26: =_xlfn.CONCAT($L$23,L17) -> 1,50000 | M26: =_xlfn.CONCAT($L$23,M17) -> 1,25000 | N26: =_xlfn.CONCAT($L$23,N17) -> 1,10000
B27: 11 | C27: =$D$3*D26 -> 0.016341456 | D27: =POWER(1-$D$3,B27) -> 0.80073135 | F27: 2 | G27: =$G$26*H26 -> 0.1275 | H27: =POWER(1-G$26,F27) -> 0.7225 | L27: =_xlfn.CONCAT($L$23,L18) -> 1,80000 | M27: =_xlfn.CONCAT($L$23,M18) -> 1,40000 | N27: =_xlfn.CONCAT($L$23,N18) -> 1,16000
B28: 12 | C28: =$D$3*D27 -> 0.016014627 | D28: =POWER(1-$D$3,B28) -> 0.78471672 | F28: 3 | G28: =$G$26*H27 -> 0.108375 | H28: =POWER(1-G$26,F28) -> 0.614125
B29: 13 | C29: =$D$3*D28 -> 0.015694334 | D29: =POWER(1-$D$3,B29) -> 0.76902239 | F29: 4 | G29: =$G$26*H28 -> 0.09211875 | H29: =POWER(1-G$26,F29) -> 0.52200625
B30: 14 | C30: =$D$3*D29 -> 0.015380448 | D30: =POWER(1-$D$3,B30) -> 0.75364194 | F30: 5 | G30: =$G$26*H29 -> 0.078300938 | H30: =POWER(1-G$26,F30) -> 0.44370531
B31: 15 | C31: =$D$3*D30 -> 0.015072839 | D31: =POWER(1-$D$3,B31) -> 0.7385691 | F31: 6 | G31: =$G$26*H30 -> 0.066555797 | H31: =POWER(1-G$26,F31) -> 0.37714952
B32: 16 | C32: =$D$3*D31 -> 0.014771382 | D32: =POWER(1-$D$3,B32) -> 0.72379772 | F32: 7 | G32: =$G$26*H31 -> 0.056572427 | H32: =POWER(1-G$26,F32) -> 0.32057709
B33: 17 | C33: =$D$3*D32 -> 0.014475954 | D33: =POWER(1-$D$3,B33) -> 0.70932177 | F33: 8 | G33: =$G$26*H32 -> 0.048086563 | H33: =POWER(1-G$26,F33) -> 0.27249053
B34: 18 | C34: =$D$3*D33 -> 0.014186435 | D34: =POWER(1-$D$3,B34) -> 0.69513533 | F34: 9 | G34: =$G$26*H33 -> 0.040873579 | H34: =POWER(1-G$26,F34) -> 0.23161695
B35: 19 | C35: =$D$3*D34 -> 0.013902707 | D35: =POWER(1-$D$3,B35) -> 0.68123262 | F35: 10 | G35: =1-SUM(G26:G34) -> 0.23161695
B36: 20 | C36: =$D$3*D35 -> 0.013624652 | D36: =POWER(1-$D$3,B36) -> 0.66760797
B37: 21 | C37: =$D$3*D36 -> 0.013352159 | D37: =POWER(1-$D$3,B37) -> 0.65425581 | G37: {=SUMPRODUCT(F26:F35,G26:G35)} -> 5.3541706
B38: 22 | C38: =$D$3*D37 -> 0.013085116 | D38: =POWER(1-$D$3,B38) -> 0.6411707 | G38: =1/G37 -> 0.18677029
B39: 23 | C39: =$D$3*D38 -> 0.012823414 | D39: =POWER(1-$D$3,B39) -> 0.62834728
B40: 24 | C40: =$D$3*D39 -> 0.012566946 | D40: =POWER(1-$D$3,B40) -> 0.61578034
B41: 25 | C41: =$D$3*D40 -> 0.012315607 | D41: =POWER(1-$D$3,B41) -> 0.60346473
B42: 26 | C42: =$D$3*D41 -> 0.012069295 | D42: =POWER(1-$D$3,B42) -> 0.59139544
B43: 27 | C43: =$D$3*D42 -> 0.011827909 | D43: =POWER(1-$D$3,B43) -> 0.57956753
B44: 28 | C44: =$D$3*D43 -> 0.011591351 | D44: =POWER(1-$D$3,B44) -> 0.56797618
B45: 29 | C45: =$D$3*D44 -> 0.011359524 | D45: =POWER(1-$D$3,B45) -> 0.55661665
B46: 30 | C46: =$D$3*D45 -> 0.011132333 | D46: =POWER(1-$D$3,B46) -> 0.54548432
B47: 31 | C47: =$D$3*D46 -> 0.010909686 | D47: =POWER(1-$D$3,B47) -> 0.53457463
B48: 32 | C48: =$D$3*D47 -> 0.010691493 | D48: =POWER(1-$D$3,B48) -> 0.52388314
B49: 33 | C49: =$D$3*D48 -> 0.010477663 | D49: =POWER(1-$D$3,B49) -> 0.51340548
B50: 34 | C50: =$D$3*D49 -> 0.01026811 | D50: =POWER(1-$D$3,B50) -> 0.50313737
... B75: 59 | C75: =$D$3*D74 -> 0.006196442 | D75: =POWER(1-$D$3,B75) -> 0.30362566
B76: 60 | C76: =1-SUM(C17:C75) -> 0.30362566 | D76: =POWER(1-$D$3,B76) -> 0.29755314

Sheet 旅券
B2: 等级上限 | C2: 60 | E2: 装备总数 | F2: 6 | H2: 每点经验所需金币 | I2: 10
B4: 等级 | C4: 提升系数 | D4: 每级所需经验 | E4: 总经验 | F4: 每级所需金币 | G4: 总金币 | J4: 单旅券总经验 | K4: =MAX(E5:E9) -> 40000 | L4: =道具定价!$F$111*K4 -> 400 | O4: 6旅券总经验 | P4: =K4*6 -> 240000 | Q4: =道具定价!$F$111*P4 -> 2400
B5: 1 | D5: 1000 | E5: =SUM($D$5:D5) -> 1000 | F5: =D5*$I$2 -> 10000 | G5: =SUM($F$5:F5) -> 10000 | J5: 单旅券总金币 | K5: =MAX(G5:G9) -> 400000 | L5: =K5*道具定价!$F$11 -> 400 | O5: 6旅券总金币 | P5: =K5*6 -> 2400000 | Q5: =P5*道具定价!$F$11 -> 2400
B6: 2 | C6: 3 | D6: =C6*D5 -> 3000 | E6: =SUM($D$5:D6) -> 4000 | F6: =D6*$I$2 -> 30000 | G6: =SUM($F$5:F6) -> 40000 | J6: 单旅券总坑深（钻石） | L6: =SUM(L4:L5) -> 800 | O6: 6旅券总坑深（钻石） | Q6: =SUM(P4:P5) -> 2640000
B7: 3 | C7: 2 | D7: =C7*D6 -> 6000 | E7: =SUM($D$5:D7) -> 10000 | F7: =D7*$I$2 -> 60000 | G7: =SUM($F$5:F7) -> 100000
B8: 4 | C8: 2 | D8: =C8*D7 -> 12000 | E8: =SUM($D$5:D8) -> 22000 | F8: =D8*$I$2 -> 120000 | G8: =SUM($F$5:F8) -> 220000
B9: 5 | C9: 1.5 | D9: =C9*D8 -> 18000 | E9: =SUM($D$5:D9) -> 40000 | F9: =D9*$I$2 -> 180000 | G9: =SUM($F$5:F9) -> 400000
B12: 品质 | C12: 品质系数
B13: 红 | C13: 1
B14: 金 | C14: 0.8
B15: 紫 | C15: 0.6
B16: 蓝 | C16: 0.4
B18: 红 | F18: 金 | J18: 紫 | N18: 蓝
B19: 等级 | C19: 提升系数 | D19: 每级所需经验 | E19: 每级所需金币 | F19: 等级 | G19: 提升系数 | H19: 每级所需经验 | I19: 每级所需金币 | J19: 等级 | K19: 提升系数 | L19: 每级所需经验 | M19: 每级所需金币 | N19: 等级 | O19: 提升系数 | P19: 每级所需经验 | Q19: 每级所需金币
B20: 1 | D20: =D5*$C$13 -> 1000 | E20: =G5*$C$13 -> 10000 | F20: 1 | H20: =$D5*$C$14 -> 800 | I20: =$F5*$C$14 -> 8000 | J20: 1 | L20: =$D5*$C$15 -> 600 | M20: =$F5*$C$15 -> 6000 | N20: 1 | P20: =$D5*$C$16 -> 400 | Q20: =$F5*$C$16 -> 4000
B21: 2 | C21: 3 | D21: =D6*$C$13 -> 3000 | E21: =G6*$C$13 -> 40000 | F21: 2 | G21: 3 | H21: =$D6*$C$14 -> 2400 | I21: =$F6*$C$14 -> 24000 | J21: 2 | K21: 3 | L21: =$D6*$C$15 -> 1800 | M21: =$F6*$C$15 -> 18000 | N21: 2 | O21: 3 | P21: =$D6*$C$16 -> 1200 | Q21: =$F6*$C$16 -> 12000
B22: 3 | C22: 2 | D22: =D7*$C$13 -> 6000 | E22: =G7*$C$13 -> 100000 | F22: 3 | G22: 2 | H22: =$D7*$C$14 -> 4800 | I22: =$F7*$C$14 -> 48000 | J22: 3 | K22: 2 | L22: =$D7*$C$15 -> 3600 | M22: =$F7*$C$15 -> 36000 | N22: 3 | O22: 2 | P22: =$D7*$C$16 -> 2400 | Q22: =$F7*$C$16 -> 24000
B23: 4 | C23: 2 | D23: =D8*$C$13 -> 12000 | E23: =G8*$C$13 -> 220000 | F23: 4 | G23: 2 | H23: =$D8*$C$14 -> 9600 | I23: =$F8*$C$14 -> 96000 | J23: 4 | K23: 2 | L23: =$D8*$C$15 -> 7200 | M23: =$F8*$C$15 -> 72000 | N23: 4 | O23: 2 | P23: =$D8*$C$16 -> 4800 | Q23: =$F8*$C$16 -> 48000
B24: 5 | C24: 1.5 | D24: =D9*$C$13 -> 18000 | E24: =G9*$C$13 -> 400000 | F24: 5 | G24: 1.5 | H24: =$D9*$C$14 -> 14400 | I24: =$F9*$C$14 -> 144000 | J24: 5 | K24: 1.5 | L24: =$D9*$C$15 -> 10800 | M24: =$F9*$C$15 -> 108000 | N24: 5 | O24: 1.5 | P24: =$D9*$C$16 -> 7200 | Q24: =$F9*$C$16 -> 72000
B26: 分解得旅券经验
B27: 品质 | C27: 经验 | D27: 额外道具
B28: 红 | C28: =道具定价!F112/道具定价!$F$111 -> 5000 | D28: 无
B29: 金 | C29: =道具定价!F113/道具定价!$F$111 -> 1000 | D29: 无
B30: 紫 | C30: =道具定价!F114/道具定价!$F$111 -> 500 | D30: 无
B31: 蓝 | C31: =道具定价!F115/道具定价!$F$111 -> 200 | D31: 无

Sheet 专武
B2: 等级上限 | C2: 60 | L2: 单角色总经验 | N2: =MAX(E7:E76) -> 2634500 | O2: =N2*道具定价!F79 -> 1317.25
L3: 单角色总金币 | N3: =MAX(G7:G76) -> 263450
L4: 总坑深（钻石） | N4: =N2*道具定价!F79+N3*道具定价!F11 -> 1580.7
H5: 0.8 | I5: 0.7
B6: 等级 | C6: 相对上级提升 | D6: 每级所需经验 | E6: 总经验 | F6: 每级所需金币 | G6: 总金币 | H6: SR每级所需经验 | I6: R每级所需经验 | L6: 突破等级 | M6: 突破次数 | N6: 消耗类型1 | O6: 消耗数量1 | P6: 消耗价值1 | Q6: 消耗类型2 | R6: 消耗数量2 | S6: 消耗价值2 | T6: 消耗价值总
B7: {=_xlfn.SEQUENCE(C2,1,1,1)} -> 1 | D7: 100 | E7: =SUM($D$7:D7) -> 100 | F7: =ROUND(D7/10,-1) -> 10 | G7: =SUM($F$7:F7) -> 10 | H7: =ROUND(D7*$H$5,0) -> 80 | I7: =ROUND(D7*$I$5,0) -> 70 | L7: 20 | M7: 1 | N7: 角色升阶材料低 | O7: 6 | P7: =VLOOKUP(N7,道具定价!$C:$F,4,0)*O7 -> 24 | Q7: 金币 | R7: 20000 | S7: =VLOOKUP(Q7,道具定价!$C:$F,4,0)*R7 -> 20 | T7: =S7+P7 -> 44
B8: 2 | C8: 100 | D8: =D7+C8 -> 200 | E8: =SUM($D$7:D8) -> 300 | F8: =ROUND(D8/10,-1) -> 20 | G8: =SUM($F$7:F8) -> 30 | H8: =ROUND(D8*$H$5,0) -> 160 | I8: =ROUND(D8*$I$5,0) -> 140 | L8: 30 | M8: 2 | N8: 角色升阶材料中 | O8: 6 | P8: =VLOOKUP(N8,道具定价!$C:$F,4,0)*O8 -> 72 | Q8: 金币 | R8: 50000 | S8: =VLOOKUP(Q8,道具定价!$C:$F,4,0)*R8 -> 50 | T8: =S8+P8 -> 122
B9: 3 | C9: 100 | D9: =D8+C9 -> 300 | E9: =SUM($D$7:D9) -> 600 | F9: =ROUND(D9/10,-1) -> 30 | G9: =SUM($F$7:F9) -> 60 | H9: =ROUND(D9*$H$5,0) -> 240 | I9: =ROUND(D9*$I$5,0) -> 210 | L9: 40 | M9: 3 | N9: 角色升阶材料中 | O9: 12 | P9: =VLOOKUP(N9,道具定价!$C:$F,4,0)*O9 -> 144 | Q9: 金币 | R9: 100000 | S9: =VLOOKUP(Q9,道具定价!$C:$F,4,0)*R9 -> 100 | T9: =S9+P9 -> 244
B10: 4 | C10: 100 | D10: =D9+C10 -> 400 | E10: =SUM($D$7:D10) -> 1000 | F10: =ROUND(D10/10,-1) -> 40 | G10: =SUM($F$7:F10) -> 100 | H10: =ROUND(D10*$H$5,0) -> 320 | I10: =ROUND(D10*$I$5,0) -> 280 | L10: 50 | M10: 4 | N10: 角色升阶材料高 | O10: 12 | P10: =VLOOKUP(N10,道具定价!$C:$F,4,0)*O10 -> 432 | Q10: 金币 | R10: 200000 | S10: =VLOOKUP(Q10,道具定价!$C:$F,4,0)*R10 -> 200 | T10: =S10+P10 -> 632
B11: 5 | C11: 100 | D11: =D10+C11 -> 500 | E11: =SUM($D$7:D11) -> 1500 | F11: =ROUND(D11/10,-1) -> 50 | G11: =SUM($F$7:F11) -> 150 | H11: =ROUND(D11*$H$5,0) -> 400 | I11: =ROUND(D11*$I$5,0) -> 350 | P11: =SUM(P7:P10) -> 672 | R11: =SUM(R7:R10) -> 370000
B12: 6 | C12: 200 | D12: =D11+C12 -> 700 | E12: =SUM($D$7:D12) -> 2200 | F12: =ROUND(D12/10,-1) -> 70 | G12: =SUM($F$7:F12) -> 220 | H12: =ROUND(D12*$H$5,0) -> 560 | I12: =ROUND(D12*$I$5,0) -> 490
B13: 7 | C13: 200 | D13: =D12+C13 -> 900 | E13: =SUM($D$7:D13) -> 3100 | F13: =ROUND(D13/10,-1) -> 90 | G13: =SUM($F$7:F13) -> 310 | H13: =ROUND(D13*$H$5,0) -> 720 | I13: =ROUND(D13*$I$5,0) -> 630
B14: 8 | C14: 200 | D14: =D13+C14 -> 1100 | E14: =SUM($D$7:D14) -> 4200 | F14: =ROUND(D14/10,-1) -> 110 | G14: =SUM($F$7:F14) -> 420 | H14: =ROUND(D14*$H$5,0) -> 880 | I14: =ROUND(D14*$I$5,0) -> 770
B15: 9 | C15: 200 | D15: =D14+C15 -> 1300 | E15: =SUM($D$7:D15) -> 5500 | F15: =ROUND(D15/10,-1) -> 130 | G15: =SUM($F$7:F15) -> 550 | H15: =ROUND(D15*$H$5,0) -> 1040 | I15: =ROUND(D15*$I$5,0) -> 910 | M15: 作为素材经验
B16: 10 | C16: 200 | D16: =D15+C16 -> 1500 | E16: =SUM($D$7:D16) -> 7000 | F16: =ROUND(D16/10,-1) -> 150 | G16: =SUM($F$7:F16) -> 700 | H16: =ROUND(D16*$H$5,0) -> 1200 | I16: =ROUND(D16*$I$5,0) -> 1050 | L16: R | M16: 5000
B17: 11 | C17: 400 | D17: =D16+C17 -> 1900 | E17: =SUM($D$7:D17) -> 8900 | F17: =ROUND(D17/10,-1) -> 190 | G17: =SUM($F$7:F17) -> 890 | H17: =ROUND(D17*$H$5,0) -> 1520 | I17: =ROUND(D17*$I$5,0) -> 1330 | L17: SR | M17: 10000
B18: 12 | C18: 400 | D18: =D17+C18 -> 2300 | E18: =SUM($D$7:D18) -> 11200 | F18: =ROUND(D18/10,-1) -> 230 | G18: =SUM($F$7:F18) -> 1120 | H18: =ROUND(D18*$H$5,0) -> 1840 | I18: =ROUND(D18*$I$5,0) -> 1610 | L18: SSR | M18: 50000
B19: 13 | C19: 400 | D19: =D18+C19 -> 2700 | E19: =SUM($D$7:D19) -> 13900 | F19: =ROUND(D19/10,-1) -> 270 | G19: =SUM($F$7:F19) -> 1390 | H19: =ROUND(D19*$H$5,0) -> 2160 | I19: =ROUND(D19*$I$5,0) -> 1890
B20: 14 | C20: 400 | D20: =D19+C20 -> 3100 | E20: =SUM($D$7:D20) -> 17000 | F20: =ROUND(D20/10,-1) -> 310 | G20: =SUM($F$7:F20) -> 1700 | H20: =ROUND(D20*$H$5,0) -> 2480 | I20: =ROUND(D20*$I$5,0) -> 2170
B21: 15 | C21: 400 | D21: =D20+C21 -> 3500 | E21: =SUM($D$7:D21) -> 20500 | F21: =ROUND(D21/10,-1) -> 350 | G21: =SUM($F$7:F21) -> 2050 | H21: =ROUND(D21*$H$5,0) -> 2800 | I21: =ROUND(D21*$I$5,0) -> 2450
B22: 16 | C22: 600 | D22: =D21+C22 -> 4100 | E22: =SUM($D$7:D22) -> 24600 | F22: =ROUND(D22/10,-1) -> 410 | G22: =SUM($F$7:F22) -> 2460 | H22: =ROUND(D22*$H$5,0) -> 3280 | I22: =ROUND(D22*$I$5,0) -> 2870
B23: 17 | C23: 600 | D23: =D22+C23 -> 4700 | E23: =SUM($D$7:D23) -> 29300 | F23: =ROUND(D23/10,-1) -> 470 | G23: =SUM($F$7:F23) -> 2930 | H23: =ROUND(D23*$H$5,0) -> 3760 | I23: =ROUND(D23*$I$5,0) -> 3290
B24: 18 | C24: 600 | D24: =D23+C24 -> 5300 | E24: =SUM($D$7:D24) -> 34600 | F24: =ROUND(D24/10,-1) -> 530 | G24: =SUM($F$7:F24) -> 3460 | H24: =ROUND(D24*$H$5,0) -> 4240 | I24: =ROUND(D24*$I$5,0) -> 3710
B25: 19 | C25: 600 | D25: =D24+C25 -> 5900 | E25: =SUM($D$7:D25) -> 40500 | F25: =ROUND(D25/10,-1) -> 590 | G25: =SUM($F$7:F25) -> 4050 | H25: =ROUND(D25*$H$5,0) -> 4720 | I25: =ROUND(D25*$I$5,0) -> 4130
B26: 20 | C26: 600 | D26: =D25+C26 -> 6500 | E26: =SUM($D$7:D26) -> 47000 | F26: =ROUND(D26/10,-1) -> 650 | G26: =SUM($F$7:F26) -> 4700 | H26: =ROUND(D26*$H$5,0) -> 5200 | I26: =ROUND(D26*$I$5,0) -> 4550
B27: 21 | C27: 1000 | D27: =D26+C27 -> 7500 | E27: =SUM($D$7:D27) -> 54500 | F27: =ROUND(D27/10,-1) -> 750 | G27: =SUM($F$7:F27) -> 5450 | H27: =ROUND(D27*$H$5,0) -> 6000 | I27: =ROUND(D27*$I$5,0) -> 5250
B28: 22 | C28: 1000 | D28: =D27+C28 -> 8500 | E28: =SUM($D$7:D28) -> 63000 | F28: =ROUND(D28/10,-1) -> 850 | G28: =SUM($F$7:F28) -> 6300 | H28: =ROUND(D28*$H$5,0) -> 6800 | I28: =ROUND(D28*$I$5,0) -> 5950
B29: 23 | C29: 1000 | D29: =D28+C29 -> 9500 | E29: =SUM($D$7:D29) -> 72500 | F29: =ROUND(D29/10,-1) -> 950 | G29: =SUM($F$7:F29) -> 7250 | H29: =ROUND(D29*$H$5,0) -> 7600 | I29: =ROUND(D29*$I$5,0) -> 6650
B30: 24 | C30: 1000 | D30: =D29+C30 -> 10500 | E30: =SUM($D$7:D30) -> 83000 | F30: =ROUND(D30/10,-1) -> 1050 | G30: =SUM($F$7:F30) -> 8300 | H30: =ROUND(D30*$H$5,0) -> 8400 | I30: =ROUND(D30*$I$5,0) -> 7350
... B66: 60 | C66: 9000 | D66: =D65+C66 -> 174000 | E66: =SUM($D$7:D66) -> 2634500 | F66: =ROUND(D66/10,-1) -> 17400 | G66: =SUM($F$7:F66) -> 263450 | H66: =ROUND(D66*$H$5,0) -> 139200 | I66: =ROUND(D66*$I$5,0) -> 121800

Sheet 角色星盘
B2: 总点数 | D2: 免费点数 | E2: 额外点数 | I2: 等级限制 | J2: 总点数
B3: 27 | D3: 21 | E3: =B3-D3 -> 6 | H3: 外圈 | I3: 40 | J3: 9
H4: 中圈 | I4: 30 | J4: 9
H5: 内圈 | I5: 20 | J5: 9
B6: 星盘点数 | C6: 限制等级 | D6: 材料1 | E6: 数量1 | F6: 材料2 | G6: 数量2 | H6: 材料3 | I6: 数量3 | J6: 材料4 | K6: 数量4 | L6: 金币 | M6: 金币美化 | N6: 价值(钻石)
B7: {=_xlfn.SEQUENCE(D3,1,1,1)} -> 1 | C7: 1 | D7: 星盘低级道具 | E7: 1 | F7: 星盘低级道具 | G7: =E7 -> 1 | L7: 5000 | M7: =MROUND(L7,5000) -> 5000 | N7: =2*VLOOKUP(D7,道具定价!$C:$F,4,0)*E7+M7*道具定价!$F$11 -> 25
B8: 2 | C8: 1 | D8: 星盘低级道具 | E8: 2 | F8: 星盘低级道具 | G8: =E8 -> 2 | L8: =L7*1.23 -> 6150 | M8: =MROUND(L8,5000) -> 5000 | N8: =2*VLOOKUP(D8,道具定价!$C:$F,4,0)*E8+M8*道具定价!$F$11 -> 45
B9: 3 | C9: 20 | D9: 星盘低级道具 | E9: 2 | F9: 星盘低级道具 | G9: =E9 -> 2 | L9: =L8*1.23 -> 7564.5 | M9: =MROUND(L9,5000) -> 10000 | N9: =2*VLOOKUP(D9,道具定价!$C:$F,4,0)*E9+M9*道具定价!$F$11 -> 50
B10: 4 | C10: 20 | D10: 星盘低级道具 | E10: 3 | F10: 星盘低级道具 | G10: =E10 -> 3 | L10: =L9*1.23 -> 9304.335 | M10: =MROUND(L10,5000) -> 10000 | N10: =2*VLOOKUP(D10,道具定价!$C:$F,4,0)*E10+M10*道具定价!$F$11 -> 70
B11: 5 | C11: 20 | D11: 星盘低级道具 | E11: 4 | F11: 星盘低级道具 | G11: =E11 -> 4 | L11: =L10*1.23 -> 11444.332 | M11: =MROUND(L11,5000) -> 10000 | N11: =2*VLOOKUP(D11,道具定价!$C:$F,4,0)*E11+M11*道具定价!$F$11 -> 90
B12: 6 | C12: 30 | D12: 星盘低级道具 | E12: 4 | F12: 星盘低级道具 | G12: =E12 -> 4 | L12: =L11*1.23 -> 14076.528 | M12: =MROUND(L12,5000) -> 15000 | N12: =2*VLOOKUP(D12,道具定价!$C:$F,4,0)*E12+M12*道具定价!$F$11 -> 95
B13: 7 | C13: 30 | D13: 星盘低级道具 | E13: 5 | F13: 星盘低级道具 | G13: =E13 -> 5 | L13: =L12*1.23 -> 17314.13 | M13: =MROUND(L13,5000) -> 15000 | N13: =2*VLOOKUP(D13,道具定价!$C:$F,4,0)*E13+M13*道具定价!$F$11 -> 115
B14: 8 | C14: 30 | D14: 星盘低级道具 | E14: 5 | F14: 星盘低级道具 | G14: =E14 -> 5 | L14: =L13*1.23 -> 21296.38 | M14: =MROUND(L14,5000) -> 20000 | N14: =2*VLOOKUP(D14,道具定价!$C:$F,4,0)*E14+M14*道具定价!$F$11 -> 120
B15: 9 | C15: 40 | D15: 星盘中级道具 | E15: 5 | F15: 星盘中级道具 | G15: =E15 -> 5 | L15: =L14*1.23 -> 26194.547 | M15: =MROUND(L15,5000) -> 25000 | N15: =2*VLOOKUP(D15,道具定价!$C:$F,4,0)*E15+M15*道具定价!$F$11 -> 175
B16: 10 | C16: 40 | D16: 星盘中级道具 | E16: 6 | F16: 星盘中级道具 | G16: =E16 -> 6 | L16: =L15*1.23 -> 32219.293 | M16: =MROUND(L16,5000) -> 30000 | N16: =2*VLOOKUP(D16,道具定价!$C:$F,4,0)*E16+M16*道具定价!$F$11 -> 210
B17: 11 | C17: 40 | D17: 星盘中级道具 | E17: 6 | F17: 星盘中级道具 | G17: =E17 -> 6 | L17: =L16*1.23 -> 39629.73 | M17: =MROUND(L17,5000) -> 40000 | N17: =2*VLOOKUP(D17,道具定价!$C:$F,4,0)*E17+M17*道具定价!$F$11 -> 220
B18: 12 | C18: 40 | D18: 星盘中级道具 | E18: 7 | F18: 星盘中级道具 | G18: =E18 -> 7 | L18: =L17*1.23 -> 48744.568 | M18: =MROUND(L18,5000) -> 50000 | N18: =2*VLOOKUP(D18,道具定价!$C:$F,4,0)*E18+M18*道具定价!$F$11 -> 260
B19: 13 | C19: 40 | D19: 星盘中级道具 | E19: 8 | F19: 星盘中级道具 | G19: =E19 -> 8 | L19: =L18*1.23 -> 59955.819 | M19: =MROUND(L19,5000) -> 60000 | N19: =2*VLOOKUP(D19,道具定价!$C:$F,4,0)*E19+M19*道具定价!$F$11 -> 300
... B27: 21 | C27: 60 | D27: 星盘顶级道具 | E27: 15 | F27: 星盘顶级道具 | G27: =E27 -> 15 | L27: =L26*1.23 -> 314103.11 | M27: =MROUND(L27,5000) -> 315000 | N27: =2*VLOOKUP(D27,道具定价!$C:$F,4,0)*E27+M27*道具定价!$F$11 -> 1065
M28: =SUM(M7:M27) -> 1655000 | N28: =SUM(N7:N27) -> 6925 | O28: =N28-M28*道具定价!F11 -> 5270 | P28: =O28/4 -> 1317.5 | Q28: 体力
E31: 攻击 | F31: 防御 | G31: 辅助
D32: 星盘低级道具 | E32: 1019 | F32: =E32+1 -> 1020 | G32: =F32+1 -> 1021
D33: 星盘中级道具 | E33: =E32+6 -> 1025 | F33: =E33+1 -> 1026 | G33: =F33+1 -> 1027
D34: 星盘高级道具 | E34: =E33+6 -> 1031 | F34: =E34+1 -> 1032 | G34: =F34+1 -> 1033
D35: 星盘顶级道具 | E35: =E34+6 -> 1037 | F35: =E35+1 -> 1038 | G35: =F35+1 -> 1039
E37: , | F37: ; | H37: 1,
D38: =VLOOKUP(D7,$D$32:$G$35,2,0) -> 1019 | E38: =D38+3 -> 1022 | F38: =CONCATENATE(D38,$E$37,E7,$F$37,E38,$E$37,G7) -> 1019,1;1022,1 | H38: =CONCATENATE($H$37,M7) -> 1,5000 | I38: =_xlfn.CONCAT(F38,$F$37,H38) -> 1019,1;1022,1;1,5000
D39: =VLOOKUP(D8,$D$32:$G$35,2,0) -> 1019 | E39: =D39+3 -> 1022 | F39: =CONCATENATE(D39,$E$37,E8,$F$37,E39,$E$37,G8) -> 1019,2;1022,2 | H39: =CONCATENATE($H$37,M8) -> 1,5000 | I39: =_xlfn.CONCAT(F39,$F$37,H39) -> 1019,2;1022,2;1,5000
D40: =VLOOKUP(D9,$D$32:$G$35,2,0) -> 1019 | E40: =D40+3 -> 1022 | F40: =CONCATENATE(D40,$E$37,E9,$F$37,E40,$E$37,G9) -> 1019,2;1022,2 | H40: =CONCATENATE($H$37,M9) -> 1,10000 | I40: =_xlfn.CONCAT(F40,$F$37,H40) -> 1019,2;1022,2;1,10000
D41: =VLOOKUP(D10,$D$32:$G$35,2,0) -> 1019 | E41: =D41+3 -> 1022 | F41: =CONCATENATE(D41,$E$37,E10,$F$37,E41,$E$37,G10) -> 1019,3;1022,3 | H41: =CONCATENATE($H$37,M10) -> 1,10000 | I41: =_xlfn.CONCAT(F41,$F$37,H41) -> 1019,3;1022,3;1,10000
D42: =VLOOKUP(D11,$D$32:$G$35,2,0) -> 1019 | E42: =D42+3 -> 1022 | F42: =CONCATENATE(D42,$E$37,E11,$F$37,E42,$E$37,G11) -> 1019,4;1022,4 | H42: =CONCATENATE($H$37,M11) -> 1,10000 | I42: =_xlfn.CONCAT(F42,$F$37,H42) -> 1019,4;1022,4;1,10000
D43: =VLOOKUP(D12,$D$32:$G$35,2,0) -> 1019 | E43: =D43+3 -> 1022 | F43: =CONCATENATE(D43,$E$37,E12,$F$37,E43,$E$37,G12) -> 1019,4;1022,4 | H43: =CONCATENATE($H$37,M12) -> 1,15000 | I43: =_xlfn.CONCAT(F43,$F$37,H43) -> 1019,4;1022,4;1,15000
D44: =VLOOKUP(D13,$D$32:$G$35,2,0) -> 1019 | E44: =D44+3 -> 1022 | F44: =CONCATENATE(D44,$E$37,E13,$F$37,E44,$E$37,G13) -> 1019,5;1022,5 | H44: =CONCATENATE($H$37,M13) -> 1,15000 | I44: =_xlfn.CONCAT(F44,$F$37,H44) -> 1019,5;1022,5;1,15000
D45: =VLOOKUP(D14,$D$32:$G$35,2,0) -> 1019 | E45: =D45+3 -> 1022 | F45: =CONCATENATE(D45,$E$37,E14,$F$37,E45,$E$37,G14) -> 1019,5;1022,5 | H45: =CONCATENATE($H$37,M14) -> 1,20000 | I45: =_xlfn.CONCAT(F45,$F$37,H45) -> 1019,5;1022,5;1,20000
D46: =VLOOKUP(D15,$D$32:$G$35,2,0) -> 1025 | E46: =D46+3 -> 1028 | F46: =CONCATENATE(D46,$E$37,E15,$F$37,E46,$E$37,G15) -> 1025,5;1028,5 | H46: =CONCATENATE($H$37,M15) -> 1,25000 | I46: =_xlfn.CONCAT(F46,$F$37,H46) -> 1025,5;1028,5;1,25000
D47: =VLOOKUP(D16,$D$32:$G$35,2,0) -> 1025 | E47: =D47+3 -> 1028 | F47: =CONCATENATE(D47,$E$37,E16,$F$37,E47,$E$37,G16) -> 1025,6;1028,6 | H47: =CONCATENATE($H$37,M16) -> 1,30000 | I47: =_xlfn.CONCAT(F47,$F$37,H47) -> 1025,6;1028,6;1,30000
D48: =VLOOKUP(D17,$D$32:$G$35,2,0) -> 1025 | E48: =D48+3 -> 1028 | F48: =CONCATENATE(D48,$E$37,E17,$F$37,E48,$E$37,G17) -> 1025,6;1028,6 | H48: =CONCATENATE($H$37,M17) -> 1,40000 | I48: =_xlfn.CONCAT(F48,$F$37,H48) -> 1025,6;1028,6;1,40000
D49: =VLOOKUP(D18,$D$32:$G$35,2,0) -> 1025 | E49: =D49+3 -> 1028 | F49: =CONCATENATE(D49,$E$37,E18,$F$37,E49,$E$37,G18) -> 1025,7;1028,7 | H49: =CONCATENATE($H$37,M18) -> 1,50000 | I49: =_xlfn.CONCAT(F49,$F$37,H49) -> 1025,7;1028,7;1,50000
... D58: =VLOOKUP(D27,$D$32:$G$35,2,0) -> 1037 | E58: =D58+3 -> 1040 | F58: =CONCATENATE(D58,$E$37,E27,$F$37,E58,$E$37,G27) -> 1037,15;1040,15 | H58: =CONCATENATE($H$37,M27) -> 1,315000 | I58: =_xlfn.CONCAT(F58,$F$37,H58) -> 1037,15;1040,15;1,315000
D59: =VLOOKUP(D7,$D$32:$G$35,3,0) -> 1020 | E59: =D59+3 -> 1023 | F59: =CONCATENATE(D59,$E$37,E7,$F$37,E59,$E$37,G7) -> 1020,1;1023,1 | H59: =CONCATENATE($H$37,M7) -> 1,5000 | I59: =_xlfn.CONCAT(F59,$F$37,H59) -> 1020,1;1023,1;1,5000
D60: =VLOOKUP(D8,$D$32:$G$35,3,0) -> 1020 | E60: =D60+3 -> 1023 | F60: =CONCATENATE(D60,$E$37,E8,$F$37,E60,$E$37,G8) -> 1020,2;1023,2 | H60: =CONCATENATE($H$37,M8) -> 1,5000 | I60: =_xlfn.CONCAT(F60,$F$37,H60) -> 1020,2;1023,2;1,5000
D61: =VLOOKUP(D9,$D$32:$G$35,3,0) -> 1020 | E61: =D61+3 -> 1023 | F61: =CONCATENATE(D61,$E$37,E9,$F$37,E61,$E$37,G9) -> 1020,2;1023,2 | H61: =CONCATENATE($H$37,M9) -> 1,10000 | I61: =_xlfn.CONCAT(F61,$F$37,H61) -> 1020,2;1023,2;1,10000
D62: =VLOOKUP(D10,$D$32:$G$35,3,0) -> 1020 | E62: =D62+3 -> 1023 | F62: =CONCATENATE(D62,$E$37,E10,$F$37,E62,$E$37,G10) -> 1020,3;1023,3 | H62: =CONCATENATE($H$37,M10) -> 1,10000 | I62: =_xlfn.CONCAT(F62,$F$37,H62) -> 1020,3;1023,3;1,10000
D63: =VLOOKUP(D11,$D$32:$G$35,3,0) -> 1020 | E63: =D63+3 -> 1023 | F63: =CONCATENATE(D63,$E$37,E11,$F$37,E63,$E$37,G11) -> 1020,4;1023,4 | H63: =CONCATENATE($H$37,M11) -> 1,10000 | I63: =_xlfn.CONCAT(F63,$F$37,H63) -> 1020,4;1023,4;1,10000
D64: =VLOOKUP(D12,$D$32:$G$35,3,0) -> 1020 | E64: =D64+3 -> 1023 | F64: =CONCATENATE(D64,$E$37,E12,$F$37,E64,$E$37,G12) -> 1020,4;1023,4 | H64: =CONCATENATE($H$37,M12) -> 1,15000 | I64: =_xlfn.CONCAT(F64,$F$37,H64) -> 1020,4;1023,4;1,15000
D65: =VLOOKUP(D13,$D$32:$G$35,3,0) -> 1020 | E65: =D65+3 -> 1023 | F65: =CONCATENATE(D65,$E$37,E13,$F$37,E65,$E$37,G13) -> 1020,5;1023,5 | H65: =CONCATENATE($H$37,M13) -> 1,15000 | I65: =_xlfn.CONCAT(F65,$F$37,H65) -> 1020,5;1023,5;1,15000
D66: =VLOOKUP(D14,$D$32:$G$35,3,0) -> 1020 | E66: =D66+3 -> 1023 | F66: =CONCATENATE(D66,$E$37,E14,$F$37,E66,$E$37,G14) -> 1020,5;1023,5 | H66: =CONCATENATE($H$37,M14) -> 1,20000 | I66: =_xlfn.CONCAT(F66,$F$37,H66) -> 1020,5;1023,5;1,20000
D67: =VLOOKUP(D15,$D$32:$G$35,3,0) -> 1026 | E67: =D67+3 -> 1029 | F67: =CONCATENATE(D67,$E$37,E15,$F$37,E67,$E$37,G15) -> 1026,5;1029,5 | H67: =CONCATENATE($H$37,M15) -> 1,25000 | I67: =_xlfn.CONCAT(F67,$F$37,H67) -> 1026,5;1029,5;1,25000
D68: =VLOOKUP(D16,$D$32:$G$35,3,0) -> 1026 | E68: =D68+3 -> 1029 | F68: =CONCATENATE(D68,$E$37,E16,$F$37,E68,$E$37,G16) -> 1026,6;1029,6 | H68: =CONCATENATE($H$37,M16) -> 1,30000 | I68: =_xlfn.CONCAT(F68,$F$37,H68) -> 1026,6;1029,6;1,30000
D69: =VLOOKUP(D17,$D$32:$G$35,3,0) -> 1026 | E69: =D69+3 -> 1029 | F69: =CONCATENATE(D69,$E$37,E17,$F$37,E69,$E$37,G17) -> 1026,6;1029,6 | H69: =CONCATENATE($H$37,M17) -> 1,40000 | I69: =_xlfn.CONCAT(F69,$F$37,H69) -> 1026,6;1029,6;1,40000
D70: =VLOOKUP(D18,$D$32:$G$35,3,0) -> 1026 | E70: =D70+3 -> 1029 | F70: =CONCATENATE(D70,$E$37,E18,$F$37,E70,$E$37,G18) -> 1026,7;1029,7 | H70: =CONCATENATE($H$37,M18) -> 1,50000 | I70: =_xlfn.CONCAT(F70,$F$37,H70) -> 1026,7;1029,7;1,50000
... D79: =VLOOKUP(D27,$D$32:$G$35,3,0) -> 1038 | E79: =D79+3 -> 1041 | F79: =CONCATENATE(D79,$E$37,E27,$F$37,E79,$E$37,G27) -> 1038,15;1041,15 | H79: =CONCATENATE($H$37,M27) -> 1,315000 | I79: =_xlfn.CONCAT(F79,$F$37,H79) -> 1038,15;1041,15;1,315000
D80: =VLOOKUP(D7,$D$32:$G$35,4,0) -> 1021 | E80: =D80+3 -> 1024 | F80: =CONCATENATE(D80,$E$37,E7,$F$37,E80,$E$37,G7) -> 1021,1;1024,1 | H80: =CONCATENATE($H$37,M7) -> 1,5000 | I80: =_xlfn.CONCAT(F80,$F$37,H80) -> 1021,1;1024,1;1,5000
D81: =VLOOKUP(D8,$D$32:$G$35,4,0) -> 1021 | E81: =D81+3 -> 1024 | F81: =CONCATENATE(D81,$E$37,E8,$F$37,E81,$E$37,G8) -> 1021,2;1024,2 | H81: =CONCATENATE($H$37,M8) -> 1,5000 | I81: =_xlfn.CONCAT(F81,$F$37,H81) -> 1021,2;1024,2;1,5000
D82: =VLOOKUP(D9,$D$32:$G$35,4,0) -> 1021 | E82: =D82+3 -> 1024 | F82: =CONCATENATE(D82,$E$37,E9,$F$37,E82,$E$37,G9) -> 1021,2;1024,2 | H82: =CONCATENATE($H$37,M9) -> 1,10000 | I82: =_xlfn.CONCAT(F82,$F$37,H82) -> 1021,2;1024,2;1,10000
D83: =VLOOKUP(D10,$D$32:$G$35,4,0) -> 1021 | E83: =D83+3 -> 1024 | F83: =CONCATENATE(D83,$E$37,E10,$F$37,E83,$E$37,G10) -> 1021,3;1024,3 | H83: =CONCATENATE($H$37,M10) -> 1,10000 | I83: =_xlfn.CONCAT(F83,$F$37,H83) -> 1021,3;1024,3;1,10000
D84: =VLOOKUP(D11,$D$32:$G$35,4,0) -> 1021 | E84: =D84+3 -> 1024 | F84: =CONCATENATE(D84,$E$37,E11,$F$37,E84,$E$37,G11) -> 1021,4;1024,4 | H84: =CONCATENATE($H$37,M11) -> 1,10000 | I84: =_xlfn.CONCAT(F84,$F$37,H84) -> 1021,4;1024,4;1,10000
D85: =VLOOKUP(D12,$D$32:$G$35,4,0) -> 1021 | E85: =D85+3 -> 1024 | F85: =CONCATENATE(D85,$E$37,E12,$F$37,E85,$E$37,G12) -> 1021,4;1024,4 | H85: =CONCATENATE($H$37,M12) -> 1,15000 | I85: =_xlfn.CONCAT(F85,$F$37,H85) -> 1021,4;1024,4;1,15000
D86: =VLOOKUP(D13,$D$32:$G$35,4,0) -> 1021 | E86: =D86+3 -> 1024 | F86: =CONCATENATE(D86,$E$37,E13,$F$37,E86,$E$37,G13) -> 1021,5;1024,5 | H86: =CONCATENATE($H$37,M13) -> 1,15000 | I86: =_xlfn.CONCAT(F86,$F$37,H86) -> 1021,5;1024,5;1,15000
D87: =VLOOKUP(D14,$D$32:$G$35,4,0) -> 1021 | E87: =D87+3 -> 1024 | F87: =CONCATENATE(D87,$E$37,E14,$F$37,E87,$E$37,G14) -> 1021,5;1024,5 | H87: =CONCATENATE($H$37,M14) -> 1,20000 | I87: =_xlfn.CONCAT(F87,$F$37,H87) -> 1021,5;1024,5;1,20000
D88: =VLOOKUP(D15,$D$32:$G$35,4,0) -> 1027 | E88: =D88+3 -> 1030 | F88: =CONCATENATE(D88,$E$37,E15,$F$37,E88,$E$37,G15) -> 1027,5;1030,5 | H88: =CONCATENATE($H$37,M15) -> 1,25000 | I88: =_xlfn.CONCAT(F88,$F$37,H88) -> 1027,5;1030,5;1,25000
D89: =VLOOKUP(D16,$D$32:$G$35,4,0) -> 1027 | E89: =D89+3 -> 1030 | F89: =CONCATENATE(D89,$E$37,E16,$F$37,E89,$E$37,G16) -> 1027,6;1030,6 | H89: =CONCATENATE($H$37,M16) -> 1,30000 | I89: =_xlfn.CONCAT(F89,$F$37,H89) -> 1027,6;1030,6;1,30000
D90: =VLOOKUP(D17,$D$32:$G$35,4,0) -> 1027 | E90: =D90+3 -> 1030 | F90: =CONCATENATE(D90,$E$37,E17,$F$37,E90,$E$37,G17) -> 1027,6;1030,6 | H90: =CONCATENATE($H$37,M17) -> 1,40000 | I90: =_xlfn.CONCAT(F90,$F$37,H90) -> 1027,6;1030,6;1,40000
D91: =VLOOKUP(D18,$D$32:$G$35,4,0) -> 1027 | E91: =D91+3 -> 1030 | F91: =CONCATENATE(D91,$E$37,E18,$F$37,E91,$E$37,G18) -> 1027,7;1030,7 | H91: =CONCATENATE($H$37,M18) -> 1,50000 | I91: =_xlfn.CONCAT(F91,$F$37,H91) -> 1027,7;1030,7;1,50000
... D100: =VLOOKUP(D27,$D$32:$G$35,4,0) -> 1039 | E100: =D100+3 -> 1042 | F100: =CONCATENATE(D100,$E$37,E27,$F$37,E100,$E$37,G27) -> 1039,15;1042,15 | H100: =CONCATENATE($H$37,M27) -> 1,315000 | I100: =_xlfn.CONCAT(F100,$F$37,H100) -> 1039,15;1042,15;1,315000

Sheet 映射装备
B5: 宝石合成
C6: 合成所需数量
B7: 1级宝石 | C7: 3 | D7: ——》 | E7: 2级宝石
B8: 2级宝石 | C8: 3 | D8: ——》 | E8: 3级宝石
B9: 3级宝石 | C9: 3 | D9: ——》 | E9: 4级宝石
B10: 4级宝石 | C10: 3 | D10: ——》 | E10: 5级宝石 | H10: 1个5级宝石所需180个1级宝石
B11: 5级宝石 | C11: 3 | D11: ——》 | E11: 6级宝石
B12: 6级宝石 | C12: 3 | D12: ——》 | E12: 7级宝石
B17: 装备升级
B19: 等级上限 | C19: 60 | E19: 装备件数 | F19: 8 | G19: 0.6 | I19: 0.8
C20: 史诗、传说 | G20: 普通 | I20: 稀有
B21: 等级 | C21: 每级所需经验 | D21: 总经验 | E21: 每级所需金币 | F21: 总金币 | G21: 每级所需经验 | H21: 每级所需金币 | I21: 每级所需经验 | J21: 每级所需金币 | L21: 单件总经验 | M21: =MAX(D22:D81) -> 526601
B22: {=_xlfn.SEQUENCE(C19,1,1,1)} -> 1 | C22: 40 | D22: =SUM($C$22:C22) -> 40 | E22: =C22 -> 40 | F22: =SUM($E$22:E22) -> 40 | G22: =ROUND(C22*$G$19,0) -> 24 | H22: =ROUND(E22*$G$19,0) -> 24 | I22: =ROUND(C22*$I$19,0) -> 32 | J22: =ROUND(E22*$I$19,0) -> 32 | L22: 单件总金币 | M22: =MAX(F22:F81) -> 526601
B23: 2 | C23: =ROUND(C22*1.2,0) -> 48 | D23: =SUM($C$22:C23) -> 88 | E23: =C23 -> 48 | F23: =SUM($E$22:E23) -> 88 | G23: =ROUND(C23*$G$19,0) -> 29 | H23: =ROUND(E23*$G$19,0) -> 29 | I23: =ROUND(C23*$I$19,0) -> 38 | J23: =ROUND(E23*$I$19,0) -> 38 | L23: 8件总经验 | M23: =$F$19*M21 -> 4212808
B24: 3 | C24: =ROUND(C23*1.2,0) -> 58 | D24: =SUM($C$22:C24) -> 146 | E24: =C24 -> 58 | F24: =SUM($E$22:E24) -> 146 | G24: =ROUND(C24*$G$19,0) -> 35 | H24: =ROUND(E24*$G$19,0) -> 35 | I24: =ROUND(C24*$I$19,0) -> 46 | J24: =ROUND(E24*$I$19,0) -> 46 | L24: 8件总金币 | M24: =$F$19*M22 -> 4212808
B25: 4 | C25: =ROUND(C24*1.2,0) -> 70 | D25: =SUM($C$22:C25) -> 216 | E25: =C25 -> 70 | F25: =SUM($E$22:E25) -> 216 | G25: =ROUND(C25*$G$19,0) -> 42 | H25: =ROUND(E25*$G$19,0) -> 42 | I25: =ROUND(C25*$I$19,0) -> 56 | J25: =ROUND(E25*$I$19,0) -> 56
B26: 5 | C26: =ROUND(C25*1.2,0) -> 84 | D26: =SUM($C$22:C26) -> 300 | E26: =C26 -> 84 | F26: =SUM($E$22:E26) -> 300 | G26: =ROUND(C26*$G$19,0) -> 50 | H26: =ROUND(E26*$G$19,0) -> 50 | I26: =ROUND(C26*$I$19,0) -> 67 | J26: =ROUND(E26*$I$19,0) -> 67 | L26: 强化获得经验比例 | N26: 0.8
B27: 6 | C27: =ROUND(C26*1.2,0) -> 101 | D27: =SUM($C$22:C27) -> 401 | E27: =C27 -> 101 | F27: =SUM($E$22:E27) -> 401 | G27: =ROUND(C27*$G$19,0) -> 61 | H27: =ROUND(E27*$G$19,0) -> 61 | I27: =ROUND(C27*$I$19,0) -> 81 | J27: =ROUND(E27*$I$19,0) -> 81
B28: 7 | C28: =ROUND(C27*1.2,0) -> 121 | D28: =SUM($C$22:C28) -> 522 | E28: =C28 -> 121 | F28: =SUM($E$22:E28) -> 522 | G28: =ROUND(C28*$G$19,0) -> 73 | H28: =ROUND(E28*$G$19,0) -> 73 | I28: =ROUND(C28*$I$19,0) -> 97 | J28: =ROUND(E28*$I$19,0) -> 97 | L28: 经验：金币比例 | N28: 1比1
B29: 8 | C29: =ROUND(C28*1.2,0) -> 145 | D29: =SUM($C$22:C29) -> 667 | E29: =C29 -> 145 | F29: =SUM($E$22:E29) -> 667 | G29: =ROUND(C29*$G$19,0) -> 87 | H29: =ROUND(E29*$G$19,0) -> 87 | I29: =ROUND(C29*$I$19,0) -> 116 | J29: =ROUND(E29*$I$19,0) -> 116
B30: 9 | C30: =ROUND(C29*1.2,0) -> 174 | D30: =SUM($C$22:C30) -> 841 | E30: =C30 -> 174 | F30: =SUM($E$22:E30) -> 841 | G30: =ROUND(C30*$G$19,0) -> 104 | H30: =ROUND(E30*$G$19,0) -> 104 | I30: =ROUND(C30*$I$19,0) -> 139 | J30: =ROUND(E30*$I$19,0) -> 139 | L30: 分解可得装备经验
B31: 10 | C31: =ROUND(C30*1.2,0) -> 209 | D31: =SUM($C$22:C31) -> 1050 | E31: =C31 -> 209 | F31: =SUM($E$22:E31) -> 1050 | G31: =ROUND(C31*$G$19,0) -> 125 | H31: =ROUND(E31*$G$19,0) -> 125 | I31: =ROUND(C31*$I$19,0) -> 167 | J31: =ROUND(E31*$I$19,0) -> 167 | L31: 星级 | M31: 经验
B32: 11 | C32: =ROUND(C31*1.2,0) -> 251 | D32: =SUM($C$22:C32) -> 1301 | E32: =C32 -> 251 | F32: =SUM($E$22:E32) -> 1301 | G32: =ROUND(C32*$G$19,0) -> 151 | H32: =ROUND(E32*$G$19,0) -> 151 | I32: =ROUND(C32*$I$19,0) -> 201 | J32: =ROUND(E32*$I$19,0) -> 201 | L32: 普通 | M32: 200 | P32: 暂定额外材料
B33: 12 | C33: =ROUND(C32*1.2,0) -> 301 | D33: =SUM($C$22:C33) -> 1602 | E33: =C33 -> 301 | F33: =SUM($E$22:E33) -> 1602 | G33: =ROUND(C33*$G$19,0) -> 181 | H33: =ROUND(E33*$G$19,0) -> 181 | I33: =ROUND(C33*$I$19,0) -> 241 | J33: =ROUND(E33*$I$19,0) -> 241 | L33: 稀有 | M33: 800 | N33: 史诗兑换材料 | O33: 1
B34: 13 | C34: =ROUND(C33*1.2,0) -> 361 | D34: =SUM($C$22:C34) -> 1963 | E34: =C34 -> 361 | F34: =SUM($E$22:E34) -> 1963 | G34: =ROUND(C34*$G$19,0) -> 217 | H34: =ROUND(E34*$G$19,0) -> 217 | I34: =ROUND(C34*$I$19,0) -> 289 | J34: =ROUND(E34*$I$19,0) -> 289 | L34: 史诗 | M34: 2000 | N34: 传说兑换材料 | O34: 1
B35: 14 | C35: =ROUND(C34*1.2,0) -> 433 | D35: =SUM($C$22:C35) -> 2396 | E35: =C35 -> 433 | F35: =SUM($E$22:E35) -> 2396 | G35: =ROUND(C35*$G$19,0) -> 260 | H35: =ROUND(E35*$G$19,0) -> 260 | I35: =ROUND(C35*$I$19,0) -> 346 | J35: =ROUND(E35*$I$19,0) -> 346 | L35: 传说 | M35: 10000 | N35: 传说兑换材料 | O35: 10
B36: 15 | C36: =ROUND(C35*1.2,0) -> 520 | D36: =SUM($C$22:C36) -> 2916 | E36: =C36 -> 520 | F36: =SUM($E$22:E36) -> 2916 | G36: =ROUND(C36*$G$19,0) -> 312 | H36: =ROUND(E36*$G$19,0) -> 312 | I36: =ROUND(C36*$I$19,0) -> 416 | J36: =ROUND(E36*$I$19,0) -> 416
B37: 16 | C37: =ROUND(C36*1.2,0) -> 624 | D37: =SUM($C$22:C37) -> 3540 | E37: =C37 -> 624 | F37: =SUM($E$22:E37) -> 3540 | G37: =ROUND(C37*$G$19,0) -> 374 | H37: =ROUND(E37*$G$19,0) -> 374 | I37: =ROUND(C37*$I$19,0) -> 499 | J37: =ROUND(E37*$I$19,0) -> 499
B38: 17 | C38: =ROUND(C37*1.2,0) -> 749 | D38: =SUM($C$22:C38) -> 4289 | E38: =C38 -> 749 | F38: =SUM($E$22:E38) -> 4289 | G38: =ROUND(C38*$G$19,0) -> 449 | H38: =ROUND(E38*$G$19,0) -> 449 | I38: =ROUND(C38*$I$19,0) -> 599 | J38: =ROUND(E38*$I$19,0) -> 599
B39: 18 | C39: =ROUND(C38*1.2,0) -> 899 | D39: =SUM($C$22:C39) -> 5188 | E39: =C39 -> 899 | F39: =SUM($E$22:E39) -> 5188 | G39: =ROUND(C39*$G$19,0) -> 539 | H39: =ROUND(E39*$G$19,0) -> 539 | I39: =ROUND(C39*$I$19,0) -> 719 | J39: =ROUND(E39*$I$19,0) -> 719
B40: 19 | C40: =ROUND(C39*1.2,0) -> 1079 | D40: =SUM($C$22:C40) -> 6267 | E40: =C40 -> 1079 | F40: =SUM($E$22:E40) -> 6267 | G40: =ROUND(C40*$G$19,0) -> 647 | H40: =ROUND(E40*$G$19,0) -> 647 | I40: =ROUND(C40*$I$19,0) -> 863 | J40: =ROUND(E40*$I$19,0) -> 863
B41: 20 | C41: =ROUND(C40*1.2,0) -> 1295 | D41: =SUM($C$22:C41) -> 7562 | E41: =C41 -> 1295 | F41: =SUM($E$22:E41) -> 7562 | G41: =ROUND(C41*$G$19,0) -> 777 | H41: =ROUND(E41*$G$19,0) -> 777 | I41: =ROUND(C41*$I$19,0) -> 1036 | J41: =ROUND(E41*$I$19,0) -> 1036
B42: 21 | C42: =ROUND(C41*1.1,0) -> 1425 | D42: =SUM($C$22:C42) -> 8987 | E42: =C42 -> 1425 | F42: =SUM($E$22:E42) -> 8987 | G42: =ROUND(C42*$G$19,0) -> 855 | H42: =ROUND(E42*$G$19,0) -> 855 | I42: =ROUND(C42*$I$19,0) -> 1140 | J42: =ROUND(E42*$I$19,0) -> 1140
B43: 22 | C43: =ROUND(C42*1.1,0) -> 1568 | D43: =SUM($C$22:C43) -> 10555 | E43: =C43 -> 1568 | F43: =SUM($E$22:E43) -> 10555 | G43: =ROUND(C43*$G$19,0) -> 941 | H43: =ROUND(E43*$G$19,0) -> 941 | I43: =ROUND(C43*$I$19,0) -> 1254 | J43: =ROUND(E43*$I$19,0) -> 1254
B44: 23 | C44: =ROUND(C43*1.1,0) -> 1725 | D44: =SUM($C$22:C44) -> 12280 | E44: =C44 -> 1725 | F44: =SUM($E$22:E44) -> 12280 | G44: =ROUND(C44*$G$19,0) -> 1035 | H44: =ROUND(E44*$G$19,0) -> 1035 | I44: =ROUND(C44*$I$19,0) -> 1380 | J44: =ROUND(E44*$I$19,0) -> 1380
B45: 24 | C45: =ROUND(C44*1.1,0) -> 1898 | D45: =SUM($C$22:C45) -> 14178 | E45: =C45 -> 1898 | F45: =SUM($E$22:E45) -> 14178 | G45: =ROUND(C45*$G$19,0) -> 1139 | H45: =ROUND(E45*$G$19,0) -> 1139 | I45: =ROUND(C45*$I$19,0) -> 1518 | J45: =ROUND(E45*$I$19,0) -> 1518
B46: 25 | C46: =ROUND(C45*1.1,0) -> 2088 | D46: =SUM($C$22:C46) -> 16266 | E46: =C46 -> 2088 | F46: =SUM($E$22:E46) -> 16266 | G46: =ROUND(C46*$G$19,0) -> 1253 | H46: =ROUND(E46*$G$19,0) -> 1253 | I46: =ROUND(C46*$I$19,0) -> 1670 | J46: =ROUND(E46*$I$19,0) -> 1670
B47: 26 | C47: =ROUND(C46*1.1,0) -> 2297 | D47: =SUM($C$22:C47) -> 18563 | E47: =C47 -> 2297 | F47: =SUM($E$22:E47) -> 18563 | G47: =ROUND(C47*$G$19,0) -> 1378 | H47: =ROUND(E47*$G$19,0) -> 1378 | I47: =ROUND(C47*$I$19,0) -> 1838 | J47: =ROUND(E47*$I$19,0) -> 1838
B48: 27 | C48: =ROUND(C47*1.1,0) -> 2527 | D48: =SUM($C$22:C48) -> 21090 | E48: =C48 -> 2527 | F48: =SUM($E$22:E48) -> 21090 | G48: =ROUND(C48*$G$19,0) -> 1516 | H48: =ROUND(E48*$G$19,0) -> 1516 | I48: =ROUND(C48*$I$19,0) -> 2022 | J48: =ROUND(E48*$I$19,0) -> 2022
B49: 28 | C49: =ROUND(C48*1.1,0) -> 2780 | D49: =SUM($C$22:C49) -> 23870 | E49: =C49 -> 2780 | F49: =SUM($E$22:E49) -> 23870 | G49: =ROUND(C49*$G$19,0) -> 1668 | H49: =ROUND(E49*$G$19,0) -> 1668 | I49: =ROUND(C49*$I$19,0) -> 2224 | J49: =ROUND(E49*$I$19,0) -> 2224
B50: 29 | C50: =ROUND(C49*1.1,0) -> 3058 | D50: =SUM($C$22:C50) -> 26928 | E50: =C50 -> 3058 | F50: =SUM($E$22:E50) -> 26928 | G50: =ROUND(C50*$G$19,0) -> 1835 | H50: =ROUND(E50*$G$19,0) -> 1835 | I50: =ROUND(C50*$I$19,0) -> 2446 | J50: =ROUND(E50*$I$19,0) -> 2446
B51: 30 | C51: =ROUND(C50*1.1,0) -> 3364 | D51: =SUM($C$22:C51) -> 30292 | E51: =C51 -> 3364 | F51: =SUM($E$22:E51) -> 30292 | G51: =ROUND(C51*$G$19,0) -> 2018 | H51: =ROUND(E51*$G$19,0) -> 2018 | I51: =ROUND(C51*$I$19,0) -> 2691 | J51: =ROUND(E51*$I$19,0) -> 2691
B52: 31 | C52: =ROUND(C51*1.1,0) -> 3700 | D52: =SUM($C$22:C52) -> 33992 | E52: =C52 -> 3700 | F52: =SUM($E$22:E52) -> 33992 | G52: =ROUND(C52*$G$19,0) -> 2220 | H52: =ROUND(E52*$G$19,0) -> 2220 | I52: =ROUND(C52*$I$19,0) -> 2960 | J52: =ROUND(E52*$I$19,0) -> 2960
B53: 32 | C53: =ROUND(C52*1.1,0) -> 4070 | D53: =SUM($C$22:C53) -> 38062 | E53: =C53 -> 4070 | F53: =SUM($E$22:E53) -> 38062 | G53: =ROUND(C53*$G$19,0) -> 2442 | H53: =ROUND(E53*$G$19,0) -> 2442 | I53: =ROUND(C53*$I$19,0) -> 3256 | J53: =ROUND(E53*$I$19,0) -> 3256
... B70: 49 | C70: =ROUND(C69*1.1,0) -> 20579 | D70: =SUM($C$22:C70) -> 219629 | E70: =C70 -> 20579 | F70: =SUM($E$22:E70) -> 219629 | G70: =ROUND(C70*$G$19,0) -> 12347 | H70: =ROUND(E70*$G$19,0) -> 12347 | I70: =ROUND(C70*$I$19,0) -> 16463 | J70: =ROUND(E70*$I$19,0) -> 16463
B71: 50 | C71: =ROUND(C70*1.05,0) -> 21608 | D71: =SUM($C$22:C71) -> 241237 | E71: =C71 -> 21608 | F71: =SUM($E$22:E71) -> 241237 | G71: =ROUND(C71*$G$19,0) -> 12965 | H71: =ROUND(E71*$G$19,0) -> 12965 | I71: =ROUND(C71*$I$19,0) -> 17286 | J71: =ROUND(E71*$I$19,0) -> 17286
B72: 51 | C72: =ROUND(C71*1.05,0) -> 22688 | D72: =SUM($C$22:C72) -> 263925 | E72: =C72 -> 22688 | F72: =SUM($E$22:E72) -> 263925 | G72: =ROUND(C72*$G$19,0) -> 13613 | H72: =ROUND(E72*$G$19,0) -> 13613 | I72: =ROUND(C72*$I$19,0) -> 18150 | J72: =ROUND(E72*$I$19,0) -> 18150
B73: 52 | C73: =ROUND(C72*1.05,0) -> 23822 | D73: =SUM($C$22:C73) -> 287747 | E73: =C73 -> 23822 | F73: =SUM($E$22:E73) -> 287747 | G73: =ROUND(C73*$G$19,0) -> 14293 | H73: =ROUND(E73*$G$19,0) -> 14293 | I73: =ROUND(C73*$I$19,0) -> 19058 | J73: =ROUND(E73*$I$19,0) -> 19058
B74: 53 | C74: =ROUND(C73*1.05,0) -> 25013 | D74: =SUM($C$22:C74) -> 312760 | E74: =C74 -> 25013 | F74: =SUM($E$22:E74) -> 312760 | G74: =ROUND(C74*$G$19,0) -> 15008 | H74: =ROUND(E74*$G$19,0) -> 15008 | I74: =ROUND(C74*$I$19,0) -> 20010 | J74: =ROUND(E74*$I$19,0) -> 20010
B75: 54 | C75: =ROUND(C74*1.05,0) -> 26264 | D75: =SUM($C$22:C75) -> 339024 | E75: =C75 -> 26264 | F75: =SUM($E$22:E75) -> 339024 | G75: =ROUND(C75*$G$19,0) -> 15758 | H75: =ROUND(E75*$G$19,0) -> 15758 | I75: =ROUND(C75*$I$19,0) -> 21011 | J75: =ROUND(E75*$I$19,0) -> 21011
B76: 55 | C76: =ROUND(C75*1.05,0) -> 27577 | D76: =SUM($C$22:C76) -> 366601 | E76: =C76 -> 27577 | F76: =SUM($E$22:E76) -> 366601 | G76: =ROUND(C76*$G$19,0) -> 16546 | H76: =ROUND(E76*$G$19,0) -> 16546 | I76: =ROUND(C76*$I$19,0) -> 22062 | J76: =ROUND(E76*$I$19,0) -> 22062
B77: 56 | C77: =ROUND(C76*1.05,0) -> 28956 | D77: =SUM($C$22:C77) -> 395557 | E77: =C77 -> 28956 | F77: =SUM($E$22:E77) -> 395557 | G77: =ROUND(C77*$G$19,0) -> 17374 | H77: =ROUND(E77*$G$19,0) -> 17374 | I77: =ROUND(C77*$I$19,0) -> 23165 | J77: =ROUND(E77*$I$19,0) -> 23165
B78: 57 | C78: =ROUND(C77*1.05,0) -> 30404 | D78: =SUM($C$22:C78) -> 425961 | E78: =C78 -> 30404 | F78: =SUM($E$22:E78) -> 425961 | G78: =ROUND(C78*$G$19,0) -> 18242 | H78: =ROUND(E78*$G$19,0) -> 18242 | I78: =ROUND(C78*$I$19,0) -> 24323 | J78: =ROUND(E78*$I$19,0) -> 24323
B79: 58 | C79: =ROUND(C78*1.05,0) -> 31924 | D79: =SUM($C$22:C79) -> 457885 | E79: =C79 -> 31924 | F79: =SUM($E$22:E79) -> 457885 | G79: =ROUND(C79*$G$19,0) -> 19154 | H79: =ROUND(E79*$G$19,0) -> 19154 | I79: =ROUND(C79*$I$19,0) -> 25539 | J79: =ROUND(E79*$I$19,0) -> 25539
B80: 59 | C80: =ROUND(C79*1.05,0) -> 33520 | D80: =SUM($C$22:C80) -> 491405 | E80: =C80 -> 33520 | F80: =SUM($E$22:E80) -> 491405 | G80: =ROUND(C80*$G$19,0) -> 20112 | H80: =ROUND(E80*$G$19,0) -> 20112 | I80: =ROUND(C80*$I$19,0) -> 26816 | J80: =ROUND(E80*$I$19,0) -> 26816
B81: 60 | C81: =ROUND(C80*1.05,0) -> 35196 | D81: =SUM($C$22:C81) -> 526601 | E81: =C81 -> 35196 | F81: =SUM($E$22:E81) -> 526601 | G81: =ROUND(C81*$G$19,0) -> 21118 | H81: =ROUND(E81*$G$19,0) -> 21118 | I81: =ROUND(C81*$I$19,0) -> 28157 | J81: =ROUND(E81*$I$19,0) -> 28157

Sheet 主角等级（从新手引导复制） 
B2: 主角等级上限 | D2: 60 | F2: =MAX($F$5:$F$63)/U18 -> 29.348276 | G2: =MAX($F$5:$F$63)/U16 -> 56.74
F3: =F63/U16 -> 56.74 | S3: 经验产出
B4: 等级 | C4: 每级成长 | D4: 升级需要经验 | E4: 升级返还体力 | F4: 所需总经验 | G4: 实际所需总经验 | H4: 对应主线章节 | K4: 对应主线关卡 | N4: 主线章节 | O4: 章节关卡数 | P4: 主角等级预计 | Q4: 对应天数 | S4: 来源 | T4: 每日产出 | U4: 核算经验
B5: {=_xlfn.SEQUENCE(D2,1,1,1)} -> 1 | C5: 10 | D5: 80 | E5: 0 | F5: =SUM($D$5:D5) -> 80 | G5: =SUM($D$5:D5)-10*SUM($E$5:E5) -> 80 | H5: {=INDEX($N$5:$N$18,MATCH(MIN(IF($P$5:$P$18>B5,$P$5:$P$18)),$P$5:$P$18,0))} -> 0 | I5: =VLOOKUP(H5,$N$5:$O$18,2,0)/COUNTIF($H$5:$H$74,H5) -> 1 | J5: =IF(H5<>H4,I5,J4+I4) -> 1 | K5: =ROUND(J5,0) -> 1 | N5: 0 | O5: 5 | P5: 6 | Q5: {=_xlfn.IFNA(INDEX(_xlfn.ANCHORARRAY($N$43),MATCH(P5,$P$43:$P$98))+1,1)} -> 1 | S5: 自然回复 | T5: 240 | U5: =T5*10 -> 2400
B6: 2 | C6: 10 | D6: =C6+D5 -> 90 | E6: 5 | F6: =SUM($D$5:D6) -> 170 | G6: =SUM($D$5:D6)-10*SUM($E$5:E6) -> 120 | H6: {=INDEX($N$5:$N$18,MATCH(MIN(IF($P$5:$P$18>B6,$P$5:$P$18)),$P$5:$P$18,0))} -> 0 | I6: =VLOOKUP(H6,$N$5:$O$18,2,0)/COUNTIF($H$5:$H$74,H6) -> 1 | J6: =IF(H6<>H5,I6,J5+I5) -> 2 | K6: =ROUND(J6,0) -> 2 | N6: 1 | O6: 10 | P6: 14 | Q6: {=_xlfn.IFNA(INDEX(_xlfn.ANCHORARRAY($N$43),MATCH(P6,$P$43:$P$98))+1,1)} -> 1 | S6: 每日任务 | T6: 0 | U6: 1500
B7: 3 | C7: 10 | D7: =C7+D6 -> 100 | E7: 5 | F7: =SUM($D$5:D7) -> 270 | G7: =SUM($D$5:D7)-10*SUM($E$5:E7) -> 170 | H7: {=INDEX($N$5:$N$18,MATCH(MIN(IF($P$5:$P$18>B7,$P$5:$P$18)),$P$5:$P$18,0))} -> 0 | I7: =VLOOKUP(H7,$N$5:$O$18,2,0)/COUNTIF($H$5:$H$74,H7) -> 1 | J7: =IF(H7<>H6,I7,J6+I6) -> 3 | K7: =ROUND(J7,0) -> 3 | N7: 2 | O7: 15 | P7: 20 | Q7: {=_xlfn.IFNA(INDEX(_xlfn.ANCHORARRAY($N$43),MATCH(P7,$P$43:$P$98))+1,1)} -> 1 | S7: 购买体力1次 | T7: 60 | U7: =T7*10 -> 600
B8: 4 | C8: 10 | D8: =C8+D7 -> 110 | E8: 5 | F8: =SUM($D$5:D8) -> 380 | G8: =SUM($D$5:D8)-10*SUM($E$5:E8) -> 230 | H8: {=INDEX($N$5:$N$18,MATCH(MIN(IF($P$5:$P$18>B8,$P$5:$P$18)),$P$5:$P$18,0))} -> 0 | I8: =VLOOKUP(H8,$N$5:$O$18,2,0)/COUNTIF($H$5:$H$74,H8) -> 1 | J8: =IF(H8<>H7,I8,J7+I7) -> 4 | K8: =ROUND(J8,0) -> 4 | N8: 3 | O8: 15 | P8: 25 | Q8: {=_xlfn.IFNA(INDEX(_xlfn.ANCHORARRAY($N$43),MATCH(P8,$P$43:$P$98))+1,1)} -> 2 | S8: 购买体力2次 | T8: 60 | U8: =T8*10 -> 600
B9: 5 | C9: 10 | D9: =C9+D8 -> 120 | E9: 5 | F9: =SUM($D$5:D9) -> 500 | G9: =SUM($D$5:D9)-10*SUM($E$5:E9) -> 300 | H9: {=INDEX($N$5:$N$18,MATCH(MIN(IF($P$5:$P$18>B9,$P$5:$P$18)),$P$5:$P$18,0))} -> 0 | I9: =VLOOKUP(H9,$N$5:$O$18,2,0)/COUNTIF($H$5:$H$74,H9) -> 1 | J9: =IF(H9<>H8,I9,J8+I8) -> 5 | K9: =ROUND(J9,0) -> 5 | N9: 4 | O9: 15 | P9: 30 | Q9: {=_xlfn.IFNA(INDEX(_xlfn.ANCHORARRAY($N$43),MATCH(P9,$P$43:$P$98))+1,1)} -> 2 | S9: 购买体力3次 | T9: 60 | U9: =T9*10 -> 600
B10: 6 | C10: 10 | D10: =C10+D9 -> 130 | E10: 5 | F10: =SUM($D$5:D10) -> 630 | G10: =SUM($D$5:D10)-10*SUM($E$5:E10) -> 380 | H10: {=INDEX($N$5:$N$18,MATCH(MIN(IF($P$5:$P$18>B10,$P$5:$P$18)),$P$5:$P$18,0))} -> 1 | I10: =VLOOKUP(H10,$N$5:$O$18,2,0)/COUNTIF($H$5:$H$74,H10) -> 1.25 | J10: =IF(H10<>H9,I10,J9+I9) -> 1.25 | K10: =ROUND(J10,0) -> 1 | N10: 5 | O10: 15 | P10: 34 | Q10: {=_xlfn.IFNA(INDEX(_xlfn.ANCHORARRAY($N$43),MATCH(P10,$P$43:$P$98))+1,1)} -> 4 | S10: 购买体力4次 | T10: 60 | U10: =T10*10 -> 600
B11: 7 | C11: 10 | D11: =C11+D10 -> 140 | E11: 5 | F11: =SUM($D$5:D11) -> 770 | G11: =SUM($D$5:D11)-10*SUM($E$5:E11) -> 470 | H11: {=INDEX($N$5:$N$18,MATCH(MIN(IF($P$5:$P$18>B11,$P$5:$P$18)),$P$5:$P$18,0))} -> 1 | I11: =VLOOKUP(H11,$N$5:$O$18,2,0)/COUNTIF($H$5:$H$74,H11) -> 1.25 | J11: =IF(H11<>H10,I11,J10+I10) -> 2.5 | K11: =ROUND(J11,0) -> 3 | N11: 6 | O11: 15 | P11: 37 | Q11: {=_xlfn.IFNA(INDEX(_xlfn.ANCHORARRAY($N$43),MATCH(P11,$P$43:$P$98))+1,1)} -> 5 | S11: 购买体力5次 | T11: 60 | U11: =T11*10 -> 600
B12: 8 | C12: 10 | D12: =C12+D11 -> 150 | E12: 5 | F12: =SUM($D$5:D12) -> 920 | G12: =SUM($D$5:D12)-10*SUM($E$5:E12) -> 570 | H12: {=INDEX($N$5:$N$18,MATCH(MIN(IF($P$5:$P$18>B12,$P$5:$P$18)),$P$5:$P$18,0))} -> 1 | I12: =VLOOKUP(H12,$N$5:$O$18,2,0)/COUNTIF($H$5:$H$74,H12) -> 1.25 | J12: =IF(H12<>H11,I12,J11+I11) -> 3.75 | K12: =ROUND(J12,0) -> 4 | N12: 7 | O12: 15 | P12: 40 | Q12: {=_xlfn.IFNA(INDEX(_xlfn.ANCHORARRAY($N$43),MATCH(P12,$P$43:$P$98))+1,1)} -> 7 | S12: 购买体力6次 | T12: 60 | U12: =T12*10 -> 600
B13: 9 | C13: 10 | D13: =C13+D12 -> 160 | E13: 5 | F13: =SUM($D$5:D13) -> 1080 | G13: =SUM($D$5:D13)-10*SUM($E$5:E13) -> 680 | H13: {=INDEX($N$5:$N$18,MATCH(MIN(IF($P$5:$P$18>B13,$P$5:$P$18)),$P$5:$P$18,0))} -> 1 | I13: =VLOOKUP(H13,$N$5:$O$18,2,0)/COUNTIF($H$5:$H$74,H13) -> 1.25 | J13: =IF(H13<>H12,I13,J12+I12) -> 5 | K13: =ROUND(J13,0) -> 5 | S13: 购买体力7次 | T13: 60 | U13: =T13*10 -> 600
B14: 10 | C14: 10 | D14: =C14+D13 -> 170 | E14: 5 | F14: =SUM($D$5:D14) -> 1250 | G14: =SUM($D$5:D14)-10*SUM($E$5:E14) -> 800 | H14: {=INDEX($N$5:$N$18,MATCH(MIN(IF($P$5:$P$18>B14,$P$5:$P$18)),$P$5:$P$18,0))} -> 1 | I14: =VLOOKUP(H14,$N$5:$O$18,2,0)/COUNTIF($H$5:$H$74,H14) -> 1.25 | J14: =IF(H14<>H13,I14,J13+I13) -> 6.25 | K14: =ROUND(J14,0) -> 6 | S14: 购买体力8次 | T14: 60 | U14: =T14*10 -> 600
B15: 11 | C15: 20 | D15: =C15+D14 -> 190 | E15: 10 | F15: =SUM($D$5:D15) -> 1440 | G15: =SUM($D$5:D15)-10*SUM($E$5:E15) -> 890 | H15: {=INDEX($N$5:$N$18,MATCH(MIN(IF($P$5:$P$18>B15,$P$5:$P$18)),$P$5:$P$18,0))} -> 1 | I15: =VLOOKUP(H15,$N$5:$O$18,2,0)/COUNTIF($H$5:$H$74,H15) -> 1.25 | J15: =IF(H15<>H14,I15,J14+I14) -> 7.5 | K15: =ROUND(J15,0) -> 8
B16: 12 | C16: 20 | D16: =C16+D15 -> 210 | E16: 10 | F16: =SUM($D$5:D16) -> 1650 | G16: =SUM($D$5:D16)-10*SUM($E$5:E16) -> 1000 | H16: {=INDEX($N$5:$N$18,MATCH(MIN(IF($P$5:$P$18>B16,$P$5:$P$18)),$P$5:$P$18,0))} -> 1 | I16: =VLOOKUP(H16,$N$5:$O$18,2,0)/COUNTIF($H$5:$H$74,H16) -> 1.25 | J16: =IF(H16<>H15,I16,J15+I15) -> 8.75 | K16: =ROUND(J16,0) -> 9 | T16: 小R | U16: =SUM(U5:U7) -> 4500
B17: 13 | C17: 20 | D17: =C17+D16 -> 230 | E17: 10 | F17: =SUM($D$5:D17) -> 1880 | G17: =SUM($D$5:D17)-10*SUM($E$5:E17) -> 1130 | H17: {=INDEX($N$5:$N$18,MATCH(MIN(IF($P$5:$P$18>B17,$P$5:$P$18)),$P$5:$P$18,0))} -> 1 | I17: =VLOOKUP(H17,$N$5:$O$18,2,0)/COUNTIF($H$5:$H$74,H17) -> 1.25 | J17: =IF(H17<>H16,I17,J16+I16) -> 10 | K17: =ROUND(J17,0) -> 10 | T17: 中R | U17: =SUM(U5:U9) -> 5700
B18: 14 | C18: 20 | D18: =C18+D17 -> 250 | E18: 10 | F18: =SUM($D$5:D18) -> 2130 | G18: =SUM($D$5:D18)-10*SUM($E$5:E18) -> 1280 | H18: {=INDEX($N$5:$N$18,MATCH(MIN(IF($P$5:$P$18>B18,$P$5:$P$18)),$P$5:$P$18,0))} -> 2 | I18: =VLOOKUP(H18,$N$5:$O$18,2,0)/COUNTIF($H$5:$H$74,H18) -> 2.5 | J18: =IF(H18<>H17,I18,J17+I17) -> 2.5 | K18: =ROUND(J18,0) -> 3 | T18: 大R | U18: =SUM(U5:U14) -> 8700
B19: 15 | C19: 20 | D19: =C19+D18 -> 270 | E19: 10 | F19: =SUM($D$5:D19) -> 2400 | G19: =SUM($D$5:D19)-10*SUM($E$5:E19) -> 1450 | H19: {=INDEX($N$5:$N$18,MATCH(MIN(IF($P$5:$P$18>B19,$P$5:$P$18)),$P$5:$P$18,0))} -> 2 | I19: =VLOOKUP(H19,$N$5:$O$18,2,0)/COUNTIF($H$5:$H$74,H19) -> 2.5 | J19: =IF(H19<>H18,I19,J18+I18) -> 5 | K19: =ROUND(J19,0) -> 5
B20: 16 | C20: 30 | D20: =C20+D19 -> 300 | E20: 10 | F20: =SUM($D$5:D20) -> 2700 | G20: =SUM($D$5:D20)-10*SUM($E$5:E20) -> 1650 | H20: {=INDEX($N$5:$N$18,MATCH(MIN(IF($P$5:$P$18>B20,$P$5:$P$18)),$P$5:$P$18,0))} -> 2 | I20: =VLOOKUP(H20,$N$5:$O$18,2,0)/COUNTIF($H$5:$H$74,H20) -> 2.5 | J20: =IF(H20<>H19,I20,J19+I19) -> 7.5 | K20: =ROUND(J20,0) -> 8 | N20: 天数 | O20: 等级 | P20: 所需经验 | Q20: 每天经验
B21: 17 | C21: 30 | D21: =C21+D20 -> 330 | E21: 10 | F21: =SUM($D$5:D21) -> 3030 | G21: =SUM($D$5:D21)-10*SUM($E$5:E21) -> 1880 | H21: {=INDEX($N$5:$N$18,MATCH(MIN(IF($P$5:$P$18>B21,$P$5:$P$18)),$P$5:$P$18,0))} -> 2 | I21: =VLOOKUP(H21,$N$5:$O$18,2,0)/COUNTIF($H$5:$H$74,H21) -> 2.5 | J21: =IF(H21<>H20,I21,J20+I20) -> 10 | K21: =ROUND(J21,0) -> 10 | N21: 1 | O21: 25 | P21: =VLOOKUP(O21-1,$B:$G,6,0) -> 4330 | Q21: =P21 -> 4330 | S21: =AVERAGE($Q$21:Q21) -> 4330
B22: 18 | C22: 30 | D22: =C22+D21 -> 360 | E22: 10 | F22: =SUM($D$5:D22) -> 3390 | G22: =SUM($D$5:D22)-10*SUM($E$5:E22) -> 2140 | H22: {=INDEX($N$5:$N$18,MATCH(MIN(IF($P$5:$P$18>B22,$P$5:$P$18)),$P$5:$P$18,0))} -> 2 | I22: =VLOOKUP(H22,$N$5:$O$18,2,0)/COUNTIF($H$5:$H$74,H22) -> 2.5 | J22: =IF(H22<>H21,I22,J21+I21) -> 12.5 | K22: =ROUND(J22,0) -> 13 | N22: 2 | O22: 31 | P22: =VLOOKUP(O22-1,$B:$G,6,0) -> 8950 | Q22: =P22-P21 -> 4620 | S22: =AVERAGE($Q$21:Q22) -> 4475
B23: 19 | C23: 30 | D23: =C23+D22 -> 390 | E23: 10 | F23: =SUM($D$5:D23) -> 3780 | G23: =SUM($D$5:D23)-10*SUM($E$5:E23) -> 2430 | H23: {=INDEX($N$5:$N$18,MATCH(MIN(IF($P$5:$P$18>B23,$P$5:$P$18)),$P$5:$P$18,0))} -> 2 | I23: =VLOOKUP(H23,$N$5:$O$18,2,0)/COUNTIF($H$5:$H$74,H23) -> 2.5 | J23: =IF(H23<>H22,I23,J22+I22) -> 15 | K23: =ROUND(J23,0) -> 15 | N23: 3 | O23: 34 | P23: =VLOOKUP(O23-1,$B:$G,6,0) -> 13060 | Q23: =P23-P22 -> 4110 | S23: =AVERAGE($Q$21:Q23) -> 4353.3333
B24: 20 | C24: 30 | D24: =C24+D23 -> 420 | E24: 10 | F24: =SUM($D$5:D24) -> 4200 | G24: =SUM($D$5:D24)-10*SUM($E$5:E24) -> 2750 | H24: {=INDEX($N$5:$N$18,MATCH(MIN(IF($P$5:$P$18>B24,$P$5:$P$18)),$P$5:$P$18,0))} -> 3 | I24: =VLOOKUP(H24,$N$5:$O$18,2,0)/COUNTIF($H$5:$H$74,H24) -> 3 | J24: =IF(H24<>H23,I24,J23+I23) -> 3 | K24: =ROUND(J24,0) -> 3 | N24: 4 | O24: 36 | P24: =VLOOKUP(O24-1,$B:$G,6,0) -> 16800 | Q24: =P24-P23 -> 3740 | S24: =AVERAGE($Q$21:Q24) -> 4200
B25: 21 | C25: 50 | D25: =C25+D24 -> 470 | E25: 15 | F25: =SUM($D$5:D25) -> 4670 | G25: =SUM($D$5:D25)-10*SUM($E$5:E25) -> 3070 | H25: {=INDEX($N$5:$N$18,MATCH(MIN(IF($P$5:$P$18>B25,$P$5:$P$18)),$P$5:$P$18,0))} -> 3 | I25: =VLOOKUP(H25,$N$5:$O$18,2,0)/COUNTIF($H$5:$H$74,H25) -> 3 | J25: =IF(H25<>H24,I25,J24+I24) -> 6 | K25: =ROUND(J25,0) -> 6 | N25: 5 | O25: 38 | P25: =VLOOKUP(O25-1,$B:$G,6,0) -> 21640 | Q25: =P25-P24 -> 4840 | S25: =AVERAGE($Q$21:Q25) -> 4328
B26: 22 | C26: 50 | D26: =C26+D25 -> 520 | E26: 15 | F26: =SUM($D$5:D26) -> 5190 | G26: =SUM($D$5:D26)-10*SUM($E$5:E26) -> 3440 | H26: {=INDEX($N$5:$N$18,MATCH(MIN(IF($P$5:$P$18>B26,$P$5:$P$18)),$P$5:$P$18,0))} -> 3 | I26: =VLOOKUP(H26,$N$5:$O$18,2,0)/COUNTIF($H$5:$H$74,H26) -> 3 | J26: =IF(H26<>H25,I26,J25+I25) -> 9 | K26: =ROUND(J26,0) -> 9 | N26: 6 | O26: 38 | P26: =VLOOKUP(O26-1,$B:$G,6,0) -> 21640 | Q26: =P26-P25 -> 0 | S26: =AVERAGE($Q$21:Q26) -> 3606.6667
B27: 23 | C27: 50 | D27: =C27+D26 -> 570 | E27: 15 | F27: =SUM($D$5:D27) -> 5760 | G27: =SUM($D$5:D27)-10*SUM($E$5:E27) -> 3860 | H27: {=INDEX($N$5:$N$18,MATCH(MIN(IF($P$5:$P$18>B27,$P$5:$P$18)),$P$5:$P$18,0))} -> 3 | I27: =VLOOKUP(H27,$N$5:$O$18,2,0)/COUNTIF($H$5:$H$74,H27) -> 3 | J27: =IF(H27<>H26,I27,J26+I26) -> 12 | K27: =ROUND(J27,0) -> 12 | N27: 7 | O27: 40 | P27: =VLOOKUP(O27-1,$B:$G,6,0) -> 27680 | Q27: =P27-P26 -> 6040 | S27: =AVERAGE($Q$21:Q27) -> 3954.2857
B28: 24 | C28: 50 | D28: =C28+D27 -> 620 | E28: 15 | F28: =SUM($D$5:D28) -> 6380 | G28: =SUM($D$5:D28)-10*SUM($E$5:E28) -> 4330 | H28: {=INDEX($N$5:$N$18,MATCH(MIN(IF($P$5:$P$18>B28,$P$5:$P$18)),$P$5:$P$18,0))} -> 3 | I28: =VLOOKUP(H28,$N$5:$O$18,2,0)/COUNTIF($H$5:$H$74,H28) -> 3 | J28: =IF(H28<>H27,I28,J27+I27) -> 15 | K28: =ROUND(J28,0) -> 15 | N28: 8 | O28: 41 | P28: =VLOOKUP(O28-1,$B:$G,6,0) -> 31150 | Q28: =P28-P27 -> 3470 | S28: =AVERAGE($Q$21:Q28) -> 3893.75
B29: 25 | C29: 50 | D29: =C29+D28 -> 670 | E29: 15 | F29: =SUM($D$5:D29) -> 7050 | G29: =SUM($D$5:D29)-10*SUM($E$5:E29) -> 4850 | H29: {=INDEX($N$5:$N$18,MATCH(MIN(IF($P$5:$P$18>B29,$P$5:$P$18)),$P$5:$P$18,0))} -> 4 | I29: =VLOOKUP(H29,$N$5:$O$18,2,0)/COUNTIF($H$5:$H$74,H29) -> 3 | J29: =IF(H29<>H28,I29,J28+I28) -> 3 | K29: =ROUND(J29,0) -> 3 | N29: 9 | O29: 42 | P29: =VLOOKUP(O29-1,$B:$G,6,0) -> 34920 | Q29: =P29-P28 -> 3770 | S29: =AVERAGE($Q$21:Q29) -> 3880
B30: 26 | C30: 100 | D30: =C30+D29 -> 770 | E30: 15 | F30: =SUM($D$5:D30) -> 7820 | G30: =SUM($D$5:D30)-10*SUM($E$5:E30) -> 5470 | H30: {=INDEX($N$5:$N$18,MATCH(MIN(IF($P$5:$P$18>B30,$P$5:$P$18)),$P$5:$P$18,0))} -> 4 | I30: =VLOOKUP(H30,$N$5:$O$18,2,0)/COUNTIF($H$5:$H$74,H30) -> 3 | J30: =IF(H30<>H29,I30,J29+I29) -> 6 | K30: =ROUND(J30,0) -> 6 | N30: 10 | O30: 43 | P30: =VLOOKUP(O30-1,$B:$G,6,0) -> 39140 | Q30: =P30-P29 -> 4220 | S30: =AVERAGE($Q$21:Q30) -> 3914
B31: 27 | C31: 100 | D31: =C31+D30 -> 870 | E31: 15 | F31: =SUM($D$5:D31) -> 8690 | G31: =SUM($D$5:D31)-10*SUM($E$5:E31) -> 6190 | H31: {=INDEX($N$5:$N$18,MATCH(MIN(IF($P$5:$P$18>B31,$P$5:$P$18)),$P$5:$P$18,0))} -> 4 | I31: =VLOOKUP(H31,$N$5:$O$18,2,0)/COUNTIF($H$5:$H$74,H31) -> 3 | J31: =IF(H31<>H30,I31,J30+I30) -> 9 | K31: =ROUND(J31,0) -> 9 | N31: 11 | O31: 44 | P31: =VLOOKUP(O31-1,$B:$G,6,0) -> 43860 | Q31: =P31-P30 -> 4720 | S31: =AVERAGE($Q$21:Q31) -> 3987.2727
B32: 28 | C32: 100 | D32: =C32+D31 -> 970 | E32: 15 | F32: =SUM($D$5:D32) -> 9660 | G32: =SUM($D$5:D32)-10*SUM($E$5:E32) -> 7010 | H32: {=INDEX($N$5:$N$18,MATCH(MIN(IF($P$5:$P$18>B32,$P$5:$P$18)),$P$5:$P$18,0))} -> 4 | I32: =VLOOKUP(H32,$N$5:$O$18,2,0)/COUNTIF($H$5:$H$74,H32) -> 3 | J32: =IF(H32<>H31,I32,J31+I31) -> 12 | K32: =ROUND(J32,0) -> 12 | N32: 12 | O32: 45 | P32: =VLOOKUP(O32-1,$B:$G,6,0) -> 49130 | Q32: =P32-P31 -> 5270 | S32: =AVERAGE($Q$21:Q32) -> 4094.1667
B33: 29 | C33: 100 | D33: =C33+D32 -> 1070 | E33: 15 | F33: =SUM($D$5:D33) -> 10730 | G33: =SUM($D$5:D33)-10*SUM($E$5:E33) -> 7930 | H33: {=INDEX($N$5:$N$18,MATCH(MIN(IF($P$5:$P$18>B33,$P$5:$P$18)),$P$5:$P$18,0))} -> 4 | I33: =VLOOKUP(H33,$N$5:$O$18,2,0)/COUNTIF($H$5:$H$74,H33) -> 3 | J33: =IF(H33<>H32,I33,J32+I32) -> 15 | K33: =ROUND(J33,0) -> 15 | N33: 13 | O33: 45 | P33: =VLOOKUP(O33-1,$B:$G,6,0) -> 49130 | Q33: =P33-P32 -> 0 | S33: =AVERAGE($Q$21:Q33) -> 3779.2308
... B39: 35 | C39: 200 | D39: =C39+D38 -> 2170 | E39: 20 | F39: =SUM($D$5:D39) -> 20750 | G39: =SUM($D$5:D39)-10*SUM($E$5:E39) -> 16800 | H39: {=INDEX($N$5:$N$18,MATCH(MIN(IF($P$5:$P$18>B39,$P$5:$P$18)),$P$5:$P$18,0))} -> 6 | I39: =VLOOKUP(H39,$N$5:$O$18,2,0)/COUNTIF($H$5:$H$74,H39) -> 5 | J39: =IF(H39<>H38,I39,J38+I38) -> 10 | K39: =ROUND(J39,0) -> 10 | N39: 19 | O39: 50 | P39: =VLOOKUP(O39-1,$B:$G,6,0) -> 85480 | Q39: =P39-P38 -> 8770 | S39: =AVERAGE($Q$21:Q39) -> 4498.9474
B40: 36 | C40: 300 | D40: =C40+D39 -> 2470 | E40: 20 | F40: =SUM($D$5:D40) -> 23220 | G40: =SUM($D$5:D40)-10*SUM($E$5:E40) -> 19070 | H40: {=INDEX($N$5:$N$18,MATCH(MIN(IF($P$5:$P$18>B40,$P$5:$P$18)),$P$5:$P$18,0))} -> 6 | I40: =VLOOKUP(H40,$N$5:$O$18,2,0)/COUNTIF($H$5:$H$74,H40) -> 5 | J40: =IF(H40<>H39,I40,J39+I39) -> 15 | K40: =ROUND(J40,0) -> 15
B41: 37 | C41: 300 | D41: =C41+D40 -> 2770 | E41: 20 | F41: =SUM($D$5:D41) -> 25990 | G41: =SUM($D$5:D41)-10*SUM($E$5:E41) -> 21640 | H41: {=INDEX($N$5:$N$18,MATCH(MIN(IF($P$5:$P$18>B41,$P$5:$P$18)),$P$5:$P$18,0))} -> 7 | I41: =VLOOKUP(H41,$N$5:$O$18,2,0)/COUNTIF($H$5:$H$74,H41) -> 5 | J41: =IF(H41<>H40,I41,J40+I40) -> 5 | K41: =ROUND(J41,0) -> 5
B42: 38 | C42: 300 | D42: =C42+D41 -> 3070 | E42: 20 | F42: =SUM($D$5:D42) -> 29060 | G42: =SUM($D$5:D42)-10*SUM($E$5:E42) -> 24510 | H42: {=INDEX($N$5:$N$18,MATCH(MIN(IF($P$5:$P$18>B42,$P$5:$P$18)),$P$5:$P$18,0))} -> 7 | I42: =VLOOKUP(H42,$N$5:$O$18,2,0)/COUNTIF($H$5:$H$74,H42) -> 5 | J42: =IF(H42<>H41,I42,J41+I41) -> 10 | K42: =ROUND(J42,0) -> 10 | N42: 天数 | O42: 总经验 | P42: 实际等级
B43: 39 | C43: 300 | D43: =C43+D42 -> 3370 | E43: 20 | F43: =SUM($D$5:D43) -> 32430 | G43: =SUM($D$5:D43)-10*SUM($E$5:E43) -> 27680 | H43: {=INDEX($N$5:$N$18,MATCH(MIN(IF($P$5:$P$18>B43,$P$5:$P$18)),$P$5:$P$18,0))} -> 7 | I43: =VLOOKUP(H43,$N$5:$O$18,2,0)/COUNTIF($H$5:$H$74,H43) -> 5 | J43: =IF(H43<>H42,I43,J42+I42) -> 15 | K43: =ROUND(J43,0) -> 15 | N43: {=_xlfn.SEQUENCE(F3,1,1,1)} -> 1 | O43: =N43*$U$16 -> 4500 | P43: {=INDEX(_xlfn.ANCHORARRAY($B$5),MATCH(O43,$G$5:$G$64,1))+1} -> 25
B44: 40 | C44: 300 | D44: =C44+D43 -> 3670 | E44: 20 | F44: =SUM($D$5:D44) -> 36100 | G44: =SUM($D$5:D44)-10*SUM($E$5:E44) -> 31150 | N44: 2 | O44: =N44*$U$16 -> 9000 | P44: {=INDEX(_xlfn.ANCHORARRAY($B$5),MATCH(O44,$G$5:$G$64,1))+1} -> 31
B45: 41 | C45: 400 | D45: =C45+D44 -> 4070 | E45: 30 | F45: =SUM($D$5:D45) -> 40170 | G45: =SUM($D$5:D45)-10*SUM($E$5:E45) -> 34920 | N45: 3 | O45: =N45*$U$16 -> 13500 | P45: {=INDEX(_xlfn.ANCHORARRAY($B$5),MATCH(O45,$G$5:$G$64,1))+1} -> 34
B46: 42 | C46: 450 | D46: =C46+D45 -> 4520 | E46: 30 | F46: =SUM($D$5:D46) -> 44690 | G46: =SUM($D$5:D46)-10*SUM($E$5:E46) -> 39140 | N46: 4 | O46: =N46*$U$16 -> 18000 | P46: {=INDEX(_xlfn.ANCHORARRAY($B$5),MATCH(O46,$G$5:$G$64,1))+1} -> 36
B47: 43 | C47: 500 | D47: =C47+D46 -> 5020 | E47: 30 | F47: =SUM($D$5:D47) -> 49710 | G47: =SUM($D$5:D47)-10*SUM($E$5:E47) -> 43860 | N47: 5 | O47: =N47*$U$16 -> 22500 | P47: {=INDEX(_xlfn.ANCHORARRAY($B$5),MATCH(O47,$G$5:$G$64,1))+1} -> 38
B48: 44 | C48: 550 | D48: =C48+D47 -> 5570 | E48: 30 | F48: =SUM($D$5:D48) -> 55280 | G48: =SUM($D$5:D48)-10*SUM($E$5:E48) -> 49130 | N48: 6 | O48: =N48*$U$16 -> 27000 | P48: {=INDEX(_xlfn.ANCHORARRAY($B$5),MATCH(O48,$G$5:$G$64,1))+1} -> 39
B49: 45 | C49: 600 | D49: =C49+D48 -> 6170 | E49: 30 | F49: =SUM($D$5:D49) -> 61450 | G49: =SUM($D$5:D49)-10*SUM($E$5:E49) -> 55000 | N49: 7 | O49: =N49*$U$16 -> 31500 | P49: {=INDEX(_xlfn.ANCHORARRAY($B$5),MATCH(O49,$G$5:$G$64,1))+1} -> 41
B50: 46 | C50: 650 | D50: =C50+D49 -> 6820 | E50: 30 | F50: =SUM($D$5:D50) -> 68270 | G50: =SUM($D$5:D50)-10*SUM($E$5:E50) -> 61520 | N50: 8 | O50: =N50*$U$16 -> 36000 | P50: {=INDEX(_xlfn.ANCHORARRAY($B$5),MATCH(O50,$G$5:$G$64,1))+1} -> 42
B51: 47 | C51: 700 | D51: =C51+D50 -> 7520 | E51: 30 | F51: =SUM($D$5:D51) -> 75790 | G51: =SUM($D$5:D51)-10*SUM($E$5:E51) -> 68740 | N51: 9 | O51: =N51*$U$16 -> 40500 | P51: {=INDEX(_xlfn.ANCHORARRAY($B$5),MATCH(O51,$G$5:$G$64,1))+1} -> 43
B52: 48 | C52: 750 | D52: =C52+D51 -> 8270 | E52: 30 | F52: =SUM($D$5:D52) -> 84060 | G52: =SUM($D$5:D52)-10*SUM($E$5:E52) -> 76710 | N52: 10 | O52: =N52*$U$16 -> 45000 | P52: {=INDEX(_xlfn.ANCHORARRAY($B$5),MATCH(O52,$G$5:$G$64,1))+1} -> 44
B53: 49 | C53: 800 | D53: =C53+D52 -> 9070 | E53: 30 | F53: =SUM($D$5:D53) -> 93130 | G53: =SUM($D$5:D53)-10*SUM($E$5:E53) -> 85480 | N53: 11 | O53: =N53*$U$16 -> 49500 | P53: {=INDEX(_xlfn.ANCHORARRAY($B$5),MATCH(O53,$G$5:$G$64,1))+1} -> 45
B54: 50 | C54: 850 | D54: =C54+D53 -> 9920 | E54: 30 | F54: =SUM($D$5:D54) -> 103050 | G54: =SUM($D$5:D54)-10*SUM($E$5:E54) -> 95100 | N54: 12 | O54: =N54*$U$16 -> 54000 | P54: {=INDEX(_xlfn.ANCHORARRAY($B$5),MATCH(O54,$G$5:$G$64,1))+1} -> 45
B55: 51 | C55: 1000 | D55: =C55+D54 -> 10920 | E55: 40 | F55: =SUM($D$5:D55) -> 113970 | G55: =SUM($D$5:D55)-10*SUM($E$5:E55) -> 105620 | N55: 13 | O55: =N55*$U$16 -> 58500 | P55: {=INDEX(_xlfn.ANCHORARRAY($B$5),MATCH(O55,$G$5:$G$64,1))+1} -> 46
... B64: 60 | C64: 5000 | D64: =C64+D63 -> 31420 | E64: 40 | F64: =SUM($D$5:D64) -> 286750 | G64: =SUM($D$5:D64)-10*SUM($E$5:E64) -> 274800 | N64: 22 | O64: =N64*$U$16 -> 99000 | P64: {=INDEX(_xlfn.ANCHORARRAY($B$5),MATCH(O64,$G$5:$G$64,1))+1} -> 51
N65: 23 | O65: =N65*$U$16 -> 103500 | P65: {=INDEX(_xlfn.ANCHORARRAY($B$5),MATCH(O65,$G$5:$G$64,1))+1} -> 51
N66: 24 | O66: =N66*$U$16 -> 108000 | P66: {=INDEX(_xlfn.ANCHORARRAY($B$5),MATCH(O66,$G$5:$G$64,1))+1} -> 52
N67: 25 | O67: =N67*$U$16 -> 112500 | P67: {=INDEX(_xlfn.ANCHORARRAY($B$5),MATCH(O67,$G$5:$G$64,1))+1} -> 52
N68: 26 | O68: =N68*$U$16 -> 117000 | P68: {=INDEX(_xlfn.ANCHORARRAY($B$5),MATCH(O68,$G$5:$G$64,1))+1} -> 52
N69: 27 | O69: =N69*$U$16 -> 121500 | P69: {=INDEX(_xlfn.ANCHORARRAY($B$5),MATCH(O69,$G$5:$G$64,1))+1} -> 53
N70: 28 | O70: =N70*$U$16 -> 126000 | P70: {=INDEX(_xlfn.ANCHORARRAY($B$5),MATCH(O70,$G$5:$G$64,1))+1} -> 53
N71: 29 | O71: =N71*$U$16 -> 130500 | P71: {=INDEX(_xlfn.ANCHORARRAY($B$5),MATCH(O71,$G$5:$G$64,1))+1} -> 54
N72: 30 | O72: =N72*$U$16 -> 135000 | P72: {=INDEX(_xlfn.ANCHORARRAY($B$5),MATCH(O72,$G$5:$G$64,1))+1} -> 54
N73: 31 | O73: =N73*$U$16 -> 139500 | P73: {=INDEX(_xlfn.ANCHORARRAY($B$5),MATCH(O73,$G$5:$G$64,1))+1} -> 54
N74: 32 | O74: =N74*$U$16 -> 144000 | P74: {=INDEX(_xlfn.ANCHORARRAY($B$5),MATCH(O74,$G$5:$G$64,1))+1} -> 54
N75: 33 | O75: =N75*$U$16 -> 148500 | P75: {=INDEX(_xlfn.ANCHORARRAY($B$5),MATCH(O75,$G$5:$G$64,1))+1} -> 55
N76: 34 | O76: =N76*$U$16 -> 153000 | P76: {=INDEX(_xlfn.ANCHORARRAY($B$5),MATCH(O76,$G$5:$G$64,1))+1} -> 55
... N98: 56 | O98: =N98*$U$16 -> 252000 | P98: {=INDEX(_xlfn.ANCHORARRAY($B$5),MATCH(O98,$G$5:$G$64,1))+1} -> 60

Sheet 炮台养成
A1: 炮台养成测算
A2: 默认按 1S+1A+1B 的混编阵容测算。这个页签先假设目标炮台本体已经获得，只测材料成长速度；如果首赛季需要先用代币补本体，实际进度通常会比表内慢半档到一档。
A4: 一、炮台养成规则 | J4: 二、竞技场资源口径
A5: 目标上阵阵容 | B5: 1S+1A+1B | C5: 竞技场基础毕业口径 | J5: 非炮台赛季限购成本 | K5: =SUMPRODUCT((竞技场!$J$86:$J$95="赛季限购")*(竞技场!$C$86:$C$95<>"炮台升级小材料")*(竞技场!$C$86:$C$95<>"炮台升级大材料")*竞技场!$G$86:$G$95*竞技场!$K$86:$K$95) -> 1000 | L5: 默认会先买满
A6: S 等级上限 | B6: 50 | C6: 大节点在 10升11 / 20升21 / 30升31 / 40升41 | J6: 赛季限购小材料 | K6: =SUMPRODUCT((竞技场!$J$86:$J$95="赛季限购")*(竞技场!$C$86:$C$95="炮台升级小材料")*竞技场!$D$86:$D$95*竞技场!$K$86:$K$95) -> 6000 | L6: 直接计入当赛季成长
A7: A 等级上限 | B7: 40 | C7: 大节点在 10升11 / 20升21 / 30升31 | J7: 赛季限购大材料 | K7: =SUMPRODUCT((竞技场!$J$86:$J$95="赛季限购")*(竞技场!$C$86:$C$95="炮台升级大材料")*竞技场!$D$86:$D$95*竞技场!$K$86:$K$95) -> 0 | L7: 直接计入当赛季成长
A8: B 等级上限 | B8: 30 | C8: 大节点在 10升11 / 20升21 | J8: 炮台赛季限购成本 | K8: =SUMPRODUCT((竞技场!$J$86:$J$95="赛季限购")*(((竞技场!$C$86:$C$95="炮台升级小材料")+(竞技场!$C$86:$C$95="炮台升级大材料")))*竞技场!$G$86:$G$95*竞技场!$K$86:$K$95) -> 500 | L8: 小材料包 + 大材料包
A9: 升级顺序 | B9: 按档位均衡推进 | C9: 先把 3 个炮台都推到 10/20/30，再把 S/A 推到 40，最后补 S 到50 | J9: 不限购大材料单价 | K9: =SUMPRODUCT((竞技场!$J$86:$J$95="不限购")*(竞技场!$C$86:$C$95="炮台升级大材料")*竞技场!$G$86:$G$95) -> 0 | L9: 剩余代币默认优先买它
A10: 小材料曲线基础值 | B10: 8 | C10: 公式：ROUND(基础值 + (目标等级-1)^指数 * 系数,0) | J10: 不限购小材料/代币 | K10: =SUMPRODUCT((竞技场!$J$86:$J$95="不限购")*(竞技场!$C$86:$C$95="炮台升级小材料")*竞技场!$D$86:$D$95)/SUMPRODUCT((竞技场!$J$86:$J$95="不限购")*(竞技场!$C$86:$C$95="炮台升级小材料")*竞技场!$G$86:$G$95) -> #DIV/0! | L10: 买完大材料后再换小材料
A11: 小材料曲线系数 | B11: 3.5 | C11: 前期压力更低 | J11: 小材料钻石价值 | K11: =VLOOKUP("炮台升级小材料",道具定价!$C:$F,4,0) -> 1 | L11: 从道具定价页读取
A12: 小材料曲线指数 | B12: 1.2 | C12: 保证每级消耗都不一样 | J12: 大材料钻石价值 | K12: =VLOOKUP("炮台升级大材料",道具定价!$C:$F,4,0) -> 1000 | L12: 从道具定价页读取
A15: 三、逐级小材料曲线 | J15: 四、坑深汇总
A16: 目标等级 | B16: 单级小材料 | C16: 累计小材料 | D16: S大材料 | E16: A大材料 | F16: B大材料 | G16: 说明 | J16: 对象 | K16: 等级上限 | L16: 小材料 | M16: 大材料 | N16: 钻石价值 | O16: 最终技能等级 | P16: 说明
A17: 2 | B17: =ROUND($B$10+(A17-1)^$B$12*$B$11,0) -> 12 | C17: =SUM($B$17:B17) -> 12 | D17: 0 | E17: 0 | F17: 0 | G17: 仅提升基础属性 | I17: =_xlfn.CONCAT($H$18,B17,IF(F17=0,"",_xlfn.CONCAT($H$19,F17))) -> 28,12 | J17: S炮台 | K17: =B6 -> 50 | L17: =SUMIFS($B$17:$B$65,$A$17:$A$65,"<="&$B$6) -> 8897 | M17: =COUNTIF($D$17:$D$65,1) -> 4 | N17: =L17*$K$11+M17*$K$12 -> 12897 | O17: =1+M17 -> 5 | P17: 50级上限，4个技能节点
A18: 3 | B18: =ROUND($B$10+(A18-1)^$B$12*$B$11,0) -> 16 | C18: =SUM($B$17:B18) -> 28 | D18: 0 | E18: 0 | F18: 0 | G18: 仅提升基础属性 | H18: 28, | I18: =_xlfn.CONCAT($H$18,B18,IF(F18=0,"",_xlfn.CONCAT($H$19,F18))) -> 28,16 | J18: A炮台 | K18: =B7 -> 40 | L18: =SUMIFS($B$17:$B$65,$A$17:$A$65,"<="&$B$7) -> 5489 | M18: =COUNTIF($E$17:$E$65,1) -> 2 | N18: =L18*$K$11+M18*$K$12 -> 7489 | O18: =1+M18 -> 3 | P18: 40级上限，3个技能节点
A19: 4 | B19: =ROUND($B$10+(A19-1)^$B$12*$B$11,0) -> 21 | C19: =SUM($B$17:B19) -> 49 | D19: 0 | E19: 0 | F19: 0 | G19: 仅提升基础属性 | H19: ;31, | I19: =_xlfn.CONCAT($H$18,B19,IF(F19=0,"",_xlfn.CONCAT($H$19,F19))) -> 28,21 | J19: B炮台 | K19: =B8 -> 30 | L19: =SUMIFS($B$17:$B$65,$A$17:$A$65,"<="&$B$8) -> 2956 | M19: =COUNTIF($F$17:$F$65,1) -> 0 | N19: =L19*$K$11+M19*$K$12 -> 2956 | O19: =1+M19 -> 1 | P19: 30级上限，2个技能节点
A20: 5 | B20: =ROUND($B$10+(A20-1)^$B$12*$B$11,0) -> 26 | C20: =SUM($B$17:B20) -> 75 | D20: 0 | E20: 0 | F20: 0 | G20: 仅提升基础属性 | I20: =_xlfn.CONCAT($H$18,B20,IF(F20=0,"",_xlfn.CONCAT($H$19,F20))) -> 28,26 | J20: 混编总计 | K20: "1S+1A+1B" | L20: =SUM(L17:L19) -> 17342 | M20: =SUM(M17:M19) -> 6 | N20: =SUM(N17:N19) -> 23342 | O20: "S5 / A4 / B3" | P20: 竞技场基础毕业目标
A21: 6 | B21: =ROUND($B$10+(A21-1)^$B$12*$B$11,0) -> 32 | C21: =SUM($B$17:B21) -> 107 | D21: 0 | E21: 0 | F21: 0 | G21: 仅提升基础属性 | I21: =_xlfn.CONCAT($H$18,B21,IF(F21=0,"",_xlfn.CONCAT($H$19,F21))) -> 28,32 | J21: 3S顶配参考 | K21: "50/50/50" | L21: =L17*3 -> 26691 | M21: =M17*3 -> 12 | N21: =N17*3 -> 38691 | O21: "S5 / S5 / S5" | P21: 如果长期层差不够，更适合用它做终局
A22: 7 | B22: =ROUND($B$10+(A22-1)^$B$12*$B$11,0) -> 38 | C22: =SUM($B$17:B22) -> 145 | D22: 0 | E22: 0 | F22: 0 | G22: 仅提升基础属性 | I22: =_xlfn.CONCAT($H$18,B22,IF(F22=0,"",_xlfn.CONCAT($H$19,F22))) -> 28,38
A23: 8 | B23: =ROUND($B$10+(A23-1)^$B$12*$B$11,0) -> 44 | C23: =SUM($B$17:B23) -> 189 | D23: 0 | E23: 0 | F23: 0 | G23: 仅提升基础属性 | I23: =_xlfn.CONCAT($H$18,B23,IF(F23=0,"",_xlfn.CONCAT($H$19,F23))) -> 28,44
A24: 9 | B24: =ROUND($B$10+(A24-1)^$B$12*$B$11,0) -> 50 | C24: =SUM($B$17:B24) -> 239 | D24: 0 | E24: 0 | F24: 0 | G24: 仅提升基础属性 | I24: =_xlfn.CONCAT($H$18,B24,IF(F24=0,"",_xlfn.CONCAT($H$19,F24))) -> 28,50
A25: 10 | B25: =ROUND($B$10+(A25-1)^$B$12*$B$11,0) -> 57 | C25: =SUM($B$17:B25) -> 296 | D25: 0 | E25: 0 | F25: 0 | G25: 仅提升基础属性 | I25: =_xlfn.CONCAT($H$18,B25,IF(F25=0,"",_xlfn.CONCAT($H$19,F25))) -> 28,57
A26: 11 | B26: =ROUND($B$10+(A26-1)^$B$12*$B$11,0) -> 63 | C26: =SUM($B$17:B26) -> 359 | D26: 1 | E26: 0 | F26: 0 | G26: S技能+1 / A技能+1 / B技能+1 | I26: =_xlfn.CONCAT($H$18,B26,IF(F26=0,"",_xlfn.CONCAT($H$19,F26))) -> 28,63
A27: 12 | B27: =ROUND($B$10+(A27-1)^$B$12*$B$11,0) -> 70 | C27: =SUM($B$17:B27) -> 429 | D27: 0 | E27: 0 | F27: 0 | G27: 仅提升基础属性 | I27: =_xlfn.CONCAT($H$18,B27,IF(F27=0,"",_xlfn.CONCAT($H$19,F27))) -> 28,70
A28: 13 | B28: =ROUND($B$10+(A28-1)^$B$12*$B$11,0) -> 77 | C28: =SUM($B$17:B28) -> 506 | D28: 0 | E28: 0 | F28: 0 | G28: 仅提升基础属性 | I28: =_xlfn.CONCAT($H$18,B28,IF(F28=0,"",_xlfn.CONCAT($H$19,F28))) -> 28,77
A29: 14 | B29: =ROUND($B$10+(A29-1)^$B$12*$B$11,0) -> 84 | C29: =SUM($B$17:B29) -> 590 | D29: 0 | E29: 0 | F29: 0 | G29: 仅提升基础属性 | I29: =_xlfn.CONCAT($H$18,B29,IF(F29=0,"",_xlfn.CONCAT($H$19,F29))) -> 28,84
A30: 15 | B30: =ROUND($B$10+(A30-1)^$B$12*$B$11,0) -> 91 | C30: =SUM($B$17:B30) -> 681 | D30: 0 | E30: 0 | F30: 0 | G30: 仅提升基础属性 | I30: =_xlfn.CONCAT($H$18,B30,IF(F30=0,"",_xlfn.CONCAT($H$19,F30))) -> 28,91
A31: 16 | B31: =ROUND($B$10+(A31-1)^$B$12*$B$11,0) -> 98 | C31: =SUM($B$17:B31) -> 779 | D31: 0 | E31: 0 | F31: 0 | G31: 仅提升基础属性 | I31: =_xlfn.CONCAT($H$18,B31,IF(F31=0,"",_xlfn.CONCAT($H$19,F31))) -> 28,98
A32: 17 | B32: =ROUND($B$10+(A32-1)^$B$12*$B$11,0) -> 106 | C32: =SUM($B$17:B32) -> 885 | D32: 0 | E32: 0 | F32: 0 | G32: 仅提升基础属性 | I32: =_xlfn.CONCAT($H$18,B32,IF(F32=0,"",_xlfn.CONCAT($H$19,F32))) -> 28,106
A33: 18 | B33: =ROUND($B$10+(A33-1)^$B$12*$B$11,0) -> 113 | C33: =SUM($B$17:B33) -> 998 | D33: 0 | E33: 0 | F33: 0 | G33: 仅提升基础属性 | I33: =_xlfn.CONCAT($H$18,B33,IF(F33=0,"",_xlfn.CONCAT($H$19,F33))) -> 28,113
... A65: 50 | B65: =ROUND($B$10+(A65-1)^$B$12*$B$11,0) -> 382 | C65: =SUM($B$17:B65) -> 8897 | D65: 0 | E65: 0 | F65: 0 | G65: 仅提升基础属性 | I65: =_xlfn.CONCAT($H$18,B65,IF(F65=0,"",_xlfn.CONCAT($H$19,F65))) -> 28,382
A68: 五、推荐升级路径 | K68: 六、结合竞技场产出的玩家进度
A69: 步骤 | B69: 档位 | C69: 品质 | D69: 达成等级 | E69: 单步小材料 | F69: 单步大材料 | G69: 累计小材料 | H69: 累计大材料 | I69: 进度标签 | K69: 玩家类型 | L69: 目标段位 | M69: 胜场 | N69: 负场 | O69: 稳态赛季代币 | P69: 首赛季代币 | Q69: 稳态赛季小材料 | R69: 稳态赛季大材料 | S69: 首赛季小材料 | T69: 首赛季大材料 | U69: 第1赛季进度 | V69: 第2赛季进度 | W69: 第3赛季进度 | X69: 第4赛季进度 | Y69: 满成所需赛季数 | Z69: 本体判断 | AA69: 备注
A70: 0 | B70: 起始 | C70: - | D70: - | E70: 0 | F70: 0 | G70: 0 | H70: 0 | I70: S1/A1/B1 | K70: =竞技场分层!A20 -> 免费 | L70: =竞技场分层!L20 -> 黄金Ⅲ | M70: =竞技场分层!I20 -> 32 | N70: =竞技场分层!J20 -> 38 | O70: =M70*竞技场!$C$40+N70*竞技场!$C$44+SUMPRODUCT((竞技场!$B$100:$B$108<=M70)*(竞技场!$C$100:$C$108="竞技场代币")*竞技场!$D$100:$D$108)+INDEX(竞技场!$K$49:$K$70,MATCH(L70,竞技场!$B$49:$B$70,0)) -> 776 | P70: =O70+SUMPRODUCT((ROW(竞技场!$B$50:$B$70)-ROW(竞技场!$B$50)+1<=MATCH(L70,竞技场!$B$50:$B$70,0))*(((竞技场!$D$50:$D$70="竞技场代币")*竞技场!$E$50:$E$70)+((竞技场!$F$50:$F$70="竞技场代币")*竞技场!$G$50:$G$70))) -> 1776 | Q70: =M70*竞技场!$F$40+N70*竞技场!$F$44+SUMPRODUCT((竞技场!$B$100:$B$108<=M70)*(竞技场!$C$100:$C$108="炮台升级小材料")*竞技场!$D$100:$D$108)+$K$6+MOD(MAX(O70-$K$5-$K$8,0),$K$9)*$K$10 -> #DIV/0! | R70: =SUMPRODUCT((竞技场!$B$100:$B$108<=M70)*(竞技场!$C$100:$C$108="炮台升级大材料")*竞技场!$D$100:$D$108)+$K$7+INT(MAX(O70-$K$5-$K$8,0)/$K$9) -> #DIV/0! | S70: =M70*竞技场!$F$40+N70*竞技场!$F$44+SUMPRODUCT((竞技场!$B$100:$B$108<=M70)*(竞技场!$C$100:$C$108="炮台升级小材料")*竞技场!$D$100:$D$108)+(SUMPRODUCT((ROW(竞技场!$B$50:$B$70)-ROW(竞技场!$B$50)+1<=MATCH(L70,竞技场!$B$50:$B$70,0))*(((竞技场!$D$50:$D$70="炮台升级小材料")*竞技场!$E$50:$E$70)+((竞技场!$F$50:$F$70="炮台升级小材料")*竞技场!$G$50:$G$70))))+$K$6+MOD(MAX(P70-$K$5-$K$8,0),$K$9)*$K$10 -> #DIV/0! | T70: =SUMPRODUCT((竞技场!$B$100:$B$108<=M70)*(竞技场!$C$100:$C$108="炮台升级大材料")*竞技场!$D$100:$D$108)+(SUMPRODUCT((ROW(竞技场!$B$50:$B$70)-ROW(竞技场!$B$50)+1<=MATCH(L70,竞技场!$B$50:$B$70,0))*(((竞技场!$D$50:$D$70="炮台升级大材料")*竞技场!$E$50:$E$70)+((竞技场!$F$50:$F$70="炮台升级大材料")*竞技场!$G$50:$G$70))))+$K$7+INT(MAX(P70-$K$5-$K$8,0)/$K$9) -> #DIV/0! | U70: =LOOKUP(2,1/(($G$70:$G$187<=S70)*($H$70:$H$187<=T70)),$I$70:$I$187) -> #N/A | V70: =LOOKUP(2,1/(($G$70:$G$187<=S70+Q70)*($H$70:$H$187<=T70+R70)),$I$70:$I$187) -> #N/A | W70: =LOOKUP(2,1/(($G$70:$G$187<=S70+Q70*2)*($H$70:$H$187<=T70+R70*2)),$I$70:$I$187) -> #N/A | X70: =LOOKUP(2,1/(($G$70:$G$187<=S70+Q70*3)*($H$70:$H$187<=T70+R70*3)),$I$70:$I$187) -> #N/A | Y70: =IFERROR(MATCH("S50/A40/B30",U70:X70,0),">4") -> >4 | Z70: =IF(MAX(P70-$K$5-$K$8,0)>=750,"赛季限购买完后，还能补齐 1S+1A+1B",IF(MAX(P70-$K$5-$K$8,0)>=650,"赛季限购买完后，还能补 1S+1B",IF(MAX(P70-$K$5-$K$8,0)>=600,"赛季限购买完后，还能补 1S",IF(MAX(P70-$K$5-$K$8,0)>=150,"赛季限购买完后，还能补 1A+1B",IF(MAX(P70-$K$5-$K$8,0)>=100,"赛季限购买完后，还能补 1A",IF(MAX(P70-$K$5-$K$8,0)>=50,"赛季限购买完后，还能补 1B","赛季限购买完后，还不够补本体")))))) -> 赛季限购买完后，还能补 1A+1B | AA70: 首达奖励已经送 3 个 B 炮台，首赛季剩余代币通常还能再补 1A+1B。
A71: 1 | B71: 1-10档 | C71: S | D71: 2 | E71: =INDEX($B$17:$B$65,MATCH(D71,$A$17:$A$65,0)) -> 12 | F71: =IF(C71="S",INDEX($D$17:$D$65,MATCH(D71,$A$17:$A$65,0)),IF(C71="A",INDEX($E$17:$E$65,MATCH(D71,$A$17:$A$65,0)),INDEX($F$17:$F$65,MATCH(D71,$A$17:$A$65,0)))) -> 0 | G71: =G70+E71 -> 12 | H71: =H70+F71 -> 0 | I71: S2/A1/B1 | K71: =竞技场分层!A21 -> 小R | L71: =竞技场分层!L21 -> 黄金Ⅰ | M71: =竞技场分层!I21 -> 43 | N71: =竞技场分层!J21 -> 41 | O71: =M71*竞技场!$C$40+N71*竞技场!$C$44+SUMPRODUCT((竞技场!$B$100:$B$108<=M71)*(竞技场!$C$100:$C$108="竞技场代币")*竞技场!$D$100:$D$108)+INDEX(竞技场!$K$49:$K$70,MATCH(L71,竞技场!$B$49:$B$70,0)) -> 1037 | P71: =O71+SUMPRODUCT((ROW(竞技场!$B$50:$B$70)-ROW(竞技场!$B$50)+1<=MATCH(L71,竞技场!$B$50:$B$70,0))*(((竞技场!$D$50:$D$70="竞技场代币")*竞技场!$E$50:$E$70)+((竞技场!$F$50:$F$70="竞技场代币")*竞技场!$G$50:$G$70))) -> 2637 | Q71: =M71*竞技场!$F$40+N71*竞技场!$F$44+SUMPRODUCT((竞技场!$B$100:$B$108<=M71)*(竞技场!$C$100:$C$108="炮台升级小材料")*竞技场!$D$100:$D$108)+$K$6+MOD(MAX(O71-$K$5-$K$8,0),$K$9)*$K$10 -> #DIV/0! | R71: =SUMPRODUCT((竞技场!$B$100:$B$108<=M71)*(竞技场!$C$100:$C$108="炮台升级大材料")*竞技场!$D$100:$D$108)+$K$7+INT(MAX(O71-$K$5-$K$8,0)/$K$9) -> #DIV/0! | S71: =M71*竞技场!$F$40+N71*竞技场!$F$44+SUMPRODUCT((竞技场!$B$100:$B$108<=M71)*(竞技场!$C$100:$C$108="炮台升级小材料")*竞技场!$D$100:$D$108)+(SUMPRODUCT((ROW(竞技场!$B$50:$B$70)-ROW(竞技场!$B$50)+1<=MATCH(L71,竞技场!$B$50:$B$70,0))*(((竞技场!$D$50:$D$70="炮台升级小材料")*竞技场!$E$50:$E$70)+((竞技场!$F$50:$F$70="炮台升级小材料")*竞技场!$G$50:$G$70))))+$K$6+MOD(MAX(P71-$K$5-$K$8,0),$K$9)*$K$10 -> #DIV/0! | T71: =SUMPRODUCT((竞技场!$B$100:$B$108<=M71)*(竞技场!$C$100:$C$108="炮台升级大材料")*竞技场!$D$100:$D$108)+(SUMPRODUCT((ROW(竞技场!$B$50:$B$70)-ROW(竞技场!$B$50)+1<=MATCH(L71,竞技场!$B$50:$B$70,0))*(((竞技场!$D$50:$D$70="炮台升级大材料")*竞技场!$E$50:$E$70)+((竞技场!$F$50:$F$70="炮台升级大材料")*竞技场!$G$50:$G$70))))+$K$7+INT(MAX(P71-$K$5-$K$8,0)/$K$9) -> #DIV/0! | U71: =LOOKUP(2,1/(($G$70:$G$187<=S71)*($H$70:$H$187<=T71)),$I$70:$I$187) -> #N/A | V71: =LOOKUP(2,1/(($G$70:$G$187<=S71+Q71)*($H$70:$H$187<=T71+R71)),$I$70:$I$187) -> #N/A | W71: =LOOKUP(2,1/(($G$70:$G$187<=S71+Q71*2)*($H$70:$H$187<=T71+R71*2)),$I$70:$I$187) -> #N/A | X71: =LOOKUP(2,1/(($G$70:$G$187<=S71+Q71*3)*($H$70:$H$187<=T71+R71*3)),$I$70:$I$187) -> #N/A | Y71: =IFERROR(MATCH("S50/A40/B30",U71:X71,0),">4") -> >4 | Z71: =IF(MAX(P71-$K$5-$K$8,0)>=750,"赛季限购买完后，还能补齐 1S+1A+1B",IF(MAX(P71-$K$5-$K$8,0)>=650,"赛季限购买完后，还能补 1S+1B",IF(MAX(P71-$K$5-$K$8,0)>=600,"赛季限购买完后，还能补 1S",IF(MAX(P71-$K$5-$K$8,0)>=150,"赛季限购买完后，还能补 1A+1B",IF(MAX(P71-$K$5-$K$8,0)>=100,"赛季限购买完后，还能补 1A",IF(MAX(P71-$K$5-$K$8,0)>=50,"赛季限购买完后，还能补 1B","赛季限购买完后，还不够补本体")))))) -> 赛季限购买完后，还能补齐 1S+1A+1B | AA71: 首达奖励已经送 3 个 B 炮台，首赛季代币结余通常已经能补齐 1S+1A+1B。
A72: 2 | B72: 1-10档 | C72: S | D72: 3 | E72: =INDEX($B$17:$B$65,MATCH(D72,$A$17:$A$65,0)) -> 16 | F72: =IF(C72="S",INDEX($D$17:$D$65,MATCH(D72,$A$17:$A$65,0)),IF(C72="A",INDEX($E$17:$E$65,MATCH(D72,$A$17:$A$65,0)),INDEX($F$17:$F$65,MATCH(D72,$A$17:$A$65,0)))) -> 0 | G72: =G71+E72 -> 28 | H72: =H71+F72 -> 0 | I72: S3/A1/B1 | K72: =竞技场分层!A22 -> 中R | L72: =竞技场分层!L22 -> 铂金Ⅰ | M72: =竞技场分层!I22 -> 58 | N72: =竞技场分层!J22 -> 54 | O72: =M72*竞技场!$C$40+N72*竞技场!$C$44+SUMPRODUCT((竞技场!$B$100:$B$108<=M72)*(竞技场!$C$100:$C$108="竞技场代币")*竞技场!$D$100:$D$108)+INDEX(竞技场!$K$49:$K$70,MATCH(L72,竞技场!$B$49:$B$70,0)) -> 1288 | P72: =O72+SUMPRODUCT((ROW(竞技场!$B$50:$B$70)-ROW(竞技场!$B$50)+1<=MATCH(L72,竞技场!$B$50:$B$70,0))*(((竞技场!$D$50:$D$70="竞技场代币")*竞技场!$E$50:$E$70)+((竞技场!$F$50:$F$70="竞技场代币")*竞技场!$G$50:$G$70))) -> 3688 | Q72: =M72*竞技场!$F$40+N72*竞技场!$F$44+SUMPRODUCT((竞技场!$B$100:$B$108<=M72)*(竞技场!$C$100:$C$108="炮台升级小材料")*竞技场!$D$100:$D$108)+$K$6+MOD(MAX(O72-$K$5-$K$8,0),$K$9)*$K$10 -> #DIV/0! | R72: =SUMPRODUCT((竞技场!$B$100:$B$108<=M72)*(竞技场!$C$100:$C$108="炮台升级大材料")*竞技场!$D$100:$D$108)+$K$7+INT(MAX(O72-$K$5-$K$8,0)/$K$9) -> #DIV/0! | S72: =M72*竞技场!$F$40+N72*竞技场!$F$44+SUMPRODUCT((竞技场!$B$100:$B$108<=M72)*(竞技场!$C$100:$C$108="炮台升级小材料")*竞技场!$D$100:$D$108)+(SUMPRODUCT((ROW(竞技场!$B$50:$B$70)-ROW(竞技场!$B$50)+1<=MATCH(L72,竞技场!$B$50:$B$70,0))*(((竞技场!$D$50:$D$70="炮台升级小材料")*竞技场!$E$50:$E$70)+((竞技场!$F$50:$F$70="炮台升级小材料")*竞技场!$G$50:$G$70))))+$K$6+MOD(MAX(P72-$K$5-$K$8,0),$K$9)*$K$10 -> #DIV/0! | T72: =SUMPRODUCT((竞技场!$B$100:$B$108<=M72)*(竞技场!$C$100:$C$108="炮台升级大材料")*竞技场!$D$100:$D$108)+(SUMPRODUCT((ROW(竞技场!$B$50:$B$70)-ROW(竞技场!$B$50)+1<=MATCH(L72,竞技场!$B$50:$B$70,0))*(((竞技场!$D$50:$D$70="炮台升级大材料")*竞技场!$E$50:$E$70)+((竞技场!$F$50:$F$70="炮台升级大材料")*竞技场!$G$50:$G$70))))+$K$7+INT(MAX(P72-$K$5-$K$8,0)/$K$9) -> #DIV/0! | U72: =LOOKUP(2,1/(($G$70:$G$187<=S72)*($H$70:$H$187<=T72)),$I$70:$I$187) -> #N/A | V72: =LOOKUP(2,1/(($G$70:$G$187<=S72+Q72)*($H$70:$H$187<=T72+R72)),$I$70:$I$187) -> #N/A | W72: =LOOKUP(2,1/(($G$70:$G$187<=S72+Q72*2)*($H$70:$H$187<=T72+R72*2)),$I$70:$I$187) -> #N/A | X72: =LOOKUP(2,1/(($G$70:$G$187<=S72+Q72*3)*($H$70:$H$187<=T72+R72*3)),$I$70:$I$187) -> #N/A | Y72: =IFERROR(MATCH("S50/A40/B30",U72:X72,0),">4") -> >4 | Z72: =IF(MAX(P72-$K$5-$K$8,0)>=750,"赛季限购买完后，还能补齐 1S+1A+1B",IF(MAX(P72-$K$5-$K$8,0)>=650,"赛季限购买完后，还能补 1S+1B",IF(MAX(P72-$K$5-$K$8,0)>=600,"赛季限购买完后，还能补 1S",IF(MAX(P72-$K$5-$K$8,0)>=150,"赛季限购买完后，还能补 1A+1B",IF(MAX(P72-$K$5-$K$8,0)>=100,"赛季限购买完后，还能补 1A",IF(MAX(P72-$K$5-$K$8,0)>=50,"赛季限购买完后，还能补 1B","赛季限购买完后，还不够补本体")))))) -> 赛季限购买完后，还能补齐 1S+1A+1B | AA72: 首达奖励已经送 1A+3B，本体压力主要转移到 S 炮台获取上。
A73: 3 | B73: 1-10档 | C73: S | D73: 4 | E73: =INDEX($B$17:$B$65,MATCH(D73,$A$17:$A$65,0)) -> 21 | F73: =IF(C73="S",INDEX($D$17:$D$65,MATCH(D73,$A$17:$A$65,0)),IF(C73="A",INDEX($E$17:$E$65,MATCH(D73,$A$17:$A$65,0)),INDEX($F$17:$F$65,MATCH(D73,$A$17:$A$65,0)))) -> 0 | G73: =G72+E73 -> 49 | H73: =H72+F73 -> 0 | I73: S4/A1/B1 | K73: =竞技场分层!A23 -> 大R | L73: =竞技场分层!L23 -> 大师Ⅱ | M73: =竞技场分层!I23 -> 85 | N73: =竞技场分层!J23 -> 55 | O73: =M73*竞技场!$C$40+N73*竞技场!$C$44+SUMPRODUCT((竞技场!$B$100:$B$108<=M73)*(竞技场!$C$100:$C$108="竞技场代币")*竞技场!$D$100:$D$108)+INDEX(竞技场!$K$49:$K$70,MATCH(L73,竞技场!$B$49:$B$70,0)) -> 1825 | P73: =O73+SUMPRODUCT((ROW(竞技场!$B$50:$B$70)-ROW(竞技场!$B$50)+1<=MATCH(L73,竞技场!$B$50:$B$70,0))*(((竞技场!$D$50:$D$70="竞技场代币")*竞技场!$E$50:$E$70)+((竞技场!$F$50:$F$70="竞技场代币")*竞技场!$G$50:$G$70))) -> 6025 | Q73: =M73*竞技场!$F$40+N73*竞技场!$F$44+SUMPRODUCT((竞技场!$B$100:$B$108<=M73)*(竞技场!$C$100:$C$108="炮台升级小材料")*竞技场!$D$100:$D$108)+$K$6+MOD(MAX(O73-$K$5-$K$8,0),$K$9)*$K$10 -> #DIV/0! | R73: =SUMPRODUCT((竞技场!$B$100:$B$108<=M73)*(竞技场!$C$100:$C$108="炮台升级大材料")*竞技场!$D$100:$D$108)+$K$7+INT(MAX(O73-$K$5-$K$8,0)/$K$9) -> #DIV/0! | S73: =M73*竞技场!$F$40+N73*竞技场!$F$44+SUMPRODUCT((竞技场!$B$100:$B$108<=M73)*(竞技场!$C$100:$C$108="炮台升级小材料")*竞技场!$D$100:$D$108)+(SUMPRODUCT((ROW(竞技场!$B$50:$B$70)-ROW(竞技场!$B$50)+1<=MATCH(L73,竞技场!$B$50:$B$70,0))*(((竞技场!$D$50:$D$70="炮台升级小材料")*竞技场!$E$50:$E$70)+((竞技场!$F$50:$F$70="炮台升级小材料")*竞技场!$G$50:$G$70))))+$K$6+MOD(MAX(P73-$K$5-$K$8,0),$K$9)*$K$10 -> #DIV/0! | T73: =SUMPRODUCT((竞技场!$B$100:$B$108<=M73)*(竞技场!$C$100:$C$108="炮台升级大材料")*竞技场!$D$100:$D$108)+(SUMPRODUCT((ROW(竞技场!$B$50:$B$70)-ROW(竞技场!$B$50)+1<=MATCH(L73,竞技场!$B$50:$B$70,0))*(((竞技场!$D$50:$D$70="炮台升级大材料")*竞技场!$E$50:$E$70)+((竞技场!$F$50:$F$70="炮台升级大材料")*竞技场!$G$50:$G$70))))+$K$7+INT(MAX(P73-$K$5-$K$8,0)/$K$9) -> #DIV/0! | U73: =LOOKUP(2,1/(($G$70:$G$187<=S73)*($H$70:$H$187<=T73)),$I$70:$I$187) -> #N/A | V73: =LOOKUP(2,1/(($G$70:$G$187<=S73+Q73)*($H$70:$H$187<=T73+R73)),$I$70:$I$187) -> #N/A | W73: =LOOKUP(2,1/(($G$70:$G$187<=S73+Q73*2)*($H$70:$H$187<=T73+R73*2)),$I$70:$I$187) -> #N/A | X73: =LOOKUP(2,1/(($G$70:$G$187<=S73+Q73*3)*($H$70:$H$187<=T73+R73*3)),$I$70:$I$187) -> #N/A | Y73: =IFERROR(MATCH("S50/A40/B30",U73:X73,0),">4") -> >4 | Z73: =IF(MAX(P73-$K$5-$K$8,0)>=750,"赛季限购买完后，还能补齐 1S+1A+1B",IF(MAX(P73-$K$5-$K$8,0)>=650,"赛季限购买完后，还能补 1S+1B",IF(MAX(P73-$K$5-$K$8,0)>=600,"赛季限购买完后，还能补 1S",IF(MAX(P73-$K$5-$K$8,0)>=150,"赛季限购买完后，还能补 1A+1B",IF(MAX(P73-$K$5-$K$8,0)>=100,"赛季限购买完后，还能补 1A",IF(MAX(P73-$K$5-$K$8,0)>=50,"赛季限购买完后，还能补 1B","赛季限购买完后，还不够补本体")))))) -> 赛季限购买完后，还能补齐 1S+1A+1B | AA73: 首达奖励已经送 1S+3A+3B，首赛季资源已经明显超过基础阵容需求。
A74: 4 | B74: 1-10档 | C74: S | D74: 5 | E74: =INDEX($B$17:$B$65,MATCH(D74,$A$17:$A$65,0)) -> 26 | F74: =IF(C74="S",INDEX($D$17:$D$65,MATCH(D74,$A$17:$A$65,0)),IF(C74="A",INDEX($E$17:$E$65,MATCH(D74,$A$17:$A$65,0)),INDEX($F$17:$F$65,MATCH(D74,$A$17:$A$65,0)))) -> 0 | G74: =G73+E74 -> 75 | H74: =H73+F74 -> 0 | I74: S5/A1/B1
A75: 5 | B75: 1-10档 | C75: S | D75: 6 | E75: =INDEX($B$17:$B$65,MATCH(D75,$A$17:$A$65,0)) -> 32 | F75: =IF(C75="S",INDEX($D$17:$D$65,MATCH(D75,$A$17:$A$65,0)),IF(C75="A",INDEX($E$17:$E$65,MATCH(D75,$A$17:$A$65,0)),INDEX($F$17:$F$65,MATCH(D75,$A$17:$A$65,0)))) -> 0 | G75: =G74+E75 -> 107 | H75: =H74+F75 -> 0 | I75: S6/A1/B1
A76: 6 | B76: 1-10档 | C76: S | D76: 7 | E76: =INDEX($B$17:$B$65,MATCH(D76,$A$17:$A$65,0)) -> 38 | F76: =IF(C76="S",INDEX($D$17:$D$65,MATCH(D76,$A$17:$A$65,0)),IF(C76="A",INDEX($E$17:$E$65,MATCH(D76,$A$17:$A$65,0)),INDEX($F$17:$F$65,MATCH(D76,$A$17:$A$65,0)))) -> 0 | G76: =G75+E76 -> 145 | H76: =H75+F76 -> 0 | I76: S7/A1/B1
A77: 7 | B77: 1-10档 | C77: S | D77: 8 | E77: =INDEX($B$17:$B$65,MATCH(D77,$A$17:$A$65,0)) -> 44 | F77: =IF(C77="S",INDEX($D$17:$D$65,MATCH(D77,$A$17:$A$65,0)),IF(C77="A",INDEX($E$17:$E$65,MATCH(D77,$A$17:$A$65,0)),INDEX($F$17:$F$65,MATCH(D77,$A$17:$A$65,0)))) -> 0 | G77: =G76+E77 -> 189 | H77: =H76+F77 -> 0 | I77: S8/A1/B1
A78: 8 | B78: 1-10档 | C78: S | D78: 9 | E78: =INDEX($B$17:$B$65,MATCH(D78,$A$17:$A$65,0)) -> 50 | F78: =IF(C78="S",INDEX($D$17:$D$65,MATCH(D78,$A$17:$A$65,0)),IF(C78="A",INDEX($E$17:$E$65,MATCH(D78,$A$17:$A$65,0)),INDEX($F$17:$F$65,MATCH(D78,$A$17:$A$65,0)))) -> 0 | G78: =G77+E78 -> 239 | H78: =H77+F78 -> 0 | I78: S9/A1/B1
A79: 9 | B79: 1-10档 | C79: S | D79: 10 | E79: =INDEX($B$17:$B$65,MATCH(D79,$A$17:$A$65,0)) -> 57 | F79: =IF(C79="S",INDEX($D$17:$D$65,MATCH(D79,$A$17:$A$65,0)),IF(C79="A",INDEX($E$17:$E$65,MATCH(D79,$A$17:$A$65,0)),INDEX($F$17:$F$65,MATCH(D79,$A$17:$A$65,0)))) -> 0 | G79: =G78+E79 -> 296 | H79: =H78+F79 -> 0 | I79: S10/A1/B1
A80: 10 | B80: 1-10档 | C80: A | D80: 2 | E80: =INDEX($B$17:$B$65,MATCH(D80,$A$17:$A$65,0)) -> 12 | F80: =IF(C80="S",INDEX($D$17:$D$65,MATCH(D80,$A$17:$A$65,0)),IF(C80="A",INDEX($E$17:$E$65,MATCH(D80,$A$17:$A$65,0)),INDEX($F$17:$F$65,MATCH(D80,$A$17:$A$65,0)))) -> 0 | G80: =G79+E80 -> 308 | H80: =H79+F80 -> 0 | I80: S10/A2/B1
A81: 11 | B81: 1-10档 | C81: A | D81: 3 | E81: =INDEX($B$17:$B$65,MATCH(D81,$A$17:$A$65,0)) -> 16 | F81: =IF(C81="S",INDEX($D$17:$D$65,MATCH(D81,$A$17:$A$65,0)),IF(C81="A",INDEX($E$17:$E$65,MATCH(D81,$A$17:$A$65,0)),INDEX($F$17:$F$65,MATCH(D81,$A$17:$A$65,0)))) -> 0 | G81: =G80+E81 -> 324 | H81: =H80+F81 -> 0 | I81: S10/A3/B1
A82: 12 | B82: 1-10档 | C82: A | D82: 4 | E82: =INDEX($B$17:$B$65,MATCH(D82,$A$17:$A$65,0)) -> 21 | F82: =IF(C82="S",INDEX($D$17:$D$65,MATCH(D82,$A$17:$A$65,0)),IF(C82="A",INDEX($E$17:$E$65,MATCH(D82,$A$17:$A$65,0)),INDEX($F$17:$F$65,MATCH(D82,$A$17:$A$65,0)))) -> 0 | G82: =G81+E82 -> 345 | H82: =H81+F82 -> 0 | I82: S10/A4/B1
A83: 13 | B83: 1-10档 | C83: A | D83: 5 | E83: =INDEX($B$17:$B$65,MATCH(D83,$A$17:$A$65,0)) -> 26 | F83: =IF(C83="S",INDEX($D$17:$D$65,MATCH(D83,$A$17:$A$65,0)),IF(C83="A",INDEX($E$17:$E$65,MATCH(D83,$A$17:$A$65,0)),INDEX($F$17:$F$65,MATCH(D83,$A$17:$A$65,0)))) -> 0 | G83: =G82+E83 -> 371 | H83: =H82+F83 -> 0 | I83: S10/A5/B1
A84: 14 | B84: 1-10档 | C84: A | D84: 6 | E84: =INDEX($B$17:$B$65,MATCH(D84,$A$17:$A$65,0)) -> 32 | F84: =IF(C84="S",INDEX($D$17:$D$65,MATCH(D84,$A$17:$A$65,0)),IF(C84="A",INDEX($E$17:$E$65,MATCH(D84,$A$17:$A$65,0)),INDEX($F$17:$F$65,MATCH(D84,$A$17:$A$65,0)))) -> 0 | G84: =G83+E84 -> 403 | H84: =H83+F84 -> 0 | I84: S10/A6/B1
A85: 15 | B85: 1-10档 | C85: A | D85: 7 | E85: =INDEX($B$17:$B$65,MATCH(D85,$A$17:$A$65,0)) -> 38 | F85: =IF(C85="S",INDEX($D$17:$D$65,MATCH(D85,$A$17:$A$65,0)),IF(C85="A",INDEX($E$17:$E$65,MATCH(D85,$A$17:$A$65,0)),INDEX($F$17:$F$65,MATCH(D85,$A$17:$A$65,0)))) -> 0 | G85: =G84+E85 -> 441 | H85: =H84+F85 -> 0 | I85: S10/A7/B1
... A187: 117 | B187: 41-50档 | C187: S | D187: 50 | E187: =INDEX($B$17:$B$65,MATCH(D187,$A$17:$A$65,0)) -> 382 | F187: =IF(C187="S",INDEX($D$17:$D$65,MATCH(D187,$A$17:$A$65,0)),IF(C187="A",INDEX($E$17:$E$65,MATCH(D187,$A$17:$A$65,0)),INDEX($F$17:$F$65,MATCH(D187,$A$17:$A$65,0)))) -> 0 | G187: =G186+E187 -> 17342 | H187: =H186+F187 -> 6 | I187: S50/A40/B30
A190: 七、结论提示
A191: 1. 这版按品质区分等级上限：S50 / A40 / B30，且只在指定的跨级点使用大材料。
A192: 2. 小材料改成了逐级递增曲线，前半段故意做得更轻，以强化前期成长反馈。
A193: 3. 按当前竞技场产出，1S+1A+1B 的混编毕业线大致变成：免费 2 赛季，小R 2 赛季，中R 2 赛季，大R 首赛季。
A194: 4. 如果你希望长期层差更强，建议把 1S+1A+1B 作为基础毕业线，再把 3S 当成真正的长期终局。

Sheet 通行证
B2: 通行证数值概述 | H2: 普通版定价 | I2: 68 | J2: rmb | Q2: 开启周数 | R2: 开启天数
B3: 活跃向、高性价比付费 | H3: 高级版定价 | I3: 98 | J3: rmb | Q3: 6 | R3: =Q3*7 -> 42
B4: 瞄准的玩家为核心中小R | H4: 等级上限 | I4: 60
B5: 数值设计上综合性价比应最高 | Q5: 升级所需积分 | R5: 每周积分上限
B6: 核心性价比仅次于月卡 | H6: 综合性价比 | I6: =H14/I2/10 -> 26.411765 | Q6: 1000 | R6: 15000
H7: 核心性价比 | I7: =I14/I2/10 -> 4.1176471
H8: 高级额外奖励性价比 | I8: =S24/(I3-I2)/10 -> 9.1666667 | Q8: 理论最高等级
Q9: =(R6*Q3+T56)/Q6 -> 111
Q12: 普通通行证一次性奖励 | R12: 680钻石
H13: 总价值 | I13: 核心奖励价值
H14: =SUM(L17:L76) -> 17960 | I14: =SUM(N17:N76) -> 2800
C15: 免费 | F15: 付费 | Q15: 高级通行证一次性奖励
B16: 等级 | C16: 奖励 | D16: 奖励数量 | E16: 奖励价值 | F16: 奖励 | G16: 奖励数量 | H16: 奖励价值 | I16: 奖励2 | J16: 奖励数量2 | K16: 奖励价值2 | L16: 总价值 | M16: 付费倍率 | N16: 核心奖励价值 | Q16: 奖励 | R16: 奖励数量 | S16: 奖励价值
B17: {=_xlfn.SEQUENCE(I4,1,1,1)} -> 1 | C17: 金币 | D17: 10000 | E17: =VLOOKUP(C17,道具定价!$C:$F,4,0)*D17 -> 10 | F17: 钻石 | G17: 680 | H17: =VLOOKUP(F17,道具定价!$C:$F,4,0)*G17 -> 680 | K17: =_xlfn.IFNA(VLOOKUP(I17,道具定价!$C:$F,4,0)*J17,0) -> 0 | L17: =H17+K17 -> 680 | M17: =L17/E17 -> 68 | N17: 0 | Q17: 钻石 | R17: 450 | S17: 300
B18: 2 | C18: 角色经验中2000 | D18: 5 | E18: =VLOOKUP(C18,道具定价!$C:$F,4,0)*D18 -> 10 | F18: 角色经验高10000 | G18: 4 | H18: =VLOOKUP(F18,道具定价!$C:$F,4,0)*G18 -> 40 | K18: =_xlfn.IFNA(VLOOKUP(I18,道具定价!$C:$F,4,0)*J18,0) -> 0 | L18: =H18+K18 -> 40 | M18: =L18/E18 -> 4 | N18: 0 | Q18: 角色抽卡券普通 | R18: 5 | S18: =VLOOKUP(Q18,道具定价!$C:$F,4,0)*R18 -> 750
B19: 3 | C19: 专武经验中4000 | D19: 5 | E19: =VLOOKUP(C19,道具定价!$C:$F,4,0)*D19 -> 10 | F19: 专武经验高20000 | G19: 4 | H19: =VLOOKUP(F19,道具定价!$C:$F,4,0)*G19 -> 40 | K19: =_xlfn.IFNA(VLOOKUP(I19,道具定价!$C:$F,4,0)*J19,0) -> 0 | L19: =H19+K19 -> 40 | M19: =L19/E19 -> 4 | N19: 0 | Q19: 头像框 | R19: 1 | S19: =VLOOKUP(Q19,道具定价!$C:$F,4,0)*R19 -> 0
B20: 4 | C20: 主角装备经验 | D20: 1000 | E20: =VLOOKUP(C20,道具定价!$C:$F,4,0)*D20 -> 10 | F20: 主角装备经验 | G20: 4000 | H20: =VLOOKUP(F20,道具定价!$C:$F,4,0)*G20 -> 40 | K20: =_xlfn.IFNA(VLOOKUP(I20,道具定价!$C:$F,4,0)*J20,0) -> 0 | L20: =H20+K20 -> 40 | M20: =L20/E20 -> 4 | N20: 0 | Q20: 额外星盘点 | R20: 1 | S20: =VLOOKUP(Q20,道具定价!$C:$F,4,0)*R20 -> 500
B21: 5 | C21: 体力药 | D21: 1 | E21: =VLOOKUP(C21,道具定价!$C:$F,4,0)*D21 -> 240 | F21: 体力药 | G21: 2 | H21: =VLOOKUP(F21,道具定价!$C:$F,4,0)*G21 -> 480 | I21: 额外星盘点 | J21: 1 | K21: =_xlfn.IFNA(VLOOKUP(I21,道具定价!$C:$F,4,0)*J21,0) -> 500 | L21: =H21+K21 -> 980 | M21: =L21/E21 -> 4.0833333 | N21: 0 | Q21: 体力药 | R21: 5 | S21: =VLOOKUP(Q21,道具定价!$C:$F,4,0)*R21 -> 1200
B22: 6 | C22: 金币 | D22: 10000 | E22: =VLOOKUP(C22,道具定价!$C:$F,4,0)*D22 -> 10 | F22: 金币 | G22: 40000 | H22: =VLOOKUP(F22,道具定价!$C:$F,4,0)*G22 -> 40 | K22: =_xlfn.IFNA(VLOOKUP(I22,道具定价!$C:$F,4,0)*J22,0) -> 0 | L22: =H22+K22 -> 40 | M22: =L22/E22 -> 4 | N22: 0
B23: 7 | C23: 角色经验中2000 | D23: 5 | E23: =VLOOKUP(C23,道具定价!$C:$F,4,0)*D23 -> 10 | F23: 角色经验高10000 | G23: 4 | H23: =VLOOKUP(F23,道具定价!$C:$F,4,0)*G23 -> 40 | K23: =_xlfn.IFNA(VLOOKUP(I23,道具定价!$C:$F,4,0)*J23,0) -> 0 | L23: =H23+K23 -> 40 | M23: =L23/E23 -> 4 | N23: 0
B24: 8 | C24: 专武经验中4000 | D24: 5 | E24: =VLOOKUP(C24,道具定价!$C:$F,4,0)*D24 -> 10 | F24: 专武经验高20000 | G24: 4 | H24: =VLOOKUP(F24,道具定价!$C:$F,4,0)*G24 -> 40 | K24: =_xlfn.IFNA(VLOOKUP(I24,道具定价!$C:$F,4,0)*J24,0) -> 0 | L24: =H24+K24 -> 40 | M24: =L24/E24 -> 4 | N24: 0 | S24: =SUM(S17:S23) -> 2750
B25: 9 | C25: 主角装备经验 | D25: 1000 | E25: =VLOOKUP(C25,道具定价!$C:$F,4,0)*D25 -> 10 | F25: 主角装备经验 | G25: 4000 | H25: =VLOOKUP(F25,道具定价!$C:$F,4,0)*G25 -> 40 | K25: =_xlfn.IFNA(VLOOKUP(I25,道具定价!$C:$F,4,0)*J25,0) -> 0 | L25: =H25+K25 -> 40 | M25: =L25/E25 -> 4 | N25: 0
B26: 10 | C26: 钻石 | D26: 50 | E26: =VLOOKUP(C26,道具定价!$C:$F,4,0)*D26 -> 50 | F26: 角色抽卡券普通 | G26: 2 | H26: =VLOOKUP(F26,道具定价!$C:$F,4,0)*G26 -> 300 | I26: 专武抽卡券普通 | J26: 2 | K26: =_xlfn.IFNA(VLOOKUP(I26,道具定价!$C:$F,4,0)*J26,0) -> 300 | L26: =H26+K26 -> 600 | M26: =L26/E26 -> 12 | N26: =H26 -> 300 | Q26: 每日任务积分 | R26: 800
B27: 11 | C27: 金币 | D27: 10000 | E27: =VLOOKUP(C27,道具定价!$C:$F,4,0)*D27 -> 10 | F27: 金币 | G27: 40000 | H27: =VLOOKUP(F27,道具定价!$C:$F,4,0)*G27 -> 40 | K27: =_xlfn.IFNA(VLOOKUP(I27,道具定价!$C:$F,4,0)*J27,0) -> 0 | L27: =H27+K27 -> 40 | M27: =L27/E27 -> 4 | N27: 0
B28: 12 | C28: 角色经验中2000 | D28: 5 | E28: =VLOOKUP(C28,道具定价!$C:$F,4,0)*D28 -> 10 | F28: 角色经验高10000 | G28: 4 | H28: =VLOOKUP(F28,道具定价!$C:$F,4,0)*G28 -> 40 | K28: =_xlfn.IFNA(VLOOKUP(I28,道具定价!$C:$F,4,0)*J28,0) -> 0 | L28: =H28+K28 -> 40 | M28: =L28/E28 -> 4 | N28: 0 | Q28: 任务分类 | R28: 任务类型 | S28: 任务类型数值 | T28: 任务积分奖励
B29: 13 | C29: 专武经验中4000 | D29: 5 | E29: =VLOOKUP(C29,道具定价!$C:$F,4,0)*D29 -> 10 | F29: 专武经验高20000 | G29: 4 | H29: =VLOOKUP(F29,道具定价!$C:$F,4,0)*G29 -> 40 | K29: =_xlfn.IFNA(VLOOKUP(I29,道具定价!$C:$F,4,0)*J29,0) -> 0 | L29: =H29+K29 -> 40 | M29: =L29/E29 -> 4 | N29: 0 | Q29: 周常 | T29: 1500
B30: 14 | C30: 主角装备经验 | D30: 1000 | E30: =VLOOKUP(C30,道具定价!$C:$F,4,0)*D30 -> 10 | F30: 主角装备经验 | G30: 4000 | H30: =VLOOKUP(F30,道具定价!$C:$F,4,0)*G30 -> 40 | K30: =_xlfn.IFNA(VLOOKUP(I30,道具定价!$C:$F,4,0)*J30,0) -> 0 | L30: =H30+K30 -> 40 | M30: =L30/E30 -> 4 | N30: 0 | Q30: 周常 | T30: 1500
B31: 15 | C31: 史诗装备兑换材料 | D31: 5 | E31: =VLOOKUP(C31,道具定价!$C:$F,4,0)*D31 -> 10 | F31: 体力药 | G31: 2 | H31: =VLOOKUP(F31,道具定价!$C:$F,4,0)*G31 -> 480 | I31: 史诗装备兑换材料 | J31: 30 | K31: =_xlfn.IFNA(VLOOKUP(I31,道具定价!$C:$F,4,0)*J31,0) -> 60 | L31: =H31+K31 -> 540 | M31: =L31/E31 -> 54 | N31: 0 | Q31: 周常 | T31: 1500
B32: 16 | C32: 金币 | D32: 10000 | E32: =VLOOKUP(C32,道具定价!$C:$F,4,0)*D32 -> 10 | F32: 金币 | G32: 40000 | H32: =VLOOKUP(F32,道具定价!$C:$F,4,0)*G32 -> 40 | K32: =_xlfn.IFNA(VLOOKUP(I32,道具定价!$C:$F,4,0)*J32,0) -> 0 | L32: =H32+K32 -> 40 | M32: =L32/E32 -> 4 | N32: 0 | Q32: 周常 | T32: 1500
B33: 17 | C33: 角色经验中2000 | D33: 5 | E33: =VLOOKUP(C33,道具定价!$C:$F,4,0)*D33 -> 10 | F33: 角色经验高10000 | G33: 4 | H33: =VLOOKUP(F33,道具定价!$C:$F,4,0)*G33 -> 40 | K33: =_xlfn.IFNA(VLOOKUP(I33,道具定价!$C:$F,4,0)*J33,0) -> 0 | L33: =H33+K33 -> 40 | M33: =L33/E33 -> 4 | N33: 0 | Q33: 周常 | T33: 1500
B34: 18 | C34: 专武经验中4000 | D34: 5 | E34: =VLOOKUP(C34,道具定价!$C:$F,4,0)*D34 -> 10 | F34: 专武经验高20000 | G34: 4 | H34: =VLOOKUP(F34,道具定价!$C:$F,4,0)*G34 -> 40 | K34: =_xlfn.IFNA(VLOOKUP(I34,道具定价!$C:$F,4,0)*J34,0) -> 0 | L34: =H34+K34 -> 40 | M34: =L34/E34 -> 4 | N34: 0 | Q34: 周常 | T34: 1500
B35: 19 | C35: 主角装备经验 | D35: 1000 | E35: =VLOOKUP(C35,道具定价!$C:$F,4,0)*D35 -> 10 | F35: 主角装备经验 | G35: 4000 | H35: =VLOOKUP(F35,道具定价!$C:$F,4,0)*G35 -> 40 | K35: =_xlfn.IFNA(VLOOKUP(I35,道具定价!$C:$F,4,0)*J35,0) -> 0 | L35: =H35+K35 -> 40 | M35: =L35/E35 -> 4 | N35: 0 | Q35: 周常 | T35: 1500
B36: 20 | C36: 钻石 | D36: 50 | E36: =VLOOKUP(C36,道具定价!$C:$F,4,0)*D36 -> 50 | F36: 角色抽卡券普通 | G36: 2 | H36: =VLOOKUP(F36,道具定价!$C:$F,4,0)*G36 -> 300 | I36: 专武抽卡券普通 | J36: 2 | K36: =_xlfn.IFNA(VLOOKUP(I36,道具定价!$C:$F,4,0)*J36,0) -> 300 | L36: =H36+K36 -> 600 | M36: =L36/E36 -> 12 | N36: =H36 -> 300 | Q36: 周常 | T36: 1500
B37: 21 | C37: 金币 | D37: 20000 | E37: =VLOOKUP(C37,道具定价!$C:$F,4,0)*D37 -> 20 | F37: 金币 | G37: 80000 | H37: =VLOOKUP(F37,道具定价!$C:$F,4,0)*G37 -> 80 | K37: =_xlfn.IFNA(VLOOKUP(I37,道具定价!$C:$F,4,0)*J37,0) -> 0 | L37: =H37+K37 -> 80 | M37: =L37/E37 -> 4 | N37: 0 | Q37: 周常 | T37: 1500
B38: 22 | C38: 角色经验中2000 | D38: 10 | E38: =VLOOKUP(C38,道具定价!$C:$F,4,0)*D38 -> 20 | F38: 角色经验高10000 | G38: 8 | H38: =VLOOKUP(F38,道具定价!$C:$F,4,0)*G38 -> 80 | K38: =_xlfn.IFNA(VLOOKUP(I38,道具定价!$C:$F,4,0)*J38,0) -> 0 | L38: =H38+K38 -> 80 | M38: =L38/E38 -> 4 | N38: 0 | Q38: 周常 | T38: 1500
B39: 23 | C39: 专武经验中4000 | D39: 10 | E39: =VLOOKUP(C39,道具定价!$C:$F,4,0)*D39 -> 20 | F39: 专武经验高20000 | G39: 8 | H39: =VLOOKUP(F39,道具定价!$C:$F,4,0)*G39 -> 80 | K39: =_xlfn.IFNA(VLOOKUP(I39,道具定价!$C:$F,4,0)*J39,0) -> 0 | L39: =H39+K39 -> 80 | M39: =L39/E39 -> 4 | N39: 0 | T39: =SUM(T29:T38) -> 15000
B40: 24 | C40: 主角装备经验 | D40: 2000 | E40: =VLOOKUP(C40,道具定价!$C:$F,4,0)*D40 -> 20 | F40: 主角装备经验 | G40: 8000 | H40: =VLOOKUP(F40,道具定价!$C:$F,4,0)*G40 -> 80 | K40: =_xlfn.IFNA(VLOOKUP(I40,道具定价!$C:$F,4,0)*J40,0) -> 0 | L40: =H40+K40 -> 80 | M40: =L40/E40 -> 4 | N40: 0
B41: 25 | C41: 体力药 | D41: 1 | E41: =VLOOKUP(C41,道具定价!$C:$F,4,0)*D41 -> 240 | F41: 体力药 | G41: 3 | H41: =VLOOKUP(F41,道具定价!$C:$F,4,0)*G41 -> 720 | I41: 额外星盘点 | J41: 1 | K41: =_xlfn.IFNA(VLOOKUP(I41,道具定价!$C:$F,4,0)*J41,0) -> 500 | L41: =H41+K41 -> 1220 | M41: =L41/E41 -> 5.0833333 | N41: 0
B42: 26 | C42: 金币 | D42: 20000 | E42: =VLOOKUP(C42,道具定价!$C:$F,4,0)*D42 -> 20 | F42: 金币 | G42: 80000 | H42: =VLOOKUP(F42,道具定价!$C:$F,4,0)*G42 -> 80 | K42: =_xlfn.IFNA(VLOOKUP(I42,道具定价!$C:$F,4,0)*J42,0) -> 0 | L42: =H42+K42 -> 80 | M42: =L42/E42 -> 4 | N42: 0
B43: 27 | C43: 角色经验中2000 | D43: 10 | E43: =VLOOKUP(C43,道具定价!$C:$F,4,0)*D43 -> 20 | F43: 角色经验高10000 | G43: 8 | H43: =VLOOKUP(F43,道具定价!$C:$F,4,0)*G43 -> 80 | K43: =_xlfn.IFNA(VLOOKUP(I43,道具定价!$C:$F,4,0)*J43,0) -> 0 | L43: =H43+K43 -> 80 | M43: =L43/E43 -> 4 | N43: 0
B44: 28 | C44: 专武经验中4000 | D44: 10 | E44: =VLOOKUP(C44,道具定价!$C:$F,4,0)*D44 -> 20 | F44: 专武经验高20000 | G44: 8 | H44: =VLOOKUP(F44,道具定价!$C:$F,4,0)*G44 -> 80 | K44: =_xlfn.IFNA(VLOOKUP(I44,道具定价!$C:$F,4,0)*J44,0) -> 0 | L44: =H44+K44 -> 80 | M44: =L44/E44 -> 4 | N44: 0
B45: 29 | C45: 主角装备经验 | D45: 2000 | E45: =VLOOKUP(C45,道具定价!$C:$F,4,0)*D45 -> 20 | F45: 主角装备经验 | G45: 8000 | H45: =VLOOKUP(F45,道具定价!$C:$F,4,0)*G45 -> 80 | K45: =_xlfn.IFNA(VLOOKUP(I45,道具定价!$C:$F,4,0)*J45,0) -> 0 | L45: =H45+K45 -> 80 | M45: =L45/E45 -> 4 | N45: 0
B46: 30 | C46: 钻石 | D46: 50 | E46: =VLOOKUP(C46,道具定价!$C:$F,4,0)*D46 -> 50 | F46: 角色抽卡券普通 | G46: 2 | H46: =VLOOKUP(F46,道具定价!$C:$F,4,0)*G46 -> 300 | I46: 专武抽卡券普通 | J46: 2 | K46: =_xlfn.IFNA(VLOOKUP(I46,道具定价!$C:$F,4,0)*J46,0) -> 300 | L46: =H46+K46 -> 600 | M46: =L46/E46 -> 12 | N46: =H46 -> 300
B47: 31 | C47: 金币 | D47: 20000 | E47: =VLOOKUP(C47,道具定价!$C:$F,4,0)*D47 -> 20 | F47: 金币 | G47: 80000 | H47: =VLOOKUP(F47,道具定价!$C:$F,4,0)*G47 -> 80 | K47: =_xlfn.IFNA(VLOOKUP(I47,道具定价!$C:$F,4,0)*J47,0) -> 0 | L47: =H47+K47 -> 80 | M47: =L47/E47 -> 4 | N47: 0
B48: 32 | C48: 角色经验中2000 | D48: 10 | E48: =VLOOKUP(C48,道具定价!$C:$F,4,0)*D48 -> 20 | F48: 角色经验高10000 | G48: 8 | H48: =VLOOKUP(F48,道具定价!$C:$F,4,0)*G48 -> 80 | K48: =_xlfn.IFNA(VLOOKUP(I48,道具定价!$C:$F,4,0)*J48,0) -> 0 | L48: =H48+K48 -> 80 | M48: =L48/E48 -> 4 | N48: 0 | Q48: 任务分类 | R48: 任务类型 | S48: 任务类型数值 | T48: 任务积分奖励
B49: 33 | C49: 专武经验中4000 | D49: 10 | E49: =VLOOKUP(C49,道具定价!$C:$F,4,0)*D49 -> 20 | F49: 专武经验高20000 | G49: 8 | H49: =VLOOKUP(F49,道具定价!$C:$F,4,0)*G49 -> 80 | K49: =_xlfn.IFNA(VLOOKUP(I49,道具定价!$C:$F,4,0)*J49,0) -> 0 | L49: =H49+K49 -> 80 | M49: =L49/E49 -> 4 | N49: 0 | Q49: 当期 | T49: 3000
B50: 34 | C50: 主角装备经验 | D50: 2000 | E50: =VLOOKUP(C50,道具定价!$C:$F,4,0)*D50 -> 20 | F50: 主角装备经验 | G50: 8000 | H50: =VLOOKUP(F50,道具定价!$C:$F,4,0)*G50 -> 80 | K50: =_xlfn.IFNA(VLOOKUP(I50,道具定价!$C:$F,4,0)*J50,0) -> 0 | L50: =H50+K50 -> 80 | M50: =L50/E50 -> 4 | N50: 0 | Q50: 当期 | T50: 3000
B51: 35 | C51: 史诗装备兑换材料 | D51: 10 | E51: =VLOOKUP(C51,道具定价!$C:$F,4,0)*D51 -> 20 | F51: 体力药 | G51: 3 | H51: =VLOOKUP(F51,道具定价!$C:$F,4,0)*G51 -> 720 | I51: 史诗装备兑换材料 | J51: 50 | K51: =_xlfn.IFNA(VLOOKUP(I51,道具定价!$C:$F,4,0)*J51,0) -> 100 | L51: =H51+K51 -> 820 | M51: =L51/E51 -> 41 | N51: 0 | Q51: 当期 | T51: 3000
B52: 36 | C52: 金币 | D52: 20000 | E52: =VLOOKUP(C52,道具定价!$C:$F,4,0)*D52 -> 20 | F52: 金币 | G52: 80000 | H52: =VLOOKUP(F52,道具定价!$C:$F,4,0)*G52 -> 80 | K52: =_xlfn.IFNA(VLOOKUP(I52,道具定价!$C:$F,4,0)*J52,0) -> 0 | L52: =H52+K52 -> 80 | M52: =L52/E52 -> 4 | N52: 0 | Q52: 当期 | T52: 3000
B53: 37 | C53: 角色经验中2000 | D53: 10 | E53: =VLOOKUP(C53,道具定价!$C:$F,4,0)*D53 -> 20 | F53: 角色经验高10000 | G53: 8 | H53: =VLOOKUP(F53,道具定价!$C:$F,4,0)*G53 -> 80 | K53: =_xlfn.IFNA(VLOOKUP(I53,道具定价!$C:$F,4,0)*J53,0) -> 0 | L53: =H53+K53 -> 80 | M53: =L53/E53 -> 4 | N53: 0 | Q53: 当期 | T53: 3000
B54: 38 | C54: 专武经验中4000 | D54: 10 | E54: =VLOOKUP(C54,道具定价!$C:$F,4,0)*D54 -> 20 | F54: 专武经验高20000 | G54: 8 | H54: =VLOOKUP(F54,道具定价!$C:$F,4,0)*G54 -> 80 | K54: =_xlfn.IFNA(VLOOKUP(I54,道具定价!$C:$F,4,0)*J54,0) -> 0 | L54: =H54+K54 -> 80 | M54: =L54/E54 -> 4 | N54: 0 | Q54: 当期 | T54: 3000
B55: 39 | C55: 主角装备经验 | D55: 2000 | E55: =VLOOKUP(C55,道具定价!$C:$F,4,0)*D55 -> 20 | F55: 主角装备经验 | G55: 8000 | H55: =VLOOKUP(F55,道具定价!$C:$F,4,0)*G55 -> 80 | K55: =_xlfn.IFNA(VLOOKUP(I55,道具定价!$C:$F,4,0)*J55,0) -> 0 | L55: =H55+K55 -> 80 | M55: =L55/E55 -> 4 | N55: 0 | Q55: 当期 | T55: 3000
B56: 40 | C56: 钻石 | D56: 100 | E56: =VLOOKUP(C56,道具定价!$C:$F,4,0)*D56 -> 100 | F56: 角色抽卡券普通 | G56: 2 | H56: =VLOOKUP(F56,道具定价!$C:$F,4,0)*G56 -> 300 | I56: 专武抽卡券普通 | J56: 2 | K56: =_xlfn.IFNA(VLOOKUP(I56,道具定价!$C:$F,4,0)*J56,0) -> 300 | L56: =H56+K56 -> 600 | M56: =L56/E56 -> 6 | N56: =H56 -> 300 | T56: =SUM(T49:T55) -> 21000
B57: 41 | C57: 金币 | D57: 30000 | E57: =VLOOKUP(C57,道具定价!$C:$F,4,0)*D57 -> 30 | F57: 金币 | G57: 120000 | H57: =VLOOKUP(F57,道具定价!$C:$F,4,0)*G57 -> 120 | K57: =_xlfn.IFNA(VLOOKUP(I57,道具定价!$C:$F,4,0)*J57,0) -> 0 | L57: =H57+K57 -> 120 | M57: =L57/E57 -> 4 | N57: 0
B58: 42 | C58: 角色经验高10000 | D58: 3 | E58: =VLOOKUP(C58,道具定价!$C:$F,4,0)*D58 -> 30 | F58: 角色经验高10000 | G58: 12 | H58: =VLOOKUP(F58,道具定价!$C:$F,4,0)*G58 -> 120 | K58: =_xlfn.IFNA(VLOOKUP(I58,道具定价!$C:$F,4,0)*J58,0) -> 0 | L58: =H58+K58 -> 120 | M58: =L58/E58 -> 4 | N58: 0
B59: 43 | C59: 专武经验高20000 | D59: 3 | E59: =VLOOKUP(C59,道具定价!$C:$F,4,0)*D59 -> 30 | F59: 专武经验高20000 | G59: 12 | H59: =VLOOKUP(F59,道具定价!$C:$F,4,0)*G59 -> 120 | K59: =_xlfn.IFNA(VLOOKUP(I59,道具定价!$C:$F,4,0)*J59,0) -> 0 | L59: =H59+K59 -> 120 | M59: =L59/E59 -> 4 | N59: 0
B60: 44 | C60: 主角装备经验 | D60: 3000 | E60: =VLOOKUP(C60,道具定价!$C:$F,4,0)*D60 -> 30 | F60: 主角装备经验 | G60: 12000 | H60: =VLOOKUP(F60,道具定价!$C:$F,4,0)*G60 -> 120 | K60: =_xlfn.IFNA(VLOOKUP(I60,道具定价!$C:$F,4,0)*J60,0) -> 0 | L60: =H60+K60 -> 120 | M60: =L60/E60 -> 4 | N60: 0
B61: 45 | C61: 体力药 | D61: 1 | E61: =VLOOKUP(C61,道具定价!$C:$F,4,0)*D61 -> 240 | F61: 体力药 | G61: 4 | H61: =VLOOKUP(F61,道具定价!$C:$F,4,0)*G61 -> 960 | I61: 传说装备兑换材料 | J61: 100 | K61: =_xlfn.IFNA(VLOOKUP(I61,道具定价!$C:$F,4,0)*J61,0) -> 1000 | L61: =H61+K61 -> 1960 | M61: =L61/E61 -> 8.1666667 | N61: 0
B62: 46 | C62: 金币 | D62: 30000 | E62: =VLOOKUP(C62,道具定价!$C:$F,4,0)*D62 -> 30 | F62: 金币 | G62: 120000 | H62: =VLOOKUP(F62,道具定价!$C:$F,4,0)*G62 -> 120 | K62: =_xlfn.IFNA(VLOOKUP(I62,道具定价!$C:$F,4,0)*J62,0) -> 0 | L62: =H62+K62 -> 120 | M62: =L62/E62 -> 4 | N62: 0
B63: 47 | C63: 角色经验高10000 | D63: 3 | E63: =VLOOKUP(C63,道具定价!$C:$F,4,0)*D63 -> 30 | F63: 角色经验高10000 | G63: 12 | H63: =VLOOKUP(F63,道具定价!$C:$F,4,0)*G63 -> 120 | K63: =_xlfn.IFNA(VLOOKUP(I63,道具定价!$C:$F,4,0)*J63,0) -> 0 | L63: =H63+K63 -> 120 | M63: =L63/E63 -> 4 | N63: 0
B64: 48 | C64: 专武经验高20000 | D64: 3 | E64: =VLOOKUP(C64,道具定价!$C:$F,4,0)*D64 -> 30 | F64: 专武经验高20000 | G64: 12 | H64: =VLOOKUP(F64,道具定价!$C:$F,4,0)*G64 -> 120 | K64: =_xlfn.IFNA(VLOOKUP(I64,道具定价!$C:$F,4,0)*J64,0) -> 0 | L64: =H64+K64 -> 120 | M64: =L64/E64 -> 4 | N64: 0
B65: 49 | C65: 主角装备经验 | D65: 3000 | E65: =VLOOKUP(C65,道具定价!$C:$F,4,0)*D65 -> 30 | F65: 主角装备经验 | G65: 12000 | H65: =VLOOKUP(F65,道具定价!$C:$F,4,0)*G65 -> 120 | K65: =_xlfn.IFNA(VLOOKUP(I65,道具定价!$C:$F,4,0)*J65,0) -> 0 | L65: =H65+K65 -> 120 | M65: =L65/E65 -> 4 | N65: 0
B66: 50 | C66: 钻石 | D66: 100 | E66: =VLOOKUP(C66,道具定价!$C:$F,4,0)*D66 -> 100 | F66: 角色抽卡券普通 | G66: 2 | H66: =VLOOKUP(F66,道具定价!$C:$F,4,0)*G66 -> 300 | I66: 专武抽卡券普通 | J66: 2 | K66: =_xlfn.IFNA(VLOOKUP(I66,道具定价!$C:$F,4,0)*J66,0) -> 300 | L66: =H66+K66 -> 600 | M66: =L66/E66 -> 6 | N66: =L66 -> 600
B67: 51 | C67: 金币 | D67: 30000 | E67: =VLOOKUP(C67,道具定价!$C:$F,4,0)*D67 -> 30 | F67: 金币 | G67: 120000 | H67: =VLOOKUP(F67,道具定价!$C:$F,4,0)*G67 -> 120 | K67: =_xlfn.IFNA(VLOOKUP(I67,道具定价!$C:$F,4,0)*J67,0) -> 0 | L67: =H67+K67 -> 120 | M67: =L67/E67 -> 4 | N67: 0
B68: 52 | C68: 角色经验高10000 | D68: 3 | E68: =VLOOKUP(C68,道具定价!$C:$F,4,0)*D68 -> 30 | F68: 角色经验高10000 | G68: 12 | H68: =VLOOKUP(F68,道具定价!$C:$F,4,0)*G68 -> 120 | K68: =_xlfn.IFNA(VLOOKUP(I68,道具定价!$C:$F,4,0)*J68,0) -> 0 | L68: =H68+K68 -> 120 | M68: =L68/E68 -> 4 | N68: 0
B69: 53 | C69: 专武经验高20000 | D69: 3 | E69: =VLOOKUP(C69,道具定价!$C:$F,4,0)*D69 -> 30 | F69: 专武经验高20000 | G69: 12 | H69: =VLOOKUP(F69,道具定价!$C:$F,4,0)*G69 -> 120 | K69: =_xlfn.IFNA(VLOOKUP(I69,道具定价!$C:$F,4,0)*J69,0) -> 0 | L69: =H69+K69 -> 120 | M69: =L69/E69 -> 4 | N69: 0
B70: 54 | C70: 主角装备经验 | D70: 3000 | E70: =VLOOKUP(C70,道具定价!$C:$F,4,0)*D70 -> 30 | F70: 主角装备经验 | G70: 12000 | H70: =VLOOKUP(F70,道具定价!$C:$F,4,0)*G70 -> 120 | K70: =_xlfn.IFNA(VLOOKUP(I70,道具定价!$C:$F,4,0)*J70,0) -> 0 | L70: =H70+K70 -> 120 | M70: =L70/E70 -> 4 | N70: 0
B71: 55 | C71: 史诗装备兑换材料 | D71: 15 | E71: =VLOOKUP(C71,道具定价!$C:$F,4,0)*D71 -> 30 | F71: 体力药 | G71: 4 | H71: =VLOOKUP(F71,道具定价!$C:$F,4,0)*G71 -> 960 | I71: 传说装备兑换材料 | J71: 100 | K71: =_xlfn.IFNA(VLOOKUP(I71,道具定价!$C:$F,4,0)*J71,0) -> 1000 | L71: =H71+K71 -> 1960 | M71: =L71/E71 -> 65.333333 | N71: 0
B72: 56 | C72: 金币 | D72: 30000 | E72: =VLOOKUP(C72,道具定价!$C:$F,4,0)*D72 -> 30 | F72: 金币 | G72: 120000 | H72: =VLOOKUP(F72,道具定价!$C:$F,4,0)*G72 -> 120 | K72: =_xlfn.IFNA(VLOOKUP(I72,道具定价!$C:$F,4,0)*J72,0) -> 0 | L72: =H72+K72 -> 120 | M72: =L72/E72 -> 4 | N72: 0
B73: 57 | C73: 角色经验高10000 | D73: 3 | E73: =VLOOKUP(C73,道具定价!$C:$F,4,0)*D73 -> 30 | F73: 角色经验高10000 | G73: 12 | H73: =VLOOKUP(F73,道具定价!$C:$F,4,0)*G73 -> 120 | K73: =_xlfn.IFNA(VLOOKUP(I73,道具定价!$C:$F,4,0)*J73,0) -> 0 | L73: =H73+K73 -> 120 | M73: =L73/E73 -> 4 | N73: 0
B74: 58 | C74: 专武经验高20000 | D74: 3 | E74: =VLOOKUP(C74,道具定价!$C:$F,4,0)*D74 -> 30 | F74: 专武经验高20000 | G74: 12 | H74: =VLOOKUP(F74,道具定价!$C:$F,4,0)*G74 -> 120 | K74: =_xlfn.IFNA(VLOOKUP(I74,道具定价!$C:$F,4,0)*J74,0) -> 0 | L74: =H74+K74 -> 120 | M74: =L74/E74 -> 4 | N74: 0
B75: 59 | C75: 主角装备经验 | D75: 3000 | E75: =VLOOKUP(C75,道具定价!$C:$F,4,0)*D75 -> 30 | F75: 主角装备经验 | G75: 12000 | H75: =VLOOKUP(F75,道具定价!$C:$F,4,0)*G75 -> 120 | K75: =_xlfn.IFNA(VLOOKUP(I75,道具定价!$C:$F,4,0)*J75,0) -> 0 | L75: =H75+K75 -> 120 | M75: =L75/E75 -> 4 | N75: 0
B76: 60 | C76: 钻石 | D76: 100 | E76: =VLOOKUP(C76,道具定价!$C:$F,4,0)*D76 -> 100 | F76: 钻石 | G76: 1000 | H76: =VLOOKUP(F76,道具定价!$C:$F,4,0)*G76 -> 1000 | I76: 传说装备兑换材料 | J76: 200 | K76: =_xlfn.IFNA(VLOOKUP(I76,道具定价!$C:$F,4,0)*J76,0) -> 2000 | L76: =H76+K76 -> 3000 | M76: =L76/E76 -> 30 | N76: =H76 -> 1000
B77: 61 | C77: 金币 | D77: 2000 | E77: =VLOOKUP(C77,道具定价!$C:$F,4,0)*D77 -> 2 | F77: 金币 | G77: 8000 | H77: =VLOOKUP(F77,道具定价!$C:$F,4,0)*G77 -> 8 | K77: =_xlfn.IFNA(VLOOKUP(I77,道具定价!$C:$F,4,0)*J77,0) -> 0 | L77: =H77+K77 -> 8 | M77: =L77/E77 -> 4 | N77: 0
B78: 62 | C78: 角色经验中2000 | D78: 1 | E78: =VLOOKUP(C78,道具定价!$C:$F,4,0)*D78 -> 2 | F78: 角色经验高10000 | G78: 1 | H78: =VLOOKUP(F78,道具定价!$C:$F,4,0)*G78 -> 10 | K78: =_xlfn.IFNA(VLOOKUP(I78,道具定价!$C:$F,4,0)*J78,0) -> 0 | L78: =H78+K78 -> 10 | M78: =L78/E78 -> 5 | N78: 0
B79: 63 | C79: 专武经验中4000 | D79: 1 | E79: =VLOOKUP(C79,道具定价!$C:$F,4,0)*D79 -> 2 | F79: 专武经验高20000 | G79: 1 | H79: =VLOOKUP(F79,道具定价!$C:$F,4,0)*G79 -> 10 | K79: =_xlfn.IFNA(VLOOKUP(I79,道具定价!$C:$F,4,0)*J79,0) -> 0 | L79: =H79+K79 -> 10 | M79: =L79/E79 -> 5 | N79: 0
B80: 64 | C80: 主角装备经验 | D80: 200 | E80: =VLOOKUP(C80,道具定价!$C:$F,4,0)*D80 -> 2 | F80: 主角装备经验 | G80: 800 | H80: =VLOOKUP(F80,道具定价!$C:$F,4,0)*G80 -> 8 | K80: =_xlfn.IFNA(VLOOKUP(I80,道具定价!$C:$F,4,0)*J80,0) -> 0 | L80: =H80+K80 -> 8 | M80: =L80/E80 -> 4 | N80: 0
B81: 65 | C81: 旅券经验 | D81: 200 | E81: =VLOOKUP(C81,道具定价!$C:$F,4,0)*D81 -> 2 | F81: 旅券经验 | G81: 800 | H81: =VLOOKUP(F81,道具定价!$C:$F,4,0)*G81 -> 8 | K81: =_xlfn.IFNA(VLOOKUP(I81,道具定价!$C:$F,4,0)*J81,0) -> 0 | L81: =H81+K81 -> 8 | M81: =L81/E81 -> 4 | N81: 0
B82: 66 | C82: 金币 | D82: 2000 | E82: =VLOOKUP(C82,道具定价!$C:$F,4,0)*D82 -> 2 | F82: 金币 | G82: 8000 | H82: =VLOOKUP(F82,道具定价!$C:$F,4,0)*G82 -> 8 | K82: =_xlfn.IFNA(VLOOKUP(I82,道具定价!$C:$F,4,0)*J82,0) -> 0 | L82: =H82+K82 -> 8 | M82: =L82/E82 -> 4 | N82: 0
B83: 67 | C83: 角色经验中2000 | D83: 1 | E83: =VLOOKUP(C83,道具定价!$C:$F,4,0)*D83 -> 2 | F83: 角色经验高10000 | G83: 1 | H83: =VLOOKUP(F83,道具定价!$C:$F,4,0)*G83 -> 10 | K83: =_xlfn.IFNA(VLOOKUP(I83,道具定价!$C:$F,4,0)*J83,0) -> 0 | L83: =H83+K83 -> 10 | M83: =L83/E83 -> 5 | N83: 0
B84: 68 | C84: 专武经验中4000 | D84: 1 | E84: =VLOOKUP(C84,道具定价!$C:$F,4,0)*D84 -> 2 | F84: 专武经验高20000 | G84: 1 | H84: =VLOOKUP(F84,道具定价!$C:$F,4,0)*G84 -> 10 | K84: =_xlfn.IFNA(VLOOKUP(I84,道具定价!$C:$F,4,0)*J84,0) -> 0 | L84: =H84+K84 -> 10 | M84: =L84/E84 -> 5 | N84: 0
B85: 69 | C85: 主角装备经验 | D85: 200 | E85: =VLOOKUP(C85,道具定价!$C:$F,4,0)*D85 -> 2 | F85: 主角装备经验 | G85: 800 | H85: =VLOOKUP(F85,道具定价!$C:$F,4,0)*G85 -> 8 | K85: =_xlfn.IFNA(VLOOKUP(I85,道具定价!$C:$F,4,0)*J85,0) -> 0 | L85: =H85+K85 -> 8 | M85: =L85/E85 -> 4 | N85: 0
B86: 70 | C86: 旅券经验 | D86: 200 | E86: =VLOOKUP(C86,道具定价!$C:$F,4,0)*D86 -> 2 | F86: 旅券经验 | G86: 800 | H86: =VLOOKUP(F86,道具定价!$C:$F,4,0)*G86 -> 8 | K86: =_xlfn.IFNA(VLOOKUP(I86,道具定价!$C:$F,4,0)*J86,0) -> 0 | L86: =H86+K86 -> 8 | M86: =L86/E86 -> 4 | N86: 0
B87: 71 | C87: 金币 | D87: 2000 | E87: =VLOOKUP(C87,道具定价!$C:$F,4,0)*D87 -> 2 | F87: 金币 | G87: 8000 | H87: =VLOOKUP(F87,道具定价!$C:$F,4,0)*G87 -> 8 | K87: =_xlfn.IFNA(VLOOKUP(I87,道具定价!$C:$F,4,0)*J87,0) -> 0 | L87: =H87+K87 -> 8 | M87: =L87/E87 -> 4 | N87: 0
B88: 72 | C88: 角色经验中2000 | D88: 1 | E88: =VLOOKUP(C88,道具定价!$C:$F,4,0)*D88 -> 2 | F88: 角色经验高10000 | G88: 1 | H88: =VLOOKUP(F88,道具定价!$C:$F,4,0)*G88 -> 10 | K88: =_xlfn.IFNA(VLOOKUP(I88,道具定价!$C:$F,4,0)*J88,0) -> 0 | L88: =H88+K88 -> 10 | M88: =L88/E88 -> 5 | N88: 0
